import java.util.Random;

public final class g
{
  private static byte an;
  static byte a;
  static byte b;
  private static int[][] ao;
  private static byte[][] ap;
  private static short aq;
  static int[] c;
  private static final int[][] ar;
  static x[] d;
  static i[] e;
  static k[] f;
  static c[] g;
  static t[] h;
  static q[] i;
  private static int[] as;
  private static int[] at;
  private static int[] au;
  static int j;
  private static byte av;
  static byte[] k;
  static byte[] l;
  private static byte aw;
  private static byte[] ax;
  private static short[] ay;
  private static byte[] az;
  static byte[] m;
  private static byte[] aA;
  private static short[] aB;
  static byte n;
  private static byte aC;
  private static int aD;
  static int[] o;
  static boolean p;
  static short[][] q;
  static final byte[] r;
  static int[] s;
  private static short aE;
  static int[] t;
  private static int aF;
  static int[] u;
  static boolean v;
  static short w;
  static e[] x;
  private static int[] aG;
  static int[] y;
  private static e[] aH;
  static byte z;
  static int A;
  private static int[] aI;
  static int[] B;
  static byte[] C;
  static byte[] D;
  static byte E;
  static byte F;
  static byte G;
  static final short[] H;
  static short[] I;
  private static int aJ;
  private static short[] aK;
  static boolean J;
  private static boolean[] aL;
  private static short[] aM;
  private static boolean[] aN;
  private static boolean[] aO;
  private static byte[] aP;
  private static byte[] aQ;
  static int[] K;
  private static byte[] aR = { 67, -14, 57, -14, 54, -14, 54, -16, 53, -17, 53, -18, 54, -16, 55, -15, 56, -13, 57, -12 };
  private static byte[] aS;
  private static byte[] aT;
  private static byte[] aU;
  static String[][] L;
  private static Random aV = new Random();
  private static byte aW;
  private static byte aX;
  private static byte aY;
  static byte M;
  private static int aZ;
  private static i ba;
  static short N;
  static int O;
  static int P;
  private static short[] bb;
  static byte[] Q;
  static int[][] R;
  private static int[] bc;
  static int[] S;
  private static short[] bd;
  private static int[][] be;
  private static short bf;
  static final int[] T;
  private static byte[] bg;
  private static byte[] bh;
  private static byte bi;
  static final int[] U;
  static byte[] V;
  static short[] W;
  private static short bj;
  static int X;
  static short Y;
  private static short bk;
  private static int bl;
  private static int bm;
  static int Z;
  private static int bn;
  static int aa;
  static int[] ab;
  private static int[] bo;
  private static int[] bp;
  private static int[] bq;
  private static int[] br;
  static int[][] ac;
  private static int bs;
  private static byte bt;
  private static byte[] bu;
  private static byte[] bv;
  private static byte[] bw;
  private static short[] bx;
  static short ad;
  private static byte[] by;
  private static byte bz;
  private static short[] bA;
  private static byte bB;
  private static byte bC;
  private static int bD;
  private static int[][] bE;
  private static short bF;
  static byte ae;
  private static short[] bG;
  static byte[][] af;
  static byte[][] ag;
  private static boolean bH;
  private static boolean bI;
  static short ah;
  static int[] ai;
  private static boolean bJ;
  private static byte bK;
  private static byte bL;
  static int aj;
  private static short[][] bM;
  static short ak;
  static short al;
  private static int bN;
  static short am;
  private static int bO;
  private static int bP;
  
  static
  {
    p = false;
    U = new int[] { 0, 0, 0, 0, 0, 0, 0, 0, 0, 0, 0, 0, 0, 0, 0, 0, 0, 0, 0, 0, 1, 0, 1, 0, 1, 0, 0, 1, 2, 0, 1, 2, 0, 1, 2, 0, 1, 2, 3, 0, 1, 2, 3, 0, 1, 1, 2, 3, 4, 0, 1, 2, 3, 4, 1, 2, 3, 4, 5, 0, 1, 2, 3, 1, 2, 3, 4, 5, 6, 0, 1, 2, 1, 2, 3, 4, 5, 6, 7, 0, 1, 1, 2, 3, 4, 5, 6, 7, 8, 0 };
    P = (O = 'ð') << '\020';
    T = new int[] { 126, 127, 120, 121 };
    be = new int[][] { { 0, 0, O }, { 0, -O, 126 }, { 0, O, 127 }, { O, 0, 120 }, { -O, 0, 121 } };
    X = 0;
    aF = 0;
    ar = new int[][] { { 3, 2, 1, 0 }, { 6, 6 }, { 4 }, { 5 }, { 8, 7 }, { 9 }, { 10 }, { 11 }, { 12 }, { 13 }, { 8, 8, 7, 7 } };
    aj = 0;
    bz = 0;
    aD = 0;
    v = false;
    r = new byte[] { 6, 4, 9, 2, 20, 4, 5 };
    by = new byte[] { 1, 0, 0, 0, 0, 0, 0 };
    l = new byte[] { 0, 0, 0, 0, 0, 0, 0 };
    k = new byte[] { 0, 0, 0, 0, 0, 0, 0 };
    aQ = new byte[] { 0, 9, 5, 30, 5, 10, 0 };
    aP = new byte[] { 0, 72, 50, 120, 30, 50, 0 };
    bh = new byte[] { 0, 7, 11, 4, 6, 7, 0 };
    bt = 0;
    bB = 0;
    bC = 0;
    bA = new short[] { 128, 256, 256, 256, 256, 256, 256, 256, 256, 256, 256, 256, 256, 256 };
    new short[] { 128, 128, 150, 180, 200, 200, 220, 220, 256, 240, 0, 130, 70 }[13] = '';
    bd = new short[] { 70, 0, 70, 0, 70, 0, 90, 40, 100, 80, 150, 255, 150, 255, 150, 255, 200, 255, 200, 255, 200, 255, 200, 255, 200, 255, 150, 255, 150, 255, 150, 200, 150, 150, 90, 80, 80, 0, 70, 0 };
    aB = new short[] { 120, 10, 120, 20, 120, 30, 140, 40, 160, 80, 150, 255, 150, 255, 150, 255, 200, 255, 200, 255, 200, 255, 200, 255, 200, 255, 150, 255, 150, 255, 170, 200, 170, 150, 160, 80, 140, 10, 120, 10 };
    new byte[] { 5, 5, 5, 5, 5 }[5] = 5;
    bv = new byte[] { 2, 6, 6, 9, 9, 6, 6, 2, 2 };
    ay = new short[] { 128, 256, 64, 200, 0, 256, 230, 256, 256, 256 };
    ax = new byte[] { 0, 2, 2, 2, 1 };
    bK = 0;
    bL = 4;
    bk = 0;
    J = false;
    bw = new byte[] { 8, 10, 10, 11, 8 };
    new int[] { 0, 16776960, 16776960, 16776960, 16776960, 255 }[6] = 0;
    bx = new short[] { 2, 8, 7, 6, 70, 8, 2 };
    bu = new byte[] { 20, 20, 30, 20, 120, 60, Byte.MAX_VALUE };
    H = new short[] { 100, 100, 100, 1024, 80, 2000, 100, 2500 };
    az = new byte[] { 0, 70, 70, 0, 0, 0, 0, 0 };
    ak = 255;
    b = 0;
    E = 0;
    aX = 0;
    aW = 0;
    as = new int[] { 1999599360 };
    at = new int[] { 796209152 };
    au = new int[] { 1718616064 };
    aM = new short[] { 3290, 63886, 135, 1050, 4790, 3430, 1050, 64346, 4642, 1050, 2390, 5857, 3590, 300, 7049, 750, 2690, 9142, 64786, 2690, 9142, 62846, 750, 9142, 64786, 62846, 9125, 1050, 62581, 9137, 2840, 64336, 9149, 750, 2690, 10055, 64786, 2690, 10055, 62846, 750, 10055, 64786, 62846, 10038, 1050, 62581, 10050 };
    aq = 0;
    ae = 0;
    z = -1;
    new short[] { 62638, 1500, 64636, 4037, 900, 4039, 5285, 64036, 2700 }[9] = '';
    new short[] { 2100, 63736, 3600, 0, 0 }[5] = 'ל';
    F = -1;
    bm = 0;
    bl = 0;
    bH = false;
    bI = false;
    aw = 1;
    aE = 490;
    bp = new int[] { 119, 176, 119, 174, 119, 176, 123, 176, 120, 178, 123, 178, 126, 178, 122, 178 };
    br = new int[] { 66, 183, 69, 182, 71, 181, 74, 177, 68, 183, 72, 180, 74, 179, 66, 182 };
    bo = new int[] { 51, 176, 55, 177, 59, 176, 62, 175, 56, 178, 59, 177, 64, 175, 55, 178 };
    bq = new int[] { 56, 12124160, 59, 12124160, 62, 12058624, 65, 11993088, 58, 12124160, 62, 11993088, 65, 11927552, 59, 12124160 };
    aT = new byte[] { 53, 53, 50, 48, 46, 46, 48, 52, 56, 58 };
    aS = new byte[] { 110, -5, 110, -5, 109, -7, 109, -9, 109, -8, 111, -4, 111, -2, 111, -2, 111, -2, 111, -5 };
    aU = new byte[] { 85, -15, 75, -15, 74, -15, 73, -17, 73, -18, 73, -18, 75, -18, 78, -16, 81, -15, 82, -13 };
  }
  
  private static void a(e parame, short paramShort)
  {
    for (int i4 = w.g ? 1 : 0; i4 < ah; i4++)
    {
      q localq;
      if (((localq = i[i4]).N) && (localq.M <= 2))
      {
        int i1 = localq.w - parame.j >> 16;
        int i2 = localq.x - parame.k >> 16;
        int i3 = localq.y - parame.l >> 16;
        if (((i1 = i1 * i1 + i2 * i2 + i3 * i3) < 250000) && (r.a(i[i4], parame, paramShort)))
        {
          q tmp116_115 = localq;
          tmp116_115.s = ((short)(tmp116_115.s - (250000 - i1 >> 10)));
          if (localq.s < 0)
          {
            localq.k = true;
            localq.L = 7;
            if ((parame.j - localq.w >> 16) * localq.E[0] + (parame.k - localq.x >> 16) * localq.E[1] < 0) {
              localq.L = 8;
            }
            if (localq.M == 2) {
              localq.L = 6;
            }
            localq.j = 0;
            a(localq, true);
          }
        }
      }
    }
  }
  
  public static final void a(int paramInt1, int paramInt2, int paramInt3, byte paramByte, short paramShort)
  {
    if (bF >= 15) {
      return;
    }
    int[][] arrayOfInt = bE;
    int i1 = 0;
    bF = (short)(bF + 1);
    for (;;)
    {
      if (arrayOfInt[i1][4] <= 0)
      {
        arrayOfInt[i1][0] = paramInt1;
        arrayOfInt[i1][1] = paramInt2;
        arrayOfInt[i1][2] = paramInt3;
        arrayOfInt[i1][3] = paramByte;
        arrayOfInt[i1][4] = (ar[paramByte].length + 1);
        arrayOfInt[i1][5] = paramShort;
        return;
      }
      i1++;
    }
  }
  
  public static final void a()
  {
    int[][] arrayOfInt = ac;
    for (int i1 = 49; i1 >= 0; i1--)
    {
      int[] arrayOfInt1;
      if ((arrayOfInt1 = arrayOfInt[i1])[6] != 0)
      {
        arrayOfInt1[6] -= 1;
        if (arrayOfInt1[6] == 0)
        {
          ad = (short)(ad - 1);
        }
        else
        {
          int i6;
          Object localObject1;
          int i19;
          int[] arrayOfInt2;
          c localc1;
          int i16;
          if (arrayOfInt1[9] <= 63536)
          {
            if ((arrayOfInt1 = arrayOfInt1)[8] != 0)
            {
              int[] arrayOfInt5 = c;
              int i2 = arrayOfInt1[7];
              int i10 = arrayOfInt1[3] * arrayOfInt1[8];
              int i12 = arrayOfInt1[4] * arrayOfInt1[8];
              int i21 = arrayOfInt1[5] * arrayOfInt1[8];
              int i3 = i10 >> 16;
              int i4 = i12 >> 16;
              i6 = i21 >> 16;
              i21 -= 1048576;
              arrayOfInt1[10] += 20;
              if (arrayOfInt1[10] > 359) {
                arrayOfInt1[10] -= 359;
              }
              arrayOfInt1[11] += 20;
              if (arrayOfInt1[11] > 359) {
                arrayOfInt1[11] -= 359;
              }
              int i7 = i3 * i3 + i4 * i4 + i6 * i6;
              i6 = 1073741824;
              i4 = 0;
              while (i6 != 0)
              {
                i3 = i4 | i6;
                i4 >>= 1;
                if (i7 >= i3)
                {
                  i7 -= i3;
                  i4 |= i6;
                }
                i6 >>= 2;
              }
              if (i4 > 100) {
                i4 = 100;
              }
              int i22 = o[i4];
              arrayOfInt1[3] = ((int)(i10 * i22 >> 16));
              arrayOfInt1[4] = ((int)(i12 * i22 >> 16));
              arrayOfInt1[5] = ((int)(i21 * i22 >> 16));
              if (i4 > 100) {
                arrayOfInt1[8] = 100;
              } else {
                arrayOfInt1[8] = i4;
              }
              i22 = arrayOfInt1[8];
              i3 = arrayOfInt1[0] + arrayOfInt1[3] * i22;
              i4 = arrayOfInt1[1] + arrayOfInt1[4] * i22;
              i6 = arrayOfInt1[2] + arrayOfInt1[5] * i22;
              c localc2;
              int[] arrayOfInt4 = (localc2 = g[i2]).j;
              localObject1 = localc2.a;
              for (i12 = arrayOfInt4.length - 2; i12 >= 0; i12 -= 2)
              {
                i10 = arrayOfInt4[i12];
                i19 = arrayOfInt4[(i12 + 1)];
                long l2;
                if ((l2 = ((i3 >> 16) - localObject1[i19]) * arrayOfInt5[i10] + ((i4 >> 16) - localObject1[(i19 + 1)]) * arrayOfInt5[(i10 + 1)] + ((i6 >> 16) - localObject1[(i19 + 2)]) * arrayOfInt5[(i10 + 2)]) < 0L)
                {
                  i3 = (int)(i3 + -(l2 >> 16) * arrayOfInt5[i10]);
                  i4 = (int)(i4 + -(l2 >> 16) * arrayOfInt5[(i10 + 1)]);
                  i6 = (int)(i6 + -(l2 >> 16) * arrayOfInt5[(i10 + 2)]);
                  l2 = arrayOfInt5[i10] * arrayOfInt1[3] + arrayOfInt5[(i10 + 1)] * arrayOfInt1[4] + arrayOfInt5[(i10 + 2)] * arrayOfInt1[5] >> 16 << 1;
                  int tmp621_620 = 3;
                  int[] tmp621_619 = arrayOfInt1;
                  tmp621_619[tmp621_620] = ((int)(tmp621_619[tmp621_620] - (arrayOfInt5[i10] * l2 >> 16)));
                  int tmp641_640 = 4;
                  int[] tmp641_639 = arrayOfInt1;
                  tmp641_639[tmp641_640] = ((int)(tmp641_639[tmp641_640] - (arrayOfInt5[(i10 + 1)] * l2 >> 16)));
                  int tmp663_662 = 5;
                  int[] tmp663_661 = arrayOfInt1;
                  tmp663_661[tmp663_662] = ((int)(tmp663_661[tmp663_662] - (arrayOfInt5[(i10 + 2)] * l2 >> 16)));
                  if (arrayOfInt1[9] > 63516) {
                    arrayOfInt1[8] = 0;
                  } else {
                    arrayOfInt1[8] >>= 1;
                  }
                }
              }
              int[] arrayOfInt3;
              if (arrayOfInt1[8] < 3)
              {
                arrayOfInt2 = arrayOfInt1;
                arrayOfInt4 = c;
                arrayOfInt3 = (localc1 = g[arrayOfInt2[7]]).j;
                localObject1 = localc1.a;
                for (i16 = arrayOfInt3.length - 2; i16 >= 0; i16 -= 2)
                {
                  i6 = arrayOfInt3[i16];
                  int i14 = arrayOfInt3[(i16 + 1)];
                  long l3;
                  if ((l3 = ((arrayOfInt2[0] >> 16) - localObject1[i14]) * arrayOfInt4[i6] + ((arrayOfInt2[1] >> 16) - localObject1[(i14 + 1)]) * arrayOfInt4[(i6 + 1)] + ((arrayOfInt2[2] >> 16) - localObject1[(i14 + 2)]) * arrayOfInt4[(i6 + 2)]) <= 0L)
                  {
                    int tmp863_862 = 0;
                    int[] tmp863_860 = arrayOfInt2;
                    tmp863_860[tmp863_862] = ((int)(tmp863_860[tmp863_862] + (-l3 * arrayOfInt4[i6] >> 16)));
                    int tmp885_884 = 1;
                    int[] tmp885_882 = arrayOfInt2;
                    tmp885_882[tmp885_884] = ((int)(tmp885_882[tmp885_884] + (-l3 * arrayOfInt4[(i6 + 1)] >> 16)));
                    int tmp909_908 = 2;
                    int[] tmp909_906 = arrayOfInt2;
                    tmp909_906[tmp909_908] = ((int)(tmp909_906[tmp909_908] + (-l3 * arrayOfInt4[(i6 + 2)] >> 16)));
                  }
                }
                h.a(arrayOfInt1);
                arrayOfInt1[8] = 0;
              }
              else
              {
                arrayOfInt1[0] = arrayOfInt2;
                arrayOfInt1[1] = arrayOfInt3;
                arrayOfInt1[2] = i6;
              }
            }
          }
          else
          {
            arrayOfInt1 = arrayOfInt1;
            localObject1 = c;
            e[] arrayOfe = x;
            int i5;
            Object localObject4;
            int i8;
            if ((i16 = arrayOfInt1[9]) > 1)
            {
              if (i16 == 2)
              {
                if ((i5 = (arrayOfInt1[11] >> 16 & 0xFF) - 20) < 0) {
                  i5 = 0;
                }
                if ((i6 = (arrayOfInt1[11] >> 8 & 0xFF) - 20) < 0) {
                  i6 = 0;
                }
                arrayOfInt1[11] = (i5 << 16 | i6 << 8);
                arrayOfInt1[5] -= 524288;
              }
              arrayOfInt1[5] -= 524288;
              arrayOfInt2 = (localc1 = g[arrayOfInt1[7]]).j;
              localObject4 = localc1.a;
              for (i8 = arrayOfInt2.length - 2; i8 >= 0; i8 -= 2)
              {
                i5 = arrayOfInt2[i8];
                i6 = arrayOfInt2[(i8 + 1)];
                long l1;
                if ((l1 = ((arrayOfInt1[0] >> 16) - localObject4[i6]) * localObject1[i5] + ((arrayOfInt1[1] >> 16) - localObject4[(i6 + 1)]) * localObject1[(i5 + 1)] + ((arrayOfInt1[2] >> 16) - localObject4[(i6 + 2)]) * localObject1[(i5 + 2)]) <= 0L)
                {
                  int tmp1200_1199 = 0;
                  int[] tmp1200_1198 = arrayOfInt1;
                  tmp1200_1198[tmp1200_1199] = ((int)(tmp1200_1198[tmp1200_1199] + (-l1 * localObject1[i5] >> 16)));
                  int tmp1220_1219 = 1;
                  int[] tmp1220_1218 = arrayOfInt1;
                  tmp1220_1218[tmp1220_1219] = ((int)(tmp1220_1218[tmp1220_1219] + (-l1 * localObject1[(i5 + 1)] >> 16)));
                  int tmp1242_1241 = 2;
                  int[] tmp1242_1240 = arrayOfInt1;
                  tmp1242_1240[tmp1242_1241] = ((int)(tmp1242_1240[tmp1242_1241] + (-l1 * localObject1[(i5 + 2)] >> 16)));
                }
              }
            }
            int i11;
            int i20;
            if ((i16 <= 1) || (i16 == 64512))
            {
              i8 = (localObject1 = arrayOfInt1)[9];
              localObject4 = x;
              i19 = localObject1[8] & 0xFF;
              if (i8 != -2)
              {
                (localc1 = localObject4[0]).j = (localObject1[0] >> 16);
                localc1.k = (localObject1[1] >> 16);
                localc1.l = (localObject1[2] >> 16);
                localc1.a = (localObject1[3] >> i19);
                localc1.b = (localObject1[4] >> i19);
                localc1.c = (localObject1[5] >> i19);
                (localc1 = localObject4[1]).j = (localObject1[0] + localObject1[3] >> 16);
                localc1.k = (localObject1[1] + localObject1[4] >> 16);
                localc1.l = (localObject1[2] + localObject1[5] >> 16);
                (localc1 = localObject4[2]).j = 0;
                localc1.k = 0;
                localc1.l = 0;
              }
              1;
              Object localObject3 = arrayOfe;
              localObject1 = arrayOfInt1;
              i11 = 0;
              localObject4 = i;
              e locale3 = localObject3[2];
              e locale4 = localObject3[0];
              arrayOfInt2 = localObject3[1];
              i5 = localObject1[8] >> 8 & 0xFF;
              bj = (short)localObject1[7];
              int i15;
              if (localObject1[9] == -2) {
                i15 = localObject1[8] & 0xFF;
              } else {
                i15 = 1 << (localObject1[8] & 0xFF);
              }
              bf = -1;
              label3317:
              do
              {
                e locale1 = (localObject5 = localObject3)[0];
                e locale2 = localObject5[1];
                Object localObject2 = localObject5[3];
                i[] arrayOfi = e;
                int i23 = -1;
                int i24 = -1;
                locale1.j <<= 16;
                locale1.k <<= 16;
                locale1.l <<= 16;
                locale2.j <<= 16;
                locale2.k <<= 16;
                locale2.l <<= 16;
                ((e)localObject2).j = locale2.j;
                ((e)localObject2).k = locale2.k;
                ((e)localObject2).l = locale2.l;
                for (int i25 = 0; i25 < arrayOfi.length; i25++)
                {
                  i locali2;
                  if (((locali2 = arrayOfi[i25]).t) && (locali2.s != 31)) {
                    if (i24 == -1)
                    {
                      if ((i24 = h.a((e)localObject2, locale1, locale2, locali2)) != -1) {
                        i23 = i25;
                      }
                    }
                    else if (h.a((e)localObject2, locale1, locale2, locali2) != -1) {
                      i23 = i25;
                    }
                  }
                }
                if (i24 >= 0)
                {
                  locale2.j = ((e)localObject2).j;
                  locale2.k = ((e)localObject2).k;
                  locale2.l = ((e)localObject2).l;
                }
                locale1.j >>= 16;
                locale1.k >>= 16;
                locale1.l >>= 16;
                locale2.j >>= 16;
                locale2.k >>= 16;
                locale2.l >>= 16;
                localObject2 = i23;
                for (int i17 = 0; i17 < ah; i17++) {
                  if (((locale2 = localObject4[i17]).B == bj) && (!locale2.k) && (i5 != i17) && ((locale2.N) || (locale2.m == 0)))
                  {
                    locale3.j = (locale2.w >> 16);
                    locale3.k = (locale2.x >> 16);
                    locale3.l = (locale2.y >> 16);
                    locale3.m = i15;
                    if (h.a(locale3, h.b[locale2.M], locale4, arrayOfInt2))
                    {
                      i11 = 1;
                      localObject2 = i17;
                    }
                  }
                }
                if (i11 != 0)
                {
                  arrayOfInt2.j <<= 16;
                  arrayOfInt2.k <<= 16;
                  arrayOfInt2.l <<= 16;
                  if (localObject4[localObject2].M != 3) {
                    for (int i9 = 0; i9 < 4; i9++) {
                      a(arrayOfInt2.j, arrayOfInt2.k, arrayOfInt2.l, bj);
                    }
                  } else {
                    for (i11 = 0; i11 < 4; i11++) {
                      b(arrayOfInt2.j, arrayOfInt2.k, arrayOfInt2.l, bj);
                    }
                  }
                  if (localObject1[9] == 1)
                  {
                    a(arrayOfInt2.j, arrayOfInt2.k, arrayOfInt2.l, (byte)0, bj);
                    a(arrayOfInt2, bj);
                  }
                  else
                  {
                    if ((localObject1[10] & 0xFF) == 4) {
                      a(arrayOfInt2.j, arrayOfInt2.k, arrayOfInt2.l, (byte)0, bj);
                    }
                    if (localObject2 == 0) {
                      a(arrayOfInt2.j, arrayOfInt2.k, arrayOfInt2.l, (byte)4, bj);
                    }
                  }
                  ad = (short)(ad - 1);
                  localObject1[6] = 0;
                  if (!localObject4[localObject2].k)
                  {
                    localObject2 = arrayOfInt2;
                    localObject6 = localObject1;
                    localObject5 = localObject4[localObject2];
                    if (!v.a)
                    {
                      i17 = localObject6[10] >> 8 & 0xFF;
                      if ((r.a == 2) && (((q)localObject5).M != 0)) {
                        i17 += 5;
                      } else {
                        i17 += Math.abs(aV.nextInt() & 0xF) + 1;
                      }
                      if ((i20 = localObject6[8] >> 8 & 0xFF) != 127)
                      {
                        if (!i[i20].k)
                        {
                          tmp2396_2395 = i[i20];
                          tmp2396_2395.u = ((byte)(tmp2396_2395.u - 1));
                        }
                        if (((((q)localObject5).n == 0) && (i[i20].M == 1) && (i[i20].K < 3)) || (i[i20].K == ((q)localObject5).K))
                        {
                          tmp2463_2462 = i[i20];
                          tmp2463_2462.u = ((byte)(tmp2463_2462.u + 1));
                          i17 >>= 2;
                        }
                        if ((((q)localObject5).M == i[i20].M) && (((q)localObject5).K == i[i20].K))
                        {
                          tmp2519_2518 = i[i20];
                          tmp2519_2518.u = ((byte)(tmp2519_2518.u + 1));
                        }
                      }
                      switch (((q)localObject5).M)
                      {
                      case 0: 
                        s.h();
                        if (!w.g) {
                          if (r.a == 0) {
                            i17 >>= 2;
                          } else {
                            i17 >>= 1;
                          }
                        }
                        break;
                      case 1: 
                      case 2: 
                        if (((e)localObject2).l - ((q)localObject5).y > 6225920)
                        {
                          if (((q)localObject5).n != 0)
                          {
                            s.b(300);
                            ((q)localObject5).s = -1;
                          }
                          else
                          {
                            tmp2635_2633 = localObject5;
                            tmp2635_2633.s = ((short)(tmp2635_2633.s - (i17 << 1)));
                          }
                          a(((e)localObject2).j, ((e)localObject2).k, ((e)localObject2).l, ((q)localObject5).B, (byte)0);
                          a(((e)localObject2).j, ((e)localObject2).k, ((e)localObject2).l, ((q)localObject5).B, (byte)0);
                        }
                        else
                        {
                          tmp2701_2699 = localObject5;
                          tmp2701_2699.s = ((short)(tmp2701_2699.s - i17));
                        }
                        if ((i20 == 0) && (((q)localObject5).K > 2)) {
                          s.b(i17);
                        }
                        a(((e)localObject2).j, ((e)localObject2).k, ((e)localObject2).l, ((q)localObject5).B, (byte)0);
                        if (((q)localObject5).s <= 0)
                        {
                          ((q)localObject5).k = true;
                          ((q)localObject5).L = 7;
                          if ((((q)localObject5).M == 1) && ((((e)localObject2).j - ((q)localObject5).w >> 16) * localObject5.E[0] + (((e)localObject2).k - ((q)localObject5).x >> 16) * localObject5.E[1] < 0)) {
                            ((q)localObject5).L = 8;
                          }
                          if (((q)localObject5).M == 2) {
                            ((q)localObject5).L = 6;
                          }
                          ((q)localObject5).j = 0;
                          if (localObject6[10] != 20) {
                            a((q)localObject5, true);
                          }
                          a((q)localObject5);
                          if (((q)localObject5).n == 0)
                          {
                            z = -1;
                            w.n = 2;
                          }
                        }
                        else if ((i20 != 127) && (((q)localObject5).n != 0))
                        {
                          if (((q)localObject5).l == -1)
                          {
                            if (((q)localObject5).K != i[i20].K)
                            {
                              ((q)localObject5).a = 2;
                              ((q)localObject5).l = ((byte)i20);
                              ((q)localObject5).d = 30;
                            }
                            break label3317;
                          }
                          if ((((q)localObject5).K != i[i20].K) && (Math.abs(i[i20].w - ((q)localObject5).w) + Math.abs(i[i20].x - ((q)localObject5).x) <= Math.abs(i[localObject5.l].w - ((q)localObject5).w) + Math.abs(i[localObject5.l].x - ((q)localObject5).x)))
                          {
                            ((q)localObject5).a = 2;
                            ((q)localObject5).l = ((byte)i20);
                            ((q)localObject5).d = 30;
                          }
                        }
                        break;
                      case 3: 
                        if ((((q)localObject5).m != -1) && (i[localObject5.m].n != 0))
                        {
                          tmp3117_3115 = localObject5;
                          tmp3117_3115.s = ((short)(tmp3117_3115.s - (i17 << 3)));
                        }
                        else
                        {
                          tmp3135_3133 = localObject5;
                          tmp3135_3133.s = ((short)(tmp3135_3133.s - (i17 >> 1)));
                        }
                        if (((q)localObject5).s <= 0)
                        {
                          ((q)localObject5).k = true;
                          ((q)localObject5).N = true;
                          if (((q)localObject5).m != -1)
                          {
                            (localObject2 = i[localObject5.m]).m = -1;
                            ((q)localObject2).N = true;
                            ((q)localObject2).k = true;
                            ((q)localObject2).s = 0;
                            ((q)localObject2).L = 7;
                            ((q)localObject2).j = 0;
                          }
                          a(((q)localObject5).w, ((q)localObject5).x, ((q)localObject5).y, (byte)0, ((q)localObject5).B);
                          ((q)localObject5).m = -1;
                          ((q)localObject5).f = h[4].b;
                          ((q)localObject5).e = h[4].a;
                          ((q)localObject5).v = h[4].c;
                          ((q)localObject5).M = 4;
                          ((q)localObject5).L = 1;
                          ((q)localObject5).j = -1;
                          ((q)localObject5).h = 0;
                        }
                        break;
                      }
                    }
                  }
                  break;
                }
                if (localObject2 != -1)
                {
                  localObject2 = arrayOfInt2;
                  localObject6 = localObject2;
                  localObject5 = localObject1;
                  i locali1 = e[localObject6];
                  localObject2.j <<= 16;
                  localObject2.k <<= 16;
                  localObject2.l <<= 16;
                  if ((locali1.s == 0) && (!v.a))
                  {
                    a(((e)localObject2).j, ((e)localObject2).k, ((e)localObject2).l, (byte)0, locali1.q);
                    locali1.t = false;
                    a((e)localObject2, locali1.q);
                    a((byte)localObject6);
                    break;
                  }
                  if (locali1.s != 9)
                  {
                    for (i20 = 0; i20 < 4; i20++) {
                      b(((e)localObject2).j, ((e)localObject2).k, ((e)localObject2).l, locali1.q);
                    }
                    a(((e)localObject2).j, ((e)localObject2).k, ((e)localObject2).l, (byte)((localObject5[10] & 0xFF) == 4 ? 0 : 1), locali1.q);
                    if (localObject5[9] == 1)
                    {
                      a(((e)localObject2).j, ((e)localObject2).k, ((e)localObject2).l, (byte)0, locali1.q);
                      a((e)localObject2, locali1.q);
                    }
                    ad = (short)(ad - 1);
                    localObject5[6] = 0;
                    break;
                  }
                  a((byte)localObject6);
                  locali1.t = false;
                  a(((e)localObject2).j, ((e)localObject2).k, ((e)localObject2).l, locali1.q, (byte)3);
                  a(((e)localObject2).j + 3276800, ((e)localObject2).k + 1310720, ((e)localObject2).l, locali1.q, (byte)3);
                  a(((e)localObject2).j - 3276800, ((e)localObject2).k + 2621440, ((e)localObject2).l, locali1.q, (byte)3);
                  a(((e)localObject2).j - 1966080, ((e)localObject2).k + 5242880, ((e)localObject2).l, locali1.q, (byte)3);
                  a(((e)localObject2).j - 3276800, ((e)localObject2).k - 3276800, ((e)localObject2).l, locali1.q, (byte)3);
                  a(((e)localObject2).j - 2621440, ((e)localObject2).k - 2621440, ((e)localObject2).l, locali1.q, (byte)3);
                  ad = (short)(ad - 1);
                  localObject5[6] = 0;
                  break;
                }
                localObject2 = arrayOfInt2;
                Object localObject6 = locale4;
                Object localObject5 = localObject1;
                localObject6.j <<= 16;
                localObject6.k <<= 16;
                localObject6.l <<= 16;
                localObject2.j <<= 16;
                localObject2.k <<= 16;
                localObject2.l <<= 16;
                if (f[bf].c == bj) {
                  bj = f[bf].d;
                } else {
                  bj = f[bf].c;
                }
                localObject6.j >>= 16;
                localObject6.k >>= 16;
                localObject6.l >>= 16;
                localObject2.j >>= 16;
                localObject2.k >>= 16;
                localObject2.l >>= 16;
                localObject5[7] = bj;
                if (h.a(bj, (e)localObject6, (e)localObject2) != -1)
                {
                  for (int i18 = 0; i18 < 4; i18++) {
                    b(((e)localObject2).j, ((e)localObject2).k, ((e)localObject2).l, bj);
                  }
                  a(((e)localObject2).j, ((e)localObject2).k, ((e)localObject2).l, (byte)((localObject5[10] & 0xFF) == 4 ? 0 : 1), bj);
                  if (localObject5[9] == 1)
                  {
                    a(((e)localObject2).j, ((e)localObject2).k, ((e)localObject2).l, (byte)0, bj);
                    a((e)localObject2, bj);
                  }
                  ad = (short)(ad - 1);
                  localObject5[6] = 0;
                }
              } while (((bf = (short)h.a(bj, (e)localObject6, (e)localObject2, bf)) != -1 ? 1 : 0) != 0);
            }
            if (arrayOfInt1[9] != 1)
            {
              arrayOfInt1[0] += arrayOfInt1[3];
              arrayOfInt1[1] += arrayOfInt1[4];
              arrayOfInt1[2] += arrayOfInt1[5];
            }
            else
            {
              localObject1 = arrayOfInt1;
              q localq;
              (localq = i[(localObject1[8] >> 8 & 0xFF)]).C = ((short)(localObject1[11] >> 16));
              localq.D = ((short)localObject1[11]);
              i11 = localq.w;
              int i13 = localq.x;
              i20 = localq.y;
              localq.w = localObject1[0];
              localq.x = localObject1[1];
              localq.y = localObject1[2];
              r.a(localq, localq.H, localq.I, 10);
              r.b(localq, localq.H, localq.I, localq.J, 10);
              localObject1[11] = (localq.C << 16 | localq.D);
              int i26 = localObject1[8] & 0xFF;
              localObject1[3] = ((int)(-h.d[localq.D] * -h.d[localq.C] >> 16) << i26);
              localObject1[4] = ((int)(-h.a[localq.D] * -h.d[localq.C] >> 16) << i26);
              localObject1[5] = (-h.a[localq.C] << i26);
              localObject1[0] += localObject1[3];
              localObject1[1] += localObject1[4];
              localObject1[2] += localObject1[5];
              localq.w = i11;
              localq.x = i13;
              localq.y = i20;
            }
          }
        }
      }
    }
  }
  
  public static final void b()
  {
    int[][] arrayOfInt = bE;
    int i1 = 0;
    int i2 = 0;
    while (i1 < bF) {
      if (arrayOfInt[i2][4] <= 0)
      {
        i2++;
      }
      else
      {
        arrayOfInt[i2][4] -= 1;
        if (arrayOfInt[i2][4] <= 0)
        {
          bF = (short)(bF - 1);
        }
        else
        {
          i1++;
          i2++;
        }
      }
    }
  }
  
  private static void a(byte paramByte)
  {
    for (int i1 = 2; i1 >= 0; i1--) {
      C[(i1 + 1)] = C[i1];
    }
    C[0] = paramByte;
  }
  
  static final void c()
  {
    q localq1 = i[0];
    Object localObject1;
    if (z != -1)
    {
      localObject1 = e[z];
      ab[0] = ((i)localObject1).l;
      ab[1] = ((i)localObject1).m;
      ab[2] = ((i)localObject1).n;
      h.a();
      if (bm > 0) {
        if (bH) {
          bm -= 1;
        } else if ((bm = bm - 8) < 0) {
          bm = 0;
        }
      }
      if (bm < 0) {
        if (bH) {
          bm += 1;
        } else if ((bm = bm + 8) > 0) {
          bm = 0;
        }
      }
      if (bl > 0) {
        if (bI) {
          bl -= 1;
        } else if ((bl = bl - 8) < 0) {
          bl = 0;
        }
      }
      if (bl < 0) {
        if (bI) {
          bl += 1;
        } else if ((bl = bl + 8) > 0) {
          bl = 0;
        }
      }
      if (!v.a)
      {
        localObject1.p += bm;
        Z += bl;
      }
      if (((i)localObject1).p < 0) {
        localObject1.p += 360;
      }
      if (((i)localObject1).p > 359) {
        localObject1.p -= 360;
      }
      if (Z > 329) {
        Z = 329;
      }
      if (Z < 210) {
        Z = 210;
      }
      bH = false;
      bI = false;
      aa = ((i)localObject1).p;
      return;
    }
    if (localq1.m != -1)
    {
      localq1 = i[localq1.m];
      q localq3 = localq1;
      (localObject1 = i[0]).w = localq3.w;
      ((q)localObject1).x = localq3.x;
      ((q)localObject1).y = localq3.y;
      ((q)localObject1).B = localq3.B;
    }
    if (!v.a)
    {
      int i3;
      if (!localq1.k)
      {
        X = localq1.B;
        localq1.P = true;
        localq1.O = ((byte)aj);
        localq1.E[0] = (-h.d[aa]);
        localq1.E[1] = (-h.a[aa]);
        localq1.D = ((short)aa);
        localq1.C = ((short)Z);
        ab[0] = localq1.w;
        ab[1] = localq1.x;
        ab[2] = (localq1.y + 4587520);
      }
      else
      {
        localObject1 = localq1;
        localq1.P = true;
        ((q)localObject1).O = ((byte)aj);
        ((q)localObject1).D = ((short)aa);
        ((q)localObject1).C = ((short)Z);
        if ((Math.abs(aE) >= 500) || (Math.abs(aE) <= 200)) {
          aw = (byte)-aw;
        }
        aE = (short)(aE + aw * 10);
        if (((q)localObject1).h == 20)
        {
          ab[0] = (((q)localObject1).w - localObject1.E[0] * 160 + h.d[aa] * aE);
          ab[1] = (((q)localObject1).x - localObject1.E[1] * 160 + h.a[aa] * aE);
          ab[2] = (((q)localObject1).y + 4587520);
        }
        else
        {
          ab[0] = (((q)localObject1).w + localObject1.E[0] * 200 + h.d[aa] * aE);
          ab[1] = (((q)localObject1).x + localObject1.E[1] * 200 + h.a[aa] * aE);
          ab[2] = (((q)localObject1).y + 4587520);
        }
        int i2 = ((q)localObject1).w;
        int i1 = ((q)localObject1).x;
        i3 = ((q)localObject1).y - h.e[0];
        ((q)localObject1).w = ab[0];
        ((q)localObject1).x = ab[1];
        ((q)localObject1).y = ab[2];
        r.b((q)localObject1, i2, i1, i3, 20);
        ((q)localObject1).w = i2;
        ((q)localObject1).x = i1;
        ((q)localObject1).y = (i3 + h.e[0]);
        Z = ((q)localObject1).C;
        h.a(ab, X);
        h.a();
        aa += 4;
      }
      if (bJ)
      {
        bK = (byte)(bK + bL);
        if ((16 <= bK) || (bK <= 0))
        {
          bL = (byte)-bL;
          bK = (byte)(bK + (bL << 1));
        }
        bJ = false;
      }
      else
      {
        if (bL < 0) {
          bL = (byte)-bL;
        }
        if (bK > 0) {
          bK = (byte)(bK - bL);
        }
        if (bK < 0) {
          bK = 0;
        }
      }
      ab[2] += (bK << 16);
      if (s.h)
      {
        q localq2 = (localObject1 = i)[0];
        int i4 = 0;
        int i5 = 0;
        int i6 = 0;
        for (int i7 = 1; i7 < ah; i7++)
        {
          if ((!localObject1[i7].k) && (aA[i7] > 0) && (localObject1[i7].K > 2))
          {
            Object localObject2;
            i3 = Math.abs((localObject2 = localObject1[i7]).w - localq2.w) + Math.abs(((q)localObject2).x - localq2.x) + Math.abs(((q)localObject2).y - localq2.y);
            if (i6 == 0)
            {
              i4 = i3;
              i5 = aA[i7];
              i6 = 1;
            }
            else if (i3 < i4)
            {
              i4 = i3;
              i5 = aA[i7];
            }
          }
          aA[i7] = 0;
        }
        if (i5 == 1) {
          Z += 1;
        }
        if (i5 == 2) {
          Z -= 1;
        }
        if (i6 == 0)
        {
          if ((Z < bn) && ((Z = Z + 2) > bn)) {
            Z = bn;
          }
          if ((Z > bn) && ((Z = Z - 2) < bn)) {
            Z = bn;
          }
        }
      }
      if (!s.h)
      {
        if ((Z < bn) && ((Z = Z + 2) > bn)) {
          Z = bn;
        }
        if ((Z > bn) && ((Z = Z - 2) < bn)) {
          Z = bn;
        }
      }
    }
    if (bm > 0) {
      if (bH) {
        bm -= 1;
      } else if ((bm = bm - 8) < 0) {
        bm = 0;
      }
    }
    if (bm < 0) {
      if (bH) {
        bm += 1;
      } else if ((bm = bm + 8) > 0) {
        bm = 0;
      }
    }
    if (bl > 0) {
      if (bI) {
        bl -= 1;
      } else if ((bl = bl - 8) < 0) {
        bl = 0;
      }
    }
    if (bl < 0) {
      if (bI) {
        bl += 1;
      } else if ((bl = bl + 8) > 0) {
        bl = 0;
      }
    }
    if (!v.a)
    {
      aa += bm;
      Z += bl;
    }
    if (aa < 0) {
      aa += 360;
    }
    if (aa > 359) {
      aa -= 360;
    }
    if (Z > 359) {
      Z = 359;
    }
    if (Z < 180) {
      Z = 180;
    }
    bH = false;
    bI = false;
  }
  
  public static final void d()
  {
    if ((bi != 0) || (aC != 0)) {
      return;
    }
    aC = 8;
    int i1 = 0;
    do
    {
      if ((bz = (byte)(bz + 1)) > 4) {
        bz = 0;
      }
      if ((by[bz] == 1) && (bz != 0)) {
        break;
      }
      i1++;
    } while (i1 < 10);
    aD = bz;
  }
  
  static void e()
  {
    int[][] arrayOfInt1 = ac;
    int[][] arrayOfInt2 = bE;
    for (int i2 = 0; i2 < 50; i2++) {
      arrayOfInt1[i2][6] = 0;
    }
    for (int i1 = 0; i1 < 15; i1++) {
      arrayOfInt2[i1][4] = 0;
    }
    ad = 0;
    bF = 0;
  }
  
  static void f()
  {
    q[] arrayOfq = i;
    int i1;
    q localq;
    switch (w.o)
    {
    case 0: 
      h.b();
      for (i1 = 1; i1 < arrayOfq.length; i1++) {
        if (((localq = arrayOfq[i1]).M == 1) && (localq.K < 3) && (r.a(i[0], localq)))
        {
          localq.l = -1;
          localq.a = 1;
          localq.p = x[9].j;
          localq.q = x[9].k;
          localq.d = 50;
        }
      }
      return;
    case 1: 
      for (i1 = 1; i1 < arrayOfq.length; i1++) {
        if (((localq = arrayOfq[i1]).M == 1) && (localq.K < 3) && (r.a(i[0], localq)))
        {
          localq.l = -1;
          localq.a = 1;
          localq.d = 50;
          localq.p = i[0].w;
          localq.q = i[0].x;
        }
      }
      return;
    case 2: 
      for (i1 = 1; i1 < arrayOfq.length; i1++) {
        if (((localq = arrayOfq[i1]).M == 1) && (localq.K < 3) && (r.a(i[0], localq)))
        {
          localq.l = -1;
          localq.d = 0;
        }
      }
    }
  }
  
  static final void a(byte[] paramArrayOfByte)
  {
    e locale = x[0];
    for (int i2 = 0; i2 < 4; i2++)
    {
      int i1;
      i locali;
      if (((i1 = paramArrayOfByte[i2]) >= 0) && ((locali = e[i1]).t))
      {
        if (locali.s == 9)
        {
          locali.t = false;
          locale.j = locali.l;
          locale.k = locali.m;
          locale.l = (locali.n + (locali.g >> 1));
          a(locale.j, locale.k, locale.l, locali.q, (byte)3);
          a(locale.j + 3276800, locale.k + 1310720, locale.l, locali.q, (byte)3);
          a(locale.j - 3276800, locale.k + 2621440, locale.l, locali.q, (byte)3);
          a(locale.j - 1966080, locale.k + 5242880, locale.l, locali.q, (byte)3);
          a(locale.j - 3276800, locale.k - 3276800, locale.l, locali.q, (byte)3);
          a(locale.j - 2621440, locale.k - 2621440, locale.l, locali.q, (byte)3);
        }
        if (locali.s == 0)
        {
          a(locali.l, locali.m, locali.n, (byte)0, locali.q);
          locali.t = false;
          locale.j = locali.l;
          locale.k = locali.m;
          locale.l = (locali.n + (locali.g >> 1));
          a(locale, locali.q);
        }
        paramArrayOfByte[i2] = -1;
      }
    }
  }
  
  private static void a(int paramInt1, int paramInt2, int paramInt3, int paramInt4)
  {
    h.a(ai, Math.abs(aV.nextInt() % 91) + 180, Math.abs(aV.nextInt() % 360));
    int[] arrayOfInt1 = aG;
    int[] arrayOfInt2;
    (arrayOfInt2 = aI)[0] = paramInt1;
    arrayOfInt2[1] = paramInt2;
    arrayOfInt2[2] = paramInt3;
    arrayOfInt1[0] = 2;
    arrayOfInt1[1] = paramInt4;
    arrayOfInt1[2] = (Math.abs(aV.nextInt() & 0x1) + 4);
    arrayOfInt1[3] = 5;
    arrayOfInt1[4] = 3;
    if ((paramInt4 = Math.abs(aV.nextInt() & 0xFF) + 70) > 240) {
      paramInt4 = 240;
    }
    arrayOfInt1[5] = (paramInt4 << 16);
    h.a(arrayOfInt2, ai, arrayOfInt1);
  }
  
  private static void b(int paramInt1, int paramInt2, int paramInt3, int paramInt4)
  {
    h.a(ai, Math.abs(aV.nextInt() % 91) + 180, Math.abs(aV.nextInt() % 360));
    int[] arrayOfInt1 = aG;
    int[] arrayOfInt2;
    (arrayOfInt2 = aI)[0] = paramInt1;
    arrayOfInt2[1] = paramInt2;
    arrayOfInt2[2] = paramInt3;
    arrayOfInt1[0] = 2;
    arrayOfInt1[1] = paramInt4;
    arrayOfInt1[2] = (Math.abs(aV.nextInt() & 0x1) + 4);
    arrayOfInt1[3] = 10;
    arrayOfInt1[4] = 2;
    if ((paramInt4 = Math.abs(aV.nextInt() & 0xFF) + 100) > 255) {
      paramInt4 = 255;
    }
    arrayOfInt1[5] = (0xFF0000 | paramInt4 << 8);
    h.a(arrayOfInt2, ai, arrayOfInt1);
  }
  
  private static void a(int paramInt1, int paramInt2, int paramInt3, int paramInt4, byte paramByte)
  {
    int i1 = 0;
    if (paramByte == 0)
    {
      paramByte = (byte)(9 + (aW & 0x3));
      aW = (byte)(aW + 1);
      h.a(ai, 270, Math.abs(aV.nextInt() % 360));
    }
    else
    {
      if (paramByte > 10)
      {
        i1 = paramByte - 10;
        paramByte = 1;
      }
      if (paramByte == 1)
      {
        paramByte = (byte)(44 + (aX & 0x7));
        aX = (byte)(aX + 1);
        h.a(ai, Math.abs(aV.nextInt() % 91) + 180, Math.abs(aV.nextInt() % 360));
      }
      else if (paramByte == 3)
      {
        aW = (byte)(aW + 1);
        paramByte = (byte)(59 + (aW & 0x1));
        h.a(ai, Math.abs(aV.nextInt() % 91) + 180, Math.abs(aV.nextInt() % 360));
      }
      else
      {
        paramByte = 58;
      }
    }
    int[] arrayOfInt1 = aG;
    int[] arrayOfInt2;
    (arrayOfInt2 = aI)[0] = paramInt1;
    arrayOfInt2[1] = paramInt2;
    arrayOfInt2[2] = paramInt3;
    arrayOfInt1[0] = (63536 - paramByte);
    arrayOfInt1[1] = paramInt4;
    arrayOfInt1[2] = ((paramByte < 20) || (paramByte > 57) ? 50 : 100);
    arrayOfInt1[3] = (paramByte < 20 ? 'ú' : 400);
    arrayOfInt1[4] = Math.abs(aV.nextInt() % 359);
    if (paramByte == 58) {
      arrayOfInt1[2] = 0;
    }
    arrayOfInt1[5] = Math.abs(aV.nextInt() % 359);
    if ((paramByte > 43) && (paramByte < 52)) {
      arrayOfInt1[6] = i1;
    }
    h.b(arrayOfInt2, ai, arrayOfInt1);
  }
  
  private static void J()
  {
    for (int i1 = 0; i1 < ah; i1++) {
      switch (i[i1].M)
      {
      case 1: 
        i[i1].e[42] = null;
        i[i1].v[42] = null;
        i[i1].e[35] = null;
        i[i1].v[35] = null;
        i[i1].e[7] = null;
        i[i1].v[7] = null;
        i[i1].e[15] = null;
        i[i1].v[15] = null;
        break;
      case 2: 
        i[i1].e[9] = null;
        i[i1].v[9] = null;
        i[i1].e[19] = null;
        i[i1].v[19] = null;
        i[i1].e[29] = null;
        i[i1].v[29] = null;
        break;
      case 3: 
        i[i1].e[9] = null;
        i[i1].v[9] = null;
      }
    }
    if (aO[1] != 0)
    {
      h[1].a[42] = null;
      h[1].c[42] = null;
      h[1].a[35] = null;
      h[1].c[35] = null;
      h[1].a[7] = null;
      h[1].c[7] = null;
      h[1].a[15] = null;
      h[1].c[15] = null;
    }
    if (aO[2] != 0)
    {
      h[2].a[9] = null;
      h[2].c[9] = null;
      h[2].a[19] = null;
      h[2].c[19] = null;
      h[2].a[29] = null;
      h[2].c[29] = null;
    }
    if (aO[3] != 0)
    {
      h[3].a[9] = null;
      h[3].c[9] = null;
    }
  }
  
  public static final void g()
  {
    s = null;
    w.i.c(10);
    K();
    w.i.c(20);
    B = null;
    y = null;
    aI = null;
    aG = null;
    u = null;
    aH = null;
    x = null;
    o = null;
    t = null;
    K = null;
    ab = null;
    ai = null;
    ac = null;
    bE = null;
    aA = null;
    bc = null;
    w.i.c(30);
    bg = null;
    bG = null;
    Q = null;
    bb = null;
    c = null;
    g = null;
    aK = null;
    w.i.c(40);
    d = null;
    e = null;
    w.i.c(50);
    h = null;
    i = null;
    w.i.c(60);
    v.a();
    w.i.c(70);
    af = null;
    R = null;
    S = null;
    ag = null;
    q = null;
    w.i.c(80);
    ba = null;
    L = null;
    w.i.c(90);
    v.a();
    w.i.c(100);
    w.i.c(100);
    System.gc();
    System.gc();
  }
  
  private static void K()
  {
    aN = null;
    aL = null;
    aO = null;
  }
  
  static final void h()
  {
    switch (s.y)
    {
    case 2: 
      Q[n] = 0;
      break;
    case 3: 
      if (I[2] == 0) {
        I[2] = 1;
      } else {
        Q[n] = 0;
      }
      break;
    case 4: 
      if (n == -1) {
        I[2] = 1;
      } else {
        Q[n] = 0;
      }
      break;
    case 5: 
      if (n == 18)
      {
        Q[n] = 0;
        Q[21] = 0;
      }
      break;
    case 6: 
      if (n == -1) {
        I[2] = 1;
      }
      break;
    case 8: 
      if (n == -1) {
        I[2] = 1;
      }
      break;
    case 9: 
      if (n == 100) {
        b = 0;
      } else if (n < 0) {
        I[2] = ((byte)Math.abs(n));
      } else {
        Q[n] = 0;
      }
      break;
    case 10: 
      if (n < 0)
      {
        n = (byte)((n = (byte)Math.abs(n)) - 1);
        I[(n * 3 + 2)] = 1;
      }
      else
      {
        Q[n] = 0;
      }
      break;
    case 11: 
      if (n > 50)
      {
        if (n == 64) {
          b = (byte)(b | 0x1);
        }
        if (n == 65) {
          b = (byte)(b | 0x2);
        }
        if (b == 3) {
          Q[65] = 0;
        }
      }
      else if (n < 0)
      {
        n = (byte)((n = (byte)Math.abs(n)) - 1);
        if (I[(n * 3 + 1)] != 0) {
          I[(n * 3 + 1)] = 0;
        }
        I[(n * 3 + 2)] = 1;
      }
      else
      {
        n = (byte)(n - 1);
        I[(n * 3 + 2)] = -1;
      }
      break;
    }
    G = n;
  }
  
  public static final void a(int[] paramArrayOfInt, int paramInt)
  {
    int[] arrayOfInt1 = new int[4];
    int i1 = g[paramInt].n;
    int[] arrayOfInt2 = u;
    do
    {
      Object localObject1 = g[paramInt].m;
      int i5 = paramInt;
      int[] arrayOfInt3 = arrayOfInt2;
      int i3 = localObject1[i1];
      localObject1 = paramArrayOfInt;
      k localk = f[i3];
      e[] arrayOfe1 = aH;
      e[] arrayOfe2 = x;
      Object localObject2 = ab;
      arrayOfe1[0] = localk.b[3];
      arrayOfe1[1] = localk.b[1];
      arrayOfe1[2] = localk.b[0];
      arrayOfe1[3] = localk.b[2];
      switch (i7 = localk.a)
      {
      case 1: 
        if ((Math.max(arrayOfe1[0].k, Math.max(arrayOfe1[1].k, arrayOfe1[2].k)) > localObject2[1]) && (Math.max(arrayOfe1[0].l, Math.max(arrayOfe1[1].l, arrayOfe1[2].l)) > localObject2[2])) {
          i7 = Math.abs(localObject2[(i7 - 1)] - arrayOfe1[0].j);
        } else {
          i7 = 9830401;
        }
        break;
      case 2: 
        if ((Math.max(arrayOfe1[0].j, Math.max(arrayOfe1[1].j, arrayOfe1[2].j)) > localObject2[0]) && (Math.max(arrayOfe1[0].l, Math.max(arrayOfe1[1].l, arrayOfe1[2].l)) > localObject2[2])) {
          i7 = Math.abs(localObject2[(i7 - 1)] - arrayOfe1[0].k);
        } else {
          i7 = 9830401;
        }
        break;
      case 3: 
        if ((Math.max(arrayOfe1[0].k, Math.max(arrayOfe1[1].k, arrayOfe1[2].k)) > localObject2[1]) && (Math.max(arrayOfe1[0].j, Math.max(arrayOfe1[1].j, arrayOfe1[2].j)) > localObject2[0])) {
          i7 = Math.abs(localObject2[(i7 - 1)] - arrayOfe1[0].l);
        } else {
          i7 = 9830401;
        }
        break;
      }
      localk.e = true;
      arrayOfInt3[aF] = localObject1[0];
      arrayOfInt3[(aF + 1)] = localObject1[1];
      arrayOfInt3[(aF + 2)] = localObject1[2];
      arrayOfInt3[(aF + 3)] = localObject1[3];
      arrayOfInt3[(aF + 4)] = localk.d;
      aF += 5;
      arrayOfInt3[(aF + 4)] = localk.c;
      aF += 5;
      for (int i7 = 3; i7 >= 0; i7--) {
        h.b(arrayOfe1[i7]);
      }
      int i10 = 4;
      int i9 = localObject1[2];
      e[] arrayOfe3 = arrayOfe1;
      localObject2 = arrayOfe2;
      int[] arrayOfInt4 = t;
      int i12 = 0;
      int[] arrayOfInt5 = U;
      int i16 = O;
      e locale1;
      e locale2;
      int i13;
      int i14;
      Object localObject3;
      long l1;
      long l2;
      for (int i11 = 0; i11 < 4; i11++)
      {
        locale1 = arrayOfe3[i11];
        locale2 = arrayOfe3[arrayOfInt5[(i11 + 36)]];
        i13 = (int)(locale1.a * i16 + locale1.c * i9 >> 24);
        i14 = (int)(locale2.a * i16 + locale2.c * i9 >> 24);
        localObject3 = localObject2[i12];
        if (i13 >= 0)
        {
          ((e)localObject3).a = locale1.a;
          ((e)localObject3).b = locale1.b;
          ((e)localObject3).c = locale1.c;
          ((e)localObject3).f = locale1.f;
          ((e)localObject3).h = locale1.h;
          i12++;
          localObject3 = localObject2[i12];
        }
        if (i14 - i13 > 0)
        {
          l1 = i14 * arrayOfInt4[(i14 - i13)];
          l2 = -i13 * arrayOfInt4[(i14 - i13)];
        }
        else
        {
          l1 = -i14 * arrayOfInt4[(i13 - i14)];
          l2 = i13 * arrayOfInt4[(i13 - i14)];
        }
        if (((i13 > 0) && (i14 < 0)) || ((i14 > 0) && (i13 < 0)))
        {
          ((e)localObject3).a = ((int)(locale1.a * l1 + locale2.a * l2 >> 18));
          ((e)localObject3).b = ((int)(locale1.b * l1 + locale2.b * l2 >> 18));
          ((e)localObject3).c = ((int)(locale1.c * l1 + locale2.c * l2 >> 18));
          ((e)localObject3).f = ((short)(int)(locale1.f * l1 + locale2.f * l2 >> 18));
          ((e)localObject3).h = ((short)(int)(locale1.h * l1 + locale2.h * l2 >> 18));
          i12++;
        }
      }
      i10 = localObject2;
      i9 = localObject1[3];
      arrayOfe3 = arrayOfe2;
      localObject2 = arrayOfe1;
      arrayOfInt4 = t;
      i12 = 0;
      int i15 = i10 * 9;
      arrayOfInt5 = U;
      i16 = O;
      for (i11 = 0; i11 < i10; i11++)
      {
        locale1 = arrayOfe3[i11];
        locale2 = arrayOfe3[arrayOfInt5[(i15 + i11)]];
        i13 = (int)(locale1.a * -i16 + locale1.c * i9 >> 24);
        i14 = (int)(locale2.a * -i16 + locale2.c * i9 >> 24);
        localObject3 = localObject2[i12];
        if (i13 >= 0)
        {
          ((e)localObject3).a = locale1.a;
          ((e)localObject3).b = locale1.b;
          ((e)localObject3).c = locale1.c;
          ((e)localObject3).f = locale1.f;
          ((e)localObject3).h = locale1.h;
          i12++;
          localObject3 = localObject2[i12];
        }
        if (i14 - i13 > 0)
        {
          l1 = i14 * arrayOfInt4[(i14 - i13)];
          l2 = -i13 * arrayOfInt4[(i14 - i13)];
        }
        else
        {
          l1 = -i14 * arrayOfInt4[(i13 - i14)];
          l2 = i13 * arrayOfInt4[(i13 - i14)];
        }
        if (((i13 > 0) && (i14 < 0)) || ((i14 > 0) && (i13 < 0)))
        {
          ((e)localObject3).a = ((int)(locale1.a * l1 + locale2.a * l2 >> 18));
          ((e)localObject3).b = ((int)(locale1.b * l1 + locale2.b * l2 >> 18));
          ((e)localObject3).c = ((int)(locale1.c * l1 + locale2.c * l2 >> 18));
          ((e)localObject3).f = ((short)(int)(locale1.f * l1 + locale2.f * l2 >> 18));
          ((e)localObject3).h = ((short)(int)(locale1.h * l1 + locale2.h * l2 >> 18));
          i12++;
        }
      }
      i10 = localObject2;
      i9 = localObject1[1];
      arrayOfe3 = arrayOfe1;
      localObject2 = arrayOfe2;
      arrayOfInt4 = t;
      i12 = 0;
      i15 = i10 * 9;
      arrayOfInt5 = U;
      i16 = O;
      for (i11 = 0; i11 < i10; i11++)
      {
        locale1 = arrayOfe3[i11];
        locale2 = arrayOfe3[arrayOfInt5[(i15 + i11)]];
        i13 = (int)(locale1.b * i16 + locale1.c * i9 >> 24);
        i14 = (int)(locale2.b * i16 + locale2.c * i9 >> 24);
        localObject3 = localObject2[i12];
        if (i13 >= 0)
        {
          ((e)localObject3).a = locale1.a;
          ((e)localObject3).b = locale1.b;
          ((e)localObject3).c = locale1.c;
          ((e)localObject3).f = locale1.f;
          ((e)localObject3).h = locale1.h;
          i12++;
          localObject3 = localObject2[i12];
        }
        if (i14 - i13 > 0)
        {
          l1 = i14 * arrayOfInt4[(i14 - i13)];
          l2 = -i13 * arrayOfInt4[(i14 - i13)];
        }
        else
        {
          l1 = -i14 * arrayOfInt4[(i13 - i14)];
          l2 = i13 * arrayOfInt4[(i13 - i14)];
        }
        if (((i13 > 0) && (i14 < 0)) || ((i14 > 0) && (i13 < 0)))
        {
          ((e)localObject3).a = ((int)(locale1.a * l1 + locale2.a * l2 >> 18));
          ((e)localObject3).b = ((int)(locale1.b * l1 + locale2.b * l2 >> 18));
          ((e)localObject3).c = ((int)(locale1.c * l1 + locale2.c * l2 >> 18));
          ((e)localObject3).f = ((short)(int)(locale1.f * l1 + locale2.f * l2 >> 18));
          ((e)localObject3).h = ((short)(int)(locale1.h * l1 + locale2.h * l2 >> 18));
          i12++;
        }
      }
      i10 = localObject2;
      i9 = localObject1[0];
      arrayOfe3 = arrayOfe2;
      localObject2 = arrayOfe1;
      arrayOfInt4 = t;
      i12 = 0;
      i15 = i10 * 9;
      arrayOfInt5 = U;
      i16 = O;
      for (i11 = 0; i11 < i10; i11++)
      {
        locale1 = arrayOfe3[i11];
        locale2 = arrayOfe3[arrayOfInt5[(i15 + i11)]];
        i13 = (int)(locale1.b * -i16 + locale1.c * i9 >> 24);
        i14 = (int)(locale2.b * -i16 + locale2.c * i9 >> 24);
        localObject3 = localObject2[i12];
        if (i13 >= 0)
        {
          ((e)localObject3).a = locale1.a;
          ((e)localObject3).b = locale1.b;
          ((e)localObject3).c = locale1.c;
          ((e)localObject3).f = locale1.f;
          ((e)localObject3).h = locale1.h;
          i12++;
          localObject3 = localObject2[i12];
        }
        if (i14 - i13 > 0)
        {
          l1 = i14 * arrayOfInt4[(i14 - i13)];
          l2 = -i13 * arrayOfInt4[(i14 - i13)];
        }
        else
        {
          l1 = -i14 * arrayOfInt4[(i13 - i14)];
          l2 = i13 * arrayOfInt4[(i13 - i14)];
        }
        if (((i13 > 0) && (i14 < 0)) || ((i14 > 0) && (i13 < 0)))
        {
          ((e)localObject3).a = ((int)(locale1.a * l1 + locale2.a * l2 >> 18));
          ((e)localObject3).b = ((int)(locale1.b * l1 + locale2.b * l2 >> 18));
          ((e)localObject3).c = ((int)(locale1.c * l1 + locale2.c * l2 >> 18));
          ((e)localObject3).f = ((short)(int)(locale1.f * l1 + locale2.f * l2 >> 18));
          ((e)localObject3).h = ((short)(int)(locale1.h * l1 + locale2.h * l2 >> 18));
          i12++;
        }
      }
      for (int i8 = localObject2 - 1; i8 >= 0; i8--) {
        h.a(arrayOfe1[i8]);
      }
      i9 = arrayOfe1[0].e;
      i10 = arrayOfe1[0].e;
      int i2 = arrayOfe1[0].d;
      int i6 = arrayOfe1[0].d;
      for (i8 = localObject2 - 1; i8 > 0; i8--)
      {
        if (i2 < arrayOfe1[i8].d) {
          i2 = arrayOfe1[i8].d;
        }
        if (i6 > arrayOfe1[i8].d) {
          i6 = arrayOfe1[i8].d;
        }
        if (i9 < arrayOfe1[i8].e) {
          i9 = arrayOfe1[i8].e;
        }
        if (i10 > arrayOfe1[i8].e) {
          i10 = arrayOfe1[i8].e;
        }
      }
      arrayOfInt3[aF] = (126 - i10);
      arrayOfInt3[(aF + 1)] = (i9 - 126 + 1);
      arrayOfInt3[(aF + 2)] = (120 - i6 + 1);
      arrayOfInt3[(aF + 3)] = (i2 - 120 + 1);
      arrayOfInt3[(aF + 4)] = localk.d;
      aF += 5;
      localk.e = true;
      arrayOfInt3[(aF + 4)] = localk.c;
      aF += 5;
      localk.e = true;
      if ((i2 = localk.c == i5 ? localk.d : (localObject2 = i12) == 0 ? -1 : (localObject2 = i12) == 0 ? -1 : (localObject2 = i12) == 0 ? -1 : (localObject2 = i12) == 0 ? -1 : i7 <= 9830400 ? localk.c : localk.c == i5 ? localk.d : f[i3].e ? -1 : localk.c) >= 0)
      {
        if ((Q[i2] == 1) || (Q[i2] < 0))
        {
          f[g[i2].m[0]].e = true;
          f[g[i2].m[1]].e = true;
        }
        int i4 = aF - 5;
        arrayOfInt1[0] = arrayOfInt2[i4];
        arrayOfInt1[1] = arrayOfInt2[(i4 + 1)];
        arrayOfInt1[2] = arrayOfInt2[(i4 + 2)];
        arrayOfInt1[3] = arrayOfInt2[(i4 + 3)];
        if (arrayOfInt2[(i4 + 4)] == 999) {
          arrayOfInt2[(i4 + 4)] = -1;
        } else {
          a(arrayOfInt1, i2);
        }
      }
      i1--;
    } while (i1 >= 0);
  }
  
  public static final void a(int[] paramArrayOfInt)
  {
    int[][] arrayOfInt = { { 0, 0, 1 }, { 0, -O, 0 }, { 0, O, 0 }, { O, 0, 0 }, { -O, 0, 0 } };
    k[] arrayOfk = f;
    for (int i4 = f.length - 1; i4 >= 0; i4--) {
      arrayOfk[i4].e = false;
    }
    for (int i3 = aF - 5; i3 >= 0; i3 -= 5)
    {
      arrayOfInt[1][2] = paramArrayOfInt[i3];
      arrayOfInt[2][2] = paramArrayOfInt[(i3 + 1)];
      arrayOfInt[3][2] = paramArrayOfInt[(i3 + 2)];
      arrayOfInt[4][2] = paramArrayOfInt[(i3 + 3)];
      a(paramArrayOfInt[(i3 + 4)], arrayOfInt);
    }
    a(X, be);
    aF = 0;
    int i8;
    if ((!v.a) && (!i[0].k)) {
      if ((i[0].m == -1) && (z == -1))
      {
        paramArrayOfInt = aj;
        int i1 = bA[(aj << 1)];
        i3 = bA[((aj << 1) + 1)];
        i1 += bB;
        i3 += bC;
        if (aj != 0)
        {
          if ((aj == 1) && (bi != 0))
          {
            paramArrayOfInt = 5;
            if (ap[5] == null) {
              paramArrayOfInt = aj;
            }
          }
          if (aj == 2)
          {
            paramArrayOfInt = bv[bt];
            if (ap[paramArrayOfInt] == null) {
              paramArrayOfInt = aj;
            }
          }
          if ((aj == 3) && (bi != 0))
          {
            paramArrayOfInt = 7;
            if (ap[7] == null) {
              paramArrayOfInt = aj;
            }
          }
          if (aj == 6)
          {
            paramArrayOfInt += ax[bt];
            i1 = ay[(bt << 1)];
            i3 = ay[((bt << 1) + 1)];
          }
          if (aC > 0) {
            i3 = (i3 = Math.abs(4 - aC)) << 6;
          } else {
            i3 -= (bK << 2);
          }
          i4 = bk << 1;
          int i5 = bk * 3;
          if (i4 >= 360) {
            i4 -= 360;
          }
          if ((i5 >= 360) && (i5 -= 360 >= 360)) {
            i5 -= 360;
          }
          i1 += 13 + (h.d[i4] * 12 >> 16);
          i3 -= 13 + (h.a[i5] * 12 >> 16);
          if (i1 < 0) {
            i1 = 0;
          }
          if (i1 > 256) {
            i1 = 256;
          }
          if (i3 < 0) {
            i3 = 0;
          }
          if (i3 > 256) {
            i3 = 256;
          }
          if (paramArrayOfInt == 5)
          {
            if ((i8 = i1 - bd[(bi << 1)]) < 0) {
              i8 = 0;
            }
            if ((i4 = i3 - bd[((bi << 1) + 1)]) < 0) {
              i4 = 0;
            }
            a(s, 10, i8, i4);
          }
          if (paramArrayOfInt == 7)
          {
            if ((i8 = i1 - aB[(bi << 1)]) < 0) {
              i8 = 0;
            }
            if ((i4 = i3 - aB[((bi << 1) + 1)]) < 0) {
              i4 = 0;
            }
            a(s, 11, i8, i4);
          }
          a(s, paramArrayOfInt, i1, i3);
        }
      }
      else
      {
        int[] arrayOfInt1 = s;
        if (aY <= 10) {
          if (aY == 0) {
            for (i3 = 0; i3 < 59999; i3++) {
              arrayOfInt1[i3] &= 0xFF0000;
            }
          } else if (Math.abs(aV.nextInt() & 0x1) != 0) {
            for (i4 = 0; i4 < 59999; i4++) {
              arrayOfInt1[i4] &= 0xFF0000;
            }
          }
        }
        if (aY > 0) {
          aY = (byte)(aY - 1);
        }
      }
    }
    if (ak != 255)
    {
      if ((paramArrayOfInt = ak) > 255)
      {
        paramArrayOfInt = 255;
        ak = 255;
      }
      if (paramArrayOfInt < 0)
      {
        paramArrayOfInt = 0;
        ak = 0;
      }
      int i2 = 60000;
      int[] arrayOfInt2 = s;
      int i6 = paramArrayOfInt;
      i8 = 8;
      int i7;
      if (i[0].k)
      {
        i7 = 1;
        i8 = 0;
      }
      do
      {
        i4 = arrayOfInt2[i2];
        arrayOfInt2[i2] = ((i4 >> 16 & 0xFF) * i7 >> i8 << 16 | (i4 >> 8 & 0xFF) * paramArrayOfInt >> 8 << 8 | (i4 & 0xFF) * paramArrayOfInt >> 8);
        i2--;
      } while (i2 >= 0);
      if ((i8 != 0) && (ak < 255)) {
        ak = (short)(ak + 1);
      }
    }
  }
  
  private static void a(int[] paramArrayOfInt, int paramInt1, int paramInt2, int paramInt3)
  {
    int i1 = bM[paramInt1][0];
    int i2 = bM[paramInt1][1];
    int i3 = i1;
    paramInt3 = 252 - (paramInt3 * i2 >> 8) - 2;
    al = (short)(paramInt2 = paramInt2 * (240 - i1) >> 8);
    am = (short)paramInt3;
    if ((paramInt2 >= 240) || (paramInt2 + i1 < 0) || (paramInt3 >= 252) || (paramInt3 + i2 < 0)) {
      return;
    }
    int[] arrayOfInt1 = ao[paramInt1];
    paramInt1 = ap[paramInt1];
    int[] arrayOfInt2 = bc;
    if ((i5 = i[0].t) < 30) {
      i5 = 30;
    }
    int i6 = arrayOfInt1.length;
    for (int i7 = 0; i7 < i6; i7++)
    {
      i8 = arrayOfInt1[i7];
      arrayOfInt2[i7] = ((i8 & 0xFF000000) + ((i8 >> 16 & 0xFF) * i5 >> 8 << 16) + ((i8 >> 8 & 0xFF) * i5 >> 8 << 8) + ((i8 & 0xFF) * i5 >> 8));
    }
    int i4 = 0;
    int i5 = 0;
    int i8 = 240 - i1;
    if (paramInt2 < 0)
    {
      i4 = -paramInt2;
      i8 -= paramInt2;
      paramInt2 = 0;
    }
    if (paramInt3 < 0)
    {
      i5 = -paramInt3;
      paramInt3 = 0;
    }
    if (paramInt2 + i1 > 240)
    {
      i1 = 240 - paramInt2;
      i8 = 240 - i1;
    }
    if (paramInt3 + i2 > 252) {
      i2 = 252 - paramInt3;
    }
    int i9 = 0;
    int i10 = 0;
    int i11 = 0;
    paramInt2 = paramInt3 * 240 + paramInt2;
    for (i7 = i5; i7 < i2; i7++)
    {
      for (i6 = i4; i6 < i1; i6++)
      {
        if (i10 == 0)
        {
          if ((i11 = paramInt1[i9]) < 0)
          {
            i10 = -i11;
            i9++;
          }
          i11 = arrayOfInt2[paramInt1[i9]];
          i9++;
          if ((i11 == 0) && (i10 > 0))
          {
            if (i6 + i10 < i3)
            {
              paramInt2 += i10 + 1;
              i6 += i10;
              i10 = 0;
              continue;
            }
            i10 = i10 - (i3 - i6) + 1;
            paramInt2 += i3 - i6;
            break;
          }
        }
        else
        {
          if ((i11 == 0) && (i10 > 0) && (i6 + i10 <= i3))
          {
            paramInt2 += i10;
            i6 += i10 - 1;
            i10 = 0;
            continue;
          }
          i10--;
        }
        if (i11 != 0) {
          paramArrayOfInt[paramInt2] = i11;
        }
        paramInt2++;
      }
      paramInt2 += i8;
    }
  }
  
  /* Error */
  private static final void a(int arg0, int[][] arg1)
  {
    // Byte code:
    //   0: aload_1
    //   1: iconst_1
    //   2: aaload
    //   3: iconst_2
    //   4: iaload
    //   5: bipush 126
    //   7: if_icmple +10 -> 17
    //   10: aload_1
    //   11: iconst_1
    //   12: aaload
    //   13: iconst_2
    //   14: bipush 126
    //   16: iastore
    //   17: aload_1
    //   18: iconst_2
    //   19: aaload
    //   20: iconst_2
    //   21: iaload
    //   22: bipush 126
    //   24: if_icmple +10 -> 34
    //   27: aload_1
    //   28: iconst_2
    //   29: aaload
    //   30: iconst_2
    //   31: bipush 126
    //   33: iastore
    //   34: aload_1
    //   35: iconst_3
    //   36: aaload
    //   37: iconst_2
    //   38: iaload
    //   39: bipush 120
    //   41: if_icmple +10 -> 51
    //   44: aload_1
    //   45: iconst_3
    //   46: aaload
    //   47: iconst_2
    //   48: bipush 120
    //   50: iastore
    //   51: iload_0
    //   52: aload_1
    //   53: astore_3
    //   54: istore_2
    //   55: getstatic 311	g:g	[Lc;
    //   58: iload_2
    //   59: aaload
    //   60: getfield 159	c:a	[S
    //   63: astore 4
    //   65: getstatic 311	g:g	[Lc;
    //   68: iload_2
    //   69: aaload
    //   70: getfield 160	c:b	[S
    //   73: astore 5
    //   75: getstatic 311	g:g	[Lc;
    //   78: iload_2
    //   79: aaload
    //   80: getfield 170	c:l	I
    //   83: bipush 7
    //   85: imul
    //   86: istore 6
    //   88: getstatic 219	g:aH	[Le;
    //   91: astore 7
    //   93: getstatic 327	g:x	[Le;
    //   96: astore 8
    //   98: aload 7
    //   100: iconst_0
    //   101: aaload
    //   102: astore 9
    //   104: aload 7
    //   106: iconst_1
    //   107: aaload
    //   108: astore 10
    //   110: aload 7
    //   112: iconst_2
    //   113: aaload
    //   114: astore 11
    //   116: aload 8
    //   118: iconst_0
    //   119: aaload
    //   120: astore 12
    //   122: getstatic 271	g:bG	[S
    //   125: astore 14
    //   127: aload 4
    //   129: getstatic 311	g:g	[Lc;
    //   132: iload_2
    //   133: aaload
    //   134: getfield 169	c:k	I
    //   137: invokestatic 519	h:a	([SI)V
    //   140: getstatic 195	g:K	[I
    //   143: astore 15
    //   145: getstatic 278	g:bN	I
    //   148: bipush 16
    //   150: ishr
    //   151: istore 17
    //   153: getstatic 279	g:bO	I
    //   156: bipush 16
    //   158: ishr
    //   159: istore 18
    //   161: iconst_0
    //   162: istore 19
    //   164: goto +474 -> 638
    //   167: aload 5
    //   169: iload 19
    //   171: saload
    //   172: istore 16
    //   174: aload 9
    //   176: aload 15
    //   178: iload 16
    //   180: iaload
    //   181: putfield 174	e:a	I
    //   184: aload 9
    //   186: aload 15
    //   188: iinc 16 1
    //   191: iload 16
    //   193: iaload
    //   194: putfield 175	e:b	I
    //   197: aload 9
    //   199: aload 15
    //   201: iinc 16 1
    //   204: iload 16
    //   206: iaload
    //   207: putfield 176	e:c	I
    //   210: aload 5
    //   212: iload 19
    //   214: iconst_1
    //   215: iadd
    //   216: saload
    //   217: istore 16
    //   219: aload 10
    //   221: aload 15
    //   223: iload 16
    //   225: iaload
    //   226: putfield 174	e:a	I
    //   229: aload 10
    //   231: aload 15
    //   233: iinc 16 1
    //   236: iload 16
    //   238: iaload
    //   239: putfield 175	e:b	I
    //   242: aload 10
    //   244: aload 15
    //   246: iinc 16 1
    //   249: iload 16
    //   251: iaload
    //   252: putfield 176	e:c	I
    //   255: aload 5
    //   257: iload 19
    //   259: iconst_2
    //   260: iadd
    //   261: saload
    //   262: istore 16
    //   264: aload 11
    //   266: aload 15
    //   268: iload 16
    //   270: iaload
    //   271: putfield 174	e:a	I
    //   274: aload 11
    //   276: aload 15
    //   278: iinc 16 1
    //   281: iload 16
    //   283: iaload
    //   284: putfield 175	e:b	I
    //   287: aload 11
    //   289: aload 15
    //   291: iinc 16 1
    //   294: iload 16
    //   296: iaload
    //   297: putfield 176	e:c	I
    //   300: aload 5
    //   302: iload 19
    //   304: iconst_3
    //   305: iadd
    //   306: saload
    //   307: istore 16
    //   309: aload 9
    //   311: aload 14
    //   313: iload 16
    //   315: saload
    //   316: putfield 179	e:f	S
    //   319: aload 9
    //   321: aload 14
    //   323: iinc 16 1
    //   326: iload 16
    //   328: saload
    //   329: putfield 180	e:h	S
    //   332: aload 5
    //   334: iload 19
    //   336: iconst_4
    //   337: iadd
    //   338: saload
    //   339: istore 16
    //   341: aload 10
    //   343: aload 14
    //   345: iload 16
    //   347: saload
    //   348: putfield 179	e:f	S
    //   351: aload 10
    //   353: aload 14
    //   355: iinc 16 1
    //   358: iload 16
    //   360: saload
    //   361: putfield 180	e:h	S
    //   364: aload 5
    //   366: iload 19
    //   368: iconst_5
    //   369: iadd
    //   370: saload
    //   371: istore 16
    //   373: aload 11
    //   375: aload 14
    //   377: iload 16
    //   379: saload
    //   380: putfield 179	e:f	S
    //   383: aload 11
    //   385: aload 14
    //   387: iinc 16 1
    //   390: iload 16
    //   392: saload
    //   393: putfield 180	e:h	S
    //   396: aload 8
    //   398: aload 7
    //   400: aload_3
    //   401: invokestatic 543	k:a	([Le;[Le;[[I)I
    //   404: dup
    //   405: istore 13
    //   407: ifle +170 -> 577
    //   410: aload 5
    //   412: iload 19
    //   414: bipush 6
    //   416: iadd
    //   417: saload
    //   418: bipush 8
    //   420: ishr
    //   421: sipush 255
    //   424: iand
    //   425: putstatic 314	g:j	I
    //   428: getstatic 326	g:v	Z
    //   431: ifeq +98 -> 529
    //   434: iload 17
    //   436: aload 4
    //   438: aload 5
    //   440: iload 19
    //   442: saload
    //   443: saload
    //   444: isub
    //   445: iload 18
    //   447: aload 4
    //   449: aload 5
    //   451: iload 19
    //   453: saload
    //   454: iconst_1
    //   455: iadd
    //   456: saload
    //   457: isub
    //   458: getstatic 314	g:j	I
    //   461: istore 22
    //   463: istore 21
    //   465: istore 20
    //   467: ldc2_w 157
    //   470: iload 20
    //   472: iload 20
    //   474: imul
    //   475: iload 21
    //   477: iload 21
    //   479: imul
    //   480: iadd
    //   481: i2l
    //   482: lmul
    //   483: bipush 28
    //   485: lshr
    //   486: l2i
    //   487: dup
    //   488: istore 23
    //   490: sipush 255
    //   493: if_icmple +8 -> 501
    //   496: sipush 255
    //   499: istore 23
    //   501: iload 22
    //   503: sipush 255
    //   506: iload 23
    //   508: isub
    //   509: iadd
    //   510: dup
    //   511: istore 22
    //   513: sipush 255
    //   516: if_icmple +8 -> 524
    //   519: sipush 255
    //   522: istore 22
    //   524: iload 22
    //   526: putstatic 314	g:j	I
    //   529: getstatic 429	s:y	B
    //   532: iconst_4
    //   533: if_icmpne +44 -> 577
    //   536: aload 4
    //   538: aload 5
    //   540: iload 19
    //   542: getstatic 314	g:j	I
    //   545: getstatic 309	g:e	[Li;
    //   548: iconst_0
    //   549: aaload
    //   550: invokestatic 488	g:a	([S[SIILi;)I
    //   553: putstatic 314	g:j	I
    //   556: aload 4
    //   558: aload 5
    //   560: iload 19
    //   562: getstatic 314	g:j	I
    //   565: getstatic 309	g:e	[Li;
    //   568: bipush 13
    //   570: aaload
    //   571: invokestatic 488	g:a	([S[SIILi;)I
    //   574: putstatic 314	g:j	I
    //   577: iload 13
    //   579: dup
    //   580: iconst_1
    //   581: isub
    //   582: istore 13
    //   584: ifle +51 -> 635
    //   587: aload 5
    //   589: iload 19
    //   591: bipush 6
    //   593: iadd
    //   594: saload
    //   595: sipush 255
    //   598: iand
    //   599: putstatic 185	g:A	I
    //   602: iinc 13 -1
    //   605: goto +22 -> 627
    //   608: aload 12
    //   610: aload 8
    //   612: iload 13
    //   614: iconst_1
    //   615: iadd
    //   616: aaload
    //   617: aload 8
    //   619: iload 13
    //   621: iconst_2
    //   622: iadd
    //   623: aaload
    //   624: invokestatic 545	m:a	(Le;Le;Le;)V
    //   627: iinc 13 -1
    //   630: iload 13
    //   632: ifge -24 -> 608
    //   635: iinc 19 7
    //   638: iload 19
    //   640: iload 6
    //   642: if_icmplt -475 -> 167
    //   645: aload_1
    //   646: iload_0
    //   647: istore_2
    //   648: getstatic 220	g:aI	[I
    //   651: astore_3
    //   652: getstatic 218	g:aG	[I
    //   655: astore 4
    //   657: getstatic 239	g:ab	[I
    //   660: iconst_0
    //   661: iaload
    //   662: istore 5
    //   664: getstatic 239	g:ab	[I
    //   667: iconst_1
    //   668: iaload
    //   669: istore 6
    //   671: getstatic 239	g:ab	[I
    //   674: iconst_2
    //   675: iaload
    //   676: istore 7
    //   678: getstatic 237	g:aZ	I
    //   681: istore 8
    //   683: iconst_0
    //   684: istore 9
    //   686: getstatic 269	g:bE	[[I
    //   689: astore 12
    //   691: getstatic 240	g:ac	[[I
    //   694: astore 13
    //   696: iconst_0
    //   697: istore 14
    //   699: iconst_0
    //   700: istore 15
    //   702: iconst_1
    //   703: istore 16
    //   705: getstatic 313	g:i	[Lq;
    //   708: iconst_0
    //   709: aaload
    //   710: getfield 392	q:k	Z
    //   713: ifeq +6 -> 719
    //   716: iconst_0
    //   717: istore 16
    //   719: getstatic 245	g:ah	S
    //   722: iconst_1
    //   723: isub
    //   724: istore_0
    //   725: goto +77 -> 802
    //   728: getstatic 313	g:i	[Lq;
    //   731: iload_0
    //   732: aaload
    //   733: dup
    //   734: astore 11
    //   736: getfield 380	q:N	Z
    //   739: ifeq +60 -> 799
    //   742: iload_2
    //   743: aload 11
    //   745: getfield 369	q:B	S
    //   748: if_icmpne +51 -> 799
    //   751: aload_3
    //   752: iload 9
    //   754: iload_0
    //   755: iastore
    //   756: aload 4
    //   758: iload 9
    //   760: aload 11
    //   762: getfield 402	q:w	I
    //   765: iload 5
    //   767: isub
    //   768: invokestatic 530	java/lang/Math:abs	(I)I
    //   771: aload 11
    //   773: getfield 403	q:x	I
    //   776: iload 6
    //   778: isub
    //   779: invokestatic 530	java/lang/Math:abs	(I)I
    //   782: iadd
    //   783: aload 11
    //   785: getfield 404	q:y	I
    //   788: iload 7
    //   790: isub
    //   791: invokestatic 530	java/lang/Math:abs	(I)I
    //   794: iadd
    //   795: iastore
    //   796: iinc 9 1
    //   799: iinc 0 -1
    //   802: iload_0
    //   803: iload 16
    //   805: if_icmpge -77 -> 728
    //   808: iconst_0
    //   809: istore_0
    //   810: goto +80 -> 890
    //   813: getstatic 309	g:e	[Li;
    //   816: iload_0
    //   817: aaload
    //   818: dup
    //   819: astore 10
    //   821: getfield 353	i:t	Z
    //   824: ifeq +63 -> 887
    //   827: aload 10
    //   829: getfield 350	i:q	S
    //   832: iload_2
    //   833: if_icmpne +54 -> 887
    //   836: aload_3
    //   837: iload 9
    //   839: iload_0
    //   840: iload 8
    //   842: iadd
    //   843: iastore
    //   844: aload 4
    //   846: iload 9
    //   848: aload 10
    //   850: getfield 345	i:l	I
    //   853: iload 5
    //   855: isub
    //   856: invokestatic 530	java/lang/Math:abs	(I)I
    //   859: aload 10
    //   861: getfield 346	i:m	I
    //   864: iload 6
    //   866: isub
    //   867: invokestatic 530	java/lang/Math:abs	(I)I
    //   870: iadd
    //   871: aload 10
    //   873: getfield 347	i:n	I
    //   876: iload 7
    //   878: isub
    //   879: invokestatic 530	java/lang/Math:abs	(I)I
    //   882: iadd
    //   883: iastore
    //   884: iinc 9 1
    //   887: iinc 0 1
    //   890: iload_0
    //   891: getstatic 198	g:N	S
    //   894: if_icmplt -81 -> 813
    //   897: iload 8
    //   899: getstatic 198	g:N	S
    //   902: iadd
    //   903: istore 8
    //   905: goto +94 -> 999
    //   908: aload 12
    //   910: iload 15
    //   912: aaload
    //   913: iconst_4
    //   914: iaload
    //   915: ifne +9 -> 924
    //   918: iinc 15 1
    //   921: goto +78 -> 999
    //   924: aload 12
    //   926: iload 15
    //   928: aaload
    //   929: iconst_5
    //   930: iaload
    //   931: iload_2
    //   932: if_icmpne +61 -> 993
    //   935: aload_3
    //   936: iload 9
    //   938: iload 15
    //   940: iload 8
    //   942: iadd
    //   943: iastore
    //   944: aload 4
    //   946: iload 9
    //   948: aload 12
    //   950: iload 15
    //   952: aaload
    //   953: iconst_0
    //   954: iaload
    //   955: iload 5
    //   957: isub
    //   958: invokestatic 530	java/lang/Math:abs	(I)I
    //   961: aload 12
    //   963: iload 15
    //   965: aaload
    //   966: iconst_1
    //   967: iaload
    //   968: iload 6
    //   970: isub
    //   971: invokestatic 530	java/lang/Math:abs	(I)I
    //   974: iadd
    //   975: aload 12
    //   977: iload 15
    //   979: aaload
    //   980: iconst_2
    //   981: iaload
    //   982: iload 7
    //   984: isub
    //   985: invokestatic 530	java/lang/Math:abs	(I)I
    //   988: iadd
    //   989: iastore
    //   990: iinc 9 1
    //   993: iinc 14 1
    //   996: iinc 15 1
    //   999: iload 14
    //   1001: getstatic 270	g:bF	S
    //   1004: if_icmplt -96 -> 908
    //   1007: iinc 8 15
    //   1010: iconst_0
    //   1011: istore 14
    //   1013: iconst_0
    //   1014: istore 15
    //   1016: goto +96 -> 1112
    //   1019: aload 13
    //   1021: iload 15
    //   1023: aaload
    //   1024: bipush 6
    //   1026: iaload
    //   1027: ifne +9 -> 1036
    //   1030: iinc 15 1
    //   1033: goto +79 -> 1112
    //   1036: aload 13
    //   1038: iload 15
    //   1040: aaload
    //   1041: bipush 7
    //   1043: iaload
    //   1044: iload_2
    //   1045: if_icmpne +61 -> 1106
    //   1048: aload_3
    //   1049: iload 9
    //   1051: iload 15
    //   1053: iload 8
    //   1055: iadd
    //   1056: iastore
    //   1057: aload 4
    //   1059: iload 9
    //   1061: aload 13
    //   1063: iload 15
    //   1065: aaload
    //   1066: iconst_0
    //   1067: iaload
    //   1068: iload 5
    //   1070: isub
    //   1071: invokestatic 530	java/lang/Math:abs	(I)I
    //   1074: aload 13
    //   1076: iload 15
    //   1078: aaload
    //   1079: iconst_1
    //   1080: iaload
    //   1081: iload 6
    //   1083: isub
    //   1084: invokestatic 530	java/lang/Math:abs	(I)I
    //   1087: iadd
    //   1088: aload 13
    //   1090: iload 15
    //   1092: aaload
    //   1093: iconst_2
    //   1094: iaload
    //   1095: iload 7
    //   1097: isub
    //   1098: invokestatic 530	java/lang/Math:abs	(I)I
    //   1101: iadd
    //   1102: iastore
    //   1103: iinc 9 1
    //   1106: iinc 14 1
    //   1109: iinc 15 1
    //   1112: iload 14
    //   1114: getstatic 241	g:ad	S
    //   1117: if_icmplt -98 -> 1019
    //   1120: aload 4
    //   1122: aload_3
    //   1123: iconst_0
    //   1124: iload 9
    //   1126: iconst_1
    //   1127: isub
    //   1128: invokestatic 517	h:a	([I[III)V
    //   1131: iload 9
    //   1133: istore_3
    //   1134: astore_2
    //   1135: getstatic 269	g:bE	[[I
    //   1138: astore 4
    //   1140: getstatic 240	g:ac	[[I
    //   1143: astore 5
    //   1145: getstatic 255	g:ar	[[I
    //   1148: astore 6
    //   1150: getstatic 309	g:e	[Li;
    //   1153: astore 7
    //   1155: getstatic 195	g:K	[I
    //   1158: astore 9
    //   1160: getstatic 219	g:aH	[Le;
    //   1163: astore 11
    //   1165: getstatic 327	g:x	[Le;
    //   1168: astore 12
    //   1170: aload 11
    //   1172: iconst_0
    //   1173: aaload
    //   1174: astore 13
    //   1176: aload 11
    //   1178: iconst_1
    //   1179: aaload
    //   1180: astore 14
    //   1182: aload 11
    //   1184: iconst_2
    //   1185: aaload
    //   1186: astore 15
    //   1188: aload 12
    //   1190: iconst_0
    //   1191: aaload
    //   1192: astore 16
    //   1194: getstatic 220	g:aI	[I
    //   1197: astore 20
    //   1199: getstatic 186	g:B	[I
    //   1202: astore 21
    //   1204: getstatic 237	g:aZ	I
    //   1207: istore 22
    //   1209: getstatic 268	g:bD	I
    //   1212: istore 23
    //   1214: getstatic 299	g:bs	I
    //   1217: istore_1
    //   1218: getstatic 330	h:a	[I
    //   1221: getstatic 238	g:aa	I
    //   1224: iaload
    //   1225: istore 24
    //   1227: getstatic 332	h:d	[I
    //   1230: getstatic 238	g:aa	I
    //   1233: iaload
    //   1234: istore 25
    //   1236: getstatic 330	h:a	[I
    //   1239: getstatic 210	g:Z	I
    //   1242: iaload
    //   1243: istore 26
    //   1245: getstatic 332	h:d	[I
    //   1248: getstatic 210	g:Z	I
    //   1251: iaload
    //   1252: istore 27
    //   1254: iload_3
    //   1255: iconst_1
    //   1256: isub
    //   1257: istore 29
    //   1259: goto +3600 -> 4859
    //   1262: aload 20
    //   1264: iload 29
    //   1266: iaload
    //   1267: iload_1
    //   1268: if_icmplt +486 -> 1754
    //   1271: aload 20
    //   1273: iload 29
    //   1275: iaload
    //   1276: iload_1
    //   1277: isub
    //   1278: istore 19
    //   1280: aload 5
    //   1282: iload 19
    //   1284: aaload
    //   1285: bipush 9
    //   1287: iaload
    //   1288: sipush 63536
    //   1291: if_icmpgt +252 -> 1543
    //   1294: aload 5
    //   1296: iload 19
    //   1298: aaload
    //   1299: bipush 9
    //   1301: iaload
    //   1302: sipush 63516
    //   1305: if_icmple +44 -> 1349
    //   1308: aload 5
    //   1310: iload 19
    //   1312: aaload
    //   1313: bipush 9
    //   1315: iaload
    //   1316: ineg
    //   1317: sipush 2000
    //   1320: isub
    //   1321: aload 5
    //   1323: iload 19
    //   1325: aaload
    //   1326: iconst_0
    //   1327: iaload
    //   1328: aload 5
    //   1330: iload 19
    //   1332: aaload
    //   1333: iconst_1
    //   1334: iaload
    //   1335: aload 5
    //   1337: iload 19
    //   1339: aaload
    //   1340: iconst_2
    //   1341: iaload
    //   1342: aload_2
    //   1343: invokestatic 544	m:a	(IIII[[I)V
    //   1346: goto +3510 -> 4856
    //   1349: getstatic 281	g:ba	Li;
    //   1352: dup
    //   1353: astore 8
    //   1355: aload 5
    //   1357: iload 19
    //   1359: aaload
    //   1360: bipush 9
    //   1362: iaload
    //   1363: ineg
    //   1364: sipush 2000
    //   1367: isub
    //   1368: i2b
    //   1369: putfield 352	i:s	B
    //   1372: aload 8
    //   1374: getfield 352	i:s	B
    //   1377: bipush 58
    //   1379: if_icmple +16 -> 1395
    //   1382: aload 8
    //   1384: dup
    //   1385: getfield 352	i:s	B
    //   1388: bipush 49
    //   1390: isub
    //   1391: i2b
    //   1392: putfield 352	i:s	B
    //   1395: aload 8
    //   1397: getstatic 308	g:d	[Lx;
    //   1400: aload 8
    //   1402: getfield 352	i:s	B
    //   1405: aaload
    //   1406: getfield 451	x:b	[S
    //   1409: putfield 335	i:b	[S
    //   1412: aload 8
    //   1414: getstatic 308	g:d	[Lx;
    //   1417: aload 8
    //   1419: getfield 352	i:s	B
    //   1422: aaload
    //   1423: getfield 450	x:a	[S
    //   1426: putfield 334	i:a	[S
    //   1429: aload 8
    //   1431: getfield 335	i:b	[S
    //   1434: astore 10
    //   1436: getstatic 308	g:d	[Lx;
    //   1439: aload 8
    //   1441: getfield 352	i:s	B
    //   1444: aaload
    //   1445: getfield 451	x:b	[S
    //   1448: arraylength
    //   1449: iconst_4
    //   1450: ishr
    //   1451: istore_0
    //   1452: aload 8
    //   1454: aload 5
    //   1456: iload 19
    //   1458: aaload
    //   1459: iconst_0
    //   1460: iaload
    //   1461: putfield 345	i:l	I
    //   1464: aload 8
    //   1466: aload 5
    //   1468: iload 19
    //   1470: aaload
    //   1471: iconst_1
    //   1472: iaload
    //   1473: putfield 346	i:m	I
    //   1476: aload 8
    //   1478: aload 5
    //   1480: iload 19
    //   1482: aaload
    //   1483: iconst_2
    //   1484: iaload
    //   1485: putfield 347	i:n	I
    //   1488: aload 8
    //   1490: aload 8
    //   1492: getfield 352	i:s	B
    //   1495: bipush 58
    //   1497: if_icmpne +7 -> 1504
    //   1500: iconst_0
    //   1501: goto +11 -> 1512
    //   1504: aload 5
    //   1506: iload 19
    //   1508: aaload
    //   1509: bipush 11
    //   1511: iaload
    //   1512: putfield 348	i:o	I
    //   1515: aload 8
    //   1517: aload 5
    //   1519: iload 19
    //   1521: aaload
    //   1522: bipush 10
    //   1524: iaload
    //   1525: putfield 349	i:p	I
    //   1528: aload 8
    //   1530: iconst_0
    //   1531: invokestatic 512	h:a	(Li;I)V
    //   1534: iconst_1
    //   1535: istore 8
    //   1537: iconst_0
    //   1538: istore 28
    //   1540: goto +209 -> 1749
    //   1543: aload 5
    //   1545: iload 19
    //   1547: aaload
    //   1548: bipush 9
    //   1550: iaload
    //   1551: iconst_1
    //   1552: if_icmple +15 -> 1567
    //   1555: aload 5
    //   1557: iload 19
    //   1559: aaload
    //   1560: aload_2
    //   1561: invokestatic 546	m:a	([I[[I)V
    //   1564: goto +3292 -> 4856
    //   1567: getstatic 281	g:ba	Li;
    //   1570: dup
    //   1571: astore 8
    //   1573: bipush 56
    //   1575: aload 5
    //   1577: iload 19
    //   1579: aaload
    //   1580: bipush 9
    //   1582: iaload
    //   1583: iadd
    //   1584: i2b
    //   1585: putfield 352	i:s	B
    //   1588: aload 8
    //   1590: getstatic 308	g:d	[Lx;
    //   1593: aload 8
    //   1595: getfield 352	i:s	B
    //   1598: aaload
    //   1599: getfield 451	x:b	[S
    //   1602: putfield 335	i:b	[S
    //   1605: aload 8
    //   1607: getstatic 308	g:d	[Lx;
    //   1610: aload 8
    //   1612: getfield 352	i:s	B
    //   1615: aaload
    //   1616: getfield 450	x:a	[S
    //   1619: putfield 334	i:a	[S
    //   1622: aload 8
    //   1624: getfield 335	i:b	[S
    //   1627: astore 10
    //   1629: getstatic 308	g:d	[Lx;
    //   1632: aload 8
    //   1634: getfield 352	i:s	B
    //   1637: aaload
    //   1638: getfield 451	x:b	[S
    //   1641: arraylength
    //   1642: iconst_4
    //   1643: ishr
    //   1644: istore_0
    //   1645: aload 8
    //   1647: aload 5
    //   1649: iload 19
    //   1651: aaload
    //   1652: iconst_0
    //   1653: iaload
    //   1654: putfield 345	i:l	I
    //   1657: aload 8
    //   1659: aload 5
    //   1661: iload 19
    //   1663: aaload
    //   1664: iconst_1
    //   1665: iaload
    //   1666: putfield 346	i:m	I
    //   1669: aload 8
    //   1671: aload 5
    //   1673: iload 19
    //   1675: aaload
    //   1676: iconst_2
    //   1677: iaload
    //   1678: putfield 347	i:n	I
    //   1681: aload 8
    //   1683: sipush 359
    //   1686: aload 5
    //   1688: iload 19
    //   1690: aaload
    //   1691: bipush 11
    //   1693: iaload
    //   1694: bipush 16
    //   1696: ishr
    //   1697: isub
    //   1698: putfield 348	i:o	I
    //   1701: aload 8
    //   1703: sipush 359
    //   1706: aload 5
    //   1708: iload 19
    //   1710: aaload
    //   1711: bipush 11
    //   1713: iaload
    //   1714: ldc 15
    //   1716: iand
    //   1717: isub
    //   1718: putfield 349	i:p	I
    //   1721: aload 8
    //   1723: invokestatic 525	h:b	(Li;)V
    //   1726: iconst_0
    //   1727: istore 28
    //   1729: aload 5
    //   1731: iload 19
    //   1733: aaload
    //   1734: bipush 9
    //   1736: iaload
    //   1737: ifne +9 -> 1746
    //   1740: iconst_0
    //   1741: istore 8
    //   1743: goto +6 -> 1749
    //   1746: iconst_1
    //   1747: istore 8
    //   1749: iconst_0
    //   1750: istore_3
    //   1751: goto +2203 -> 3954
    //   1754: aload 20
    //   1756: iload 29
    //   1758: iaload
    //   1759: iload 23
    //   1761: if_icmplt +61 -> 1822
    //   1764: aload 20
    //   1766: iload 29
    //   1768: iaload
    //   1769: iload 23
    //   1771: isub
    //   1772: istore 19
    //   1774: aload 6
    //   1776: aload 4
    //   1778: iload 19
    //   1780: aaload
    //   1781: iconst_3
    //   1782: iaload
    //   1783: aaload
    //   1784: aload 4
    //   1786: iload 19
    //   1788: aaload
    //   1789: iconst_4
    //   1790: iaload
    //   1791: iconst_1
    //   1792: isub
    //   1793: iaload
    //   1794: aload 4
    //   1796: iload 19
    //   1798: aaload
    //   1799: iconst_0
    //   1800: iaload
    //   1801: aload 4
    //   1803: iload 19
    //   1805: aaload
    //   1806: iconst_1
    //   1807: iaload
    //   1808: aload 4
    //   1810: iload 19
    //   1812: aaload
    //   1813: iconst_2
    //   1814: iaload
    //   1815: aload_2
    //   1816: invokestatic 544	m:a	(IIII[[I)V
    //   1819: goto +3037 -> 4856
    //   1822: aload 20
    //   1824: iload 29
    //   1826: iaload
    //   1827: iload 22
    //   1829: if_icmplt +558 -> 2387
    //   1832: aload 20
    //   1834: iload 29
    //   1836: iaload
    //   1837: iload 22
    //   1839: isub
    //   1840: istore 19
    //   1842: aload 7
    //   1844: iload 19
    //   1846: aaload
    //   1847: dup
    //   1848: astore 8
    //   1850: getfield 351	i:r	Z
    //   1853: istore_3
    //   1854: aload 8
    //   1856: getfield 335	i:b	[S
    //   1859: astore 10
    //   1861: aload 8
    //   1863: getfield 335	i:b	[S
    //   1866: arraylength
    //   1867: iconst_4
    //   1868: ishr
    //   1869: istore_0
    //   1870: aload_2
    //   1871: aload 8
    //   1873: astore 18
    //   1875: astore 17
    //   1877: aload 18
    //   1879: getfield 352	i:s	B
    //   1882: bipush 39
    //   1884: if_icmple +13 -> 1897
    //   1887: aload 18
    //   1889: getfield 352	i:s	B
    //   1892: bipush 44
    //   1894: if_icmplt +368 -> 2262
    //   1897: getstatic 308	g:d	[Lx;
    //   1900: aload 18
    //   1902: getfield 352	i:s	B
    //   1905: aaload
    //   1906: astore 32
    //   1908: getstatic 239	g:ab	[I
    //   1911: iconst_0
    //   1912: iaload
    //   1913: aload 18
    //   1915: getfield 345	i:l	I
    //   1918: isub
    //   1919: i2l
    //   1920: getstatic 330	h:a	[I
    //   1923: getstatic 238	g:aa	I
    //   1926: iaload
    //   1927: i2l
    //   1928: lmul
    //   1929: getstatic 239	g:ab	[I
    //   1932: iconst_1
    //   1933: iaload
    //   1934: aload 18
    //   1936: getfield 346	i:m	I
    //   1939: isub
    //   1940: i2l
    //   1941: getstatic 332	h:d	[I
    //   1944: getstatic 238	g:aa	I
    //   1947: iaload
    //   1948: i2l
    //   1949: lmul
    //   1950: lsub
    //   1951: bipush 16
    //   1953: lshr
    //   1954: l2i
    //   1955: istore 28
    //   1957: getstatic 239	g:ab	[I
    //   1960: iconst_0
    //   1961: iaload
    //   1962: aload 18
    //   1964: getfield 345	i:l	I
    //   1967: isub
    //   1968: i2l
    //   1969: getstatic 332	h:d	[I
    //   1972: getstatic 238	g:aa	I
    //   1975: iaload
    //   1976: i2l
    //   1977: lmul
    //   1978: getstatic 239	g:ab	[I
    //   1981: iconst_1
    //   1982: iaload
    //   1983: aload 18
    //   1985: getfield 346	i:m	I
    //   1988: isub
    //   1989: i2l
    //   1990: getstatic 330	h:a	[I
    //   1993: getstatic 238	g:aa	I
    //   1996: iaload
    //   1997: i2l
    //   1998: lmul
    //   1999: ladd
    //   2000: bipush 16
    //   2002: lshr
    //   2003: l2i
    //   2004: istore 30
    //   2006: getstatic 239	g:ab	[I
    //   2009: iconst_2
    //   2010: iaload
    //   2011: aload 18
    //   2013: getfield 347	i:n	I
    //   2016: isub
    //   2017: i2l
    //   2018: getstatic 330	h:a	[I
    //   2021: getstatic 210	g:Z	I
    //   2024: iaload
    //   2025: i2l
    //   2026: lmul
    //   2027: iload 30
    //   2029: i2l
    //   2030: getstatic 332	h:d	[I
    //   2033: getstatic 210	g:Z	I
    //   2036: iaload
    //   2037: i2l
    //   2038: lmul
    //   2039: lsub
    //   2040: bipush 16
    //   2042: lshr
    //   2043: l2i
    //   2044: istore 31
    //   2046: getstatic 239	g:ab	[I
    //   2049: iconst_2
    //   2050: iaload
    //   2051: aload 18
    //   2053: getfield 347	i:n	I
    //   2056: isub
    //   2057: i2l
    //   2058: getstatic 332	h:d	[I
    //   2061: getstatic 210	g:Z	I
    //   2064: iaload
    //   2065: i2l
    //   2066: lmul
    //   2067: iload 30
    //   2069: i2l
    //   2070: getstatic 330	h:a	[I
    //   2073: getstatic 210	g:Z	I
    //   2076: iaload
    //   2077: i2l
    //   2078: lmul
    //   2079: ladd
    //   2080: bipush 16
    //   2082: lshr
    //   2083: l2i
    //   2084: istore 30
    //   2086: iload 28
    //   2088: bipush 16
    //   2090: ishr
    //   2091: istore 28
    //   2093: iload 30
    //   2095: bipush 16
    //   2097: ishr
    //   2098: istore 30
    //   2100: iload 31
    //   2102: bipush 16
    //   2104: ishr
    //   2105: dup
    //   2106: istore 31
    //   2108: i2l
    //   2109: aload 17
    //   2111: iconst_0
    //   2112: aaload
    //   2113: iconst_2
    //   2114: iaload
    //   2115: i2l
    //   2116: lmul
    //   2117: lconst_0
    //   2118: lcmp
    //   2119: ifle +139 -> 2258
    //   2122: iload 30
    //   2124: i2l
    //   2125: aload 17
    //   2127: iconst_1
    //   2128: aaload
    //   2129: iconst_1
    //   2130: iaload
    //   2131: i2l
    //   2132: lmul
    //   2133: iload 31
    //   2135: i2l
    //   2136: aload 17
    //   2138: iconst_1
    //   2139: aaload
    //   2140: iconst_2
    //   2141: iaload
    //   2142: i2l
    //   2143: lmul
    //   2144: ladd
    //   2145: aload 32
    //   2147: getfield 452	x:c	I
    //   2150: ineg
    //   2151: i2l
    //   2152: lcmp
    //   2153: ifle +105 -> 2258
    //   2156: iload 30
    //   2158: i2l
    //   2159: aload 17
    //   2161: iconst_2
    //   2162: aaload
    //   2163: iconst_1
    //   2164: iaload
    //   2165: i2l
    //   2166: lmul
    //   2167: iload 31
    //   2169: i2l
    //   2170: aload 17
    //   2172: iconst_2
    //   2173: aaload
    //   2174: iconst_2
    //   2175: iaload
    //   2176: i2l
    //   2177: lmul
    //   2178: ladd
    //   2179: aload 32
    //   2181: getfield 452	x:c	I
    //   2184: ineg
    //   2185: i2l
    //   2186: lcmp
    //   2187: ifle +71 -> 2258
    //   2190: iload 28
    //   2192: i2l
    //   2193: aload 17
    //   2195: iconst_3
    //   2196: aaload
    //   2197: iconst_0
    //   2198: iaload
    //   2199: i2l
    //   2200: lmul
    //   2201: iload 31
    //   2203: i2l
    //   2204: aload 17
    //   2206: iconst_3
    //   2207: aaload
    //   2208: iconst_2
    //   2209: iaload
    //   2210: i2l
    //   2211: lmul
    //   2212: ladd
    //   2213: aload 32
    //   2215: getfield 453	x:d	I
    //   2218: ineg
    //   2219: i2l
    //   2220: lcmp
    //   2221: ifle +37 -> 2258
    //   2224: iload 28
    //   2226: i2l
    //   2227: aload 17
    //   2229: iconst_4
    //   2230: aaload
    //   2231: iconst_0
    //   2232: iaload
    //   2233: i2l
    //   2234: lmul
    //   2235: iload 31
    //   2237: i2l
    //   2238: aload 17
    //   2240: iconst_4
    //   2241: aaload
    //   2242: iconst_2
    //   2243: iaload
    //   2244: i2l
    //   2245: lmul
    //   2246: ladd
    //   2247: aload 32
    //   2249: getfield 453	x:d	I
    //   2252: ineg
    //   2253: i2l
    //   2254: lcmp
    //   2255: ifgt +7 -> 2262
    //   2258: iconst_1
    //   2259: goto +4 -> 2263
    //   2262: iconst_0
    //   2263: ifne +2593 -> 4856
    //   2266: aload 8
    //   2268: iconst_0
    //   2269: invokestatic 512	h:a	(Li;I)V
    //   2272: aload 8
    //   2274: getfield 337	i:d	S
    //   2277: putstatic 314	g:j	I
    //   2280: getstatic 326	g:v	Z
    //   2283: ifeq +91 -> 2374
    //   2286: getstatic 278	g:bN	I
    //   2289: aload 8
    //   2291: getfield 345	i:l	I
    //   2294: isub
    //   2295: bipush 16
    //   2297: ishr
    //   2298: istore 30
    //   2300: getstatic 279	g:bO	I
    //   2303: aload 8
    //   2305: getfield 346	i:m	I
    //   2308: isub
    //   2309: bipush 16
    //   2311: ishr
    //   2312: istore 31
    //   2314: ldc2_w 157
    //   2317: iload 30
    //   2319: iload 30
    //   2321: imul
    //   2322: iload 31
    //   2324: iload 31
    //   2326: imul
    //   2327: iadd
    //   2328: i2l
    //   2329: lmul
    //   2330: bipush 28
    //   2332: lshr
    //   2333: l2i
    //   2334: dup
    //   2335: istore 30
    //   2337: sipush 255
    //   2340: if_icmple +8 -> 2348
    //   2343: sipush 255
    //   2346: istore 30
    //   2348: getstatic 314	g:j	I
    //   2351: sipush 255
    //   2354: iload 30
    //   2356: isub
    //   2357: iadd
    //   2358: dup
    //   2359: putstatic 314	g:j	I
    //   2362: sipush 255
    //   2365: if_icmple +9 -> 2374
    //   2368: sipush 255
    //   2371: putstatic 314	g:j	I
    //   2374: aload 8
    //   2376: getfield 336	i:c	Z
    //   2379: istore 8
    //   2381: iconst_0
    //   2382: istore 28
    //   2384: goto +1570 -> 3954
    //   2387: aload 20
    //   2389: iload 29
    //   2391: iaload
    //   2392: istore 19
    //   2394: getstatic 313	g:i	[Lq;
    //   2397: iload 19
    //   2399: aaload
    //   2400: getfield 387	q:f	[S
    //   2403: astore 10
    //   2405: getstatic 313	g:i	[Lq;
    //   2408: iload 19
    //   2410: aaload
    //   2411: getfield 379	q:M	B
    //   2414: ifeq +23 -> 2437
    //   2417: getstatic 312	g:h	[Lt;
    //   2420: getstatic 313	g:i	[Lq;
    //   2423: iload 19
    //   2425: aaload
    //   2426: getfield 379	q:M	B
    //   2429: aaload
    //   2430: getfield 434	t:e	I
    //   2433: istore_0
    //   2434: goto +12 -> 2446
    //   2437: getstatic 312	g:h	[Lt;
    //   2440: iconst_1
    //   2441: aaload
    //   2442: getfield 434	t:e	I
    //   2445: istore_0
    //   2446: getstatic 313	g:i	[Lq;
    //   2449: iload 19
    //   2451: aaload
    //   2452: invokestatic 528	h:c	(Lq;)V
    //   2455: getstatic 313	g:i	[Lq;
    //   2458: iload 19
    //   2460: aaload
    //   2461: getfield 392	q:k	Z
    //   2464: ifne +1482 -> 3946
    //   2467: getstatic 313	g:i	[Lq;
    //   2470: iload 19
    //   2472: aaload
    //   2473: getfield 379	q:M	B
    //   2476: iconst_3
    //   2477: if_icmpge +1469 -> 3946
    //   2480: getstatic 313	g:i	[Lq;
    //   2483: iload 19
    //   2485: aaload
    //   2486: getfield 382	q:P	Z
    //   2489: ifeq +1457 -> 3946
    //   2492: getstatic 313	g:i	[Lq;
    //   2495: iload 19
    //   2497: aaload
    //   2498: getfield 381	q:O	B
    //   2501: ifeq +1445 -> 3946
    //   2504: getstatic 281	g:ba	Li;
    //   2507: dup
    //   2508: astore 8
    //   2510: getstatic 313	g:i	[Lq;
    //   2513: iload 19
    //   2515: aaload
    //   2516: astore 18
    //   2518: astore 17
    //   2520: aload 18
    //   2522: getfield 379	q:M	B
    //   2525: iconst_2
    //   2526: if_icmpge +580 -> 3106
    //   2529: aload 18
    //   2531: getfield 381	q:O	B
    //   2534: tableswitch	default:+569->3103, 1:+30->2564, 2:+146->2680, 3:+291->2825, 4:+436->2970
    //   2564: aload 18
    //   2566: getfield 389	q:h	S
    //   2569: bipush 8
    //   2571: if_icmpge +532 -> 3103
    //   2574: aload 17
    //   2576: aload 18
    //   2578: getfield 402	q:w	I
    //   2581: getstatic 296	g:bp	[I
    //   2584: aload 18
    //   2586: getfield 389	q:h	S
    //   2589: iconst_1
    //   2590: ishl
    //   2591: iaload
    //   2592: getstatic 332	h:d	[I
    //   2595: aload 18
    //   2597: getfield 371	q:D	S
    //   2600: iaload
    //   2601: ineg
    //   2602: imul
    //   2603: iadd
    //   2604: putfield 345	i:l	I
    //   2607: aload 17
    //   2609: aload 18
    //   2611: getfield 403	q:x	I
    //   2614: getstatic 296	g:bp	[I
    //   2617: aload 18
    //   2619: getfield 389	q:h	S
    //   2622: iconst_1
    //   2623: ishl
    //   2624: iaload
    //   2625: getstatic 330	h:a	[I
    //   2628: aload 18
    //   2630: getfield 371	q:D	S
    //   2633: iaload
    //   2634: ineg
    //   2635: imul
    //   2636: iadd
    //   2637: putfield 346	i:m	I
    //   2640: aload 17
    //   2642: aload 18
    //   2644: getfield 404	q:y	I
    //   2647: getstatic 296	g:bp	[I
    //   2650: aload 18
    //   2652: getfield 389	q:h	S
    //   2655: iconst_1
    //   2656: ishl
    //   2657: iconst_1
    //   2658: iadd
    //   2659: iaload
    //   2660: bipush 16
    //   2662: ishl
    //   2663: iadd
    //   2664: getstatic 333	h:e	[I
    //   2667: aload 18
    //   2669: getfield 379	q:M	B
    //   2672: iaload
    //   2673: isub
    //   2674: putfield 347	i:n	I
    //   2677: goto +1049 -> 3726
    //   2680: aload 18
    //   2682: getfield 389	q:h	S
    //   2685: bipush 8
    //   2687: isub
    //   2688: dup
    //   2689: istore 28
    //   2691: iflt +412 -> 3103
    //   2694: iload 28
    //   2696: bipush 7
    //   2698: if_icmpgt +405 -> 3103
    //   2701: iload 28
    //   2703: iconst_1
    //   2704: ishl
    //   2705: istore 28
    //   2707: aload 17
    //   2709: aload 18
    //   2711: getfield 402	q:w	I
    //   2714: getstatic 298	g:br	[I
    //   2717: iload 28
    //   2719: iaload
    //   2720: getstatic 332	h:d	[I
    //   2723: aload 18
    //   2725: getfield 371	q:D	S
    //   2728: iaload
    //   2729: ineg
    //   2730: imul
    //   2731: iadd
    //   2732: bipush -26
    //   2734: getstatic 330	h:a	[I
    //   2737: aload 18
    //   2739: getfield 371	q:D	S
    //   2742: iaload
    //   2743: imul
    //   2744: iadd
    //   2745: putfield 345	i:l	I
    //   2748: aload 17
    //   2750: aload 18
    //   2752: getfield 403	q:x	I
    //   2755: getstatic 298	g:br	[I
    //   2758: iload 28
    //   2760: iaload
    //   2761: getstatic 330	h:a	[I
    //   2764: aload 18
    //   2766: getfield 371	q:D	S
    //   2769: iaload
    //   2770: ineg
    //   2771: imul
    //   2772: iadd
    //   2773: bipush -26
    //   2775: getstatic 332	h:d	[I
    //   2778: aload 18
    //   2780: getfield 371	q:D	S
    //   2783: iaload
    //   2784: ineg
    //   2785: imul
    //   2786: iadd
    //   2787: putfield 346	i:m	I
    //   2790: aload 17
    //   2792: aload 18
    //   2794: getfield 404	q:y	I
    //   2797: getstatic 298	g:br	[I
    //   2800: iload 28
    //   2802: iconst_1
    //   2803: iadd
    //   2804: iaload
    //   2805: bipush 16
    //   2807: ishl
    //   2808: iadd
    //   2809: getstatic 333	h:e	[I
    //   2812: aload 18
    //   2814: getfield 379	q:M	B
    //   2817: iaload
    //   2818: isub
    //   2819: putfield 347	i:n	I
    //   2822: goto +904 -> 3726
    //   2825: aload 18
    //   2827: getfield 389	q:h	S
    //   2830: bipush 8
    //   2832: isub
    //   2833: dup
    //   2834: istore 30
    //   2836: iflt +267 -> 3103
    //   2839: iload 30
    //   2841: bipush 7
    //   2843: if_icmpgt +260 -> 3103
    //   2846: iload 30
    //   2848: iconst_1
    //   2849: ishl
    //   2850: istore 30
    //   2852: aload 17
    //   2854: aload 18
    //   2856: getfield 402	q:w	I
    //   2859: getstatic 295	g:bo	[I
    //   2862: iload 30
    //   2864: iaload
    //   2865: getstatic 332	h:d	[I
    //   2868: aload 18
    //   2870: getfield 371	q:D	S
    //   2873: iaload
    //   2874: ineg
    //   2875: imul
    //   2876: iadd
    //   2877: bipush -26
    //   2879: getstatic 330	h:a	[I
    //   2882: aload 18
    //   2884: getfield 371	q:D	S
    //   2887: iaload
    //   2888: imul
    //   2889: iadd
    //   2890: putfield 345	i:l	I
    //   2893: aload 17
    //   2895: aload 18
    //   2897: getfield 403	q:x	I
    //   2900: getstatic 295	g:bo	[I
    //   2903: iload 30
    //   2905: iaload
    //   2906: getstatic 330	h:a	[I
    //   2909: aload 18
    //   2911: getfield 371	q:D	S
    //   2914: iaload
    //   2915: ineg
    //   2916: imul
    //   2917: iadd
    //   2918: bipush -26
    //   2920: getstatic 332	h:d	[I
    //   2923: aload 18
    //   2925: getfield 371	q:D	S
    //   2928: iaload
    //   2929: ineg
    //   2930: imul
    //   2931: iadd
    //   2932: putfield 346	i:m	I
    //   2935: aload 17
    //   2937: aload 18
    //   2939: getfield 404	q:y	I
    //   2942: getstatic 295	g:bo	[I
    //   2945: iload 30
    //   2947: iconst_1
    //   2948: iadd
    //   2949: iaload
    //   2950: bipush 16
    //   2952: ishl
    //   2953: iadd
    //   2954: getstatic 333	h:e	[I
    //   2957: aload 18
    //   2959: getfield 379	q:M	B
    //   2962: iaload
    //   2963: isub
    //   2964: putfield 347	i:n	I
    //   2967: goto +759 -> 3726
    //   2970: aload 18
    //   2972: getfield 389	q:h	S
    //   2975: bipush 8
    //   2977: isub
    //   2978: dup
    //   2979: istore 31
    //   2981: iflt +122 -> 3103
    //   2984: iload 31
    //   2986: bipush 7
    //   2988: if_icmpgt +115 -> 3103
    //   2991: iload 31
    //   2993: iconst_1
    //   2994: ishl
    //   2995: istore 31
    //   2997: aload 17
    //   2999: aload 18
    //   3001: getfield 402	q:w	I
    //   3004: getstatic 297	g:bq	[I
    //   3007: iload 31
    //   3009: iaload
    //   3010: getstatic 332	h:d	[I
    //   3013: aload 18
    //   3015: getfield 371	q:D	S
    //   3018: iaload
    //   3019: ineg
    //   3020: imul
    //   3021: iadd
    //   3022: bipush -37
    //   3024: getstatic 330	h:a	[I
    //   3027: aload 18
    //   3029: getfield 371	q:D	S
    //   3032: iaload
    //   3033: imul
    //   3034: iadd
    //   3035: putfield 345	i:l	I
    //   3038: aload 17
    //   3040: aload 18
    //   3042: getfield 403	q:x	I
    //   3045: getstatic 297	g:bq	[I
    //   3048: iload 31
    //   3050: iaload
    //   3051: getstatic 330	h:a	[I
    //   3054: aload 18
    //   3056: getfield 371	q:D	S
    //   3059: iaload
    //   3060: ineg
    //   3061: imul
    //   3062: iadd
    //   3063: bipush -37
    //   3065: getstatic 332	h:d	[I
    //   3068: aload 18
    //   3070: getfield 371	q:D	S
    //   3073: iaload
    //   3074: ineg
    //   3075: imul
    //   3076: iadd
    //   3077: putfield 346	i:m	I
    //   3080: aload 17
    //   3082: aload 18
    //   3084: getfield 404	q:y	I
    //   3087: ldc 42
    //   3089: iadd
    //   3090: getstatic 333	h:e	[I
    //   3093: aload 18
    //   3095: getfield 379	q:M	B
    //   3098: iaload
    //   3099: isub
    //   3100: putfield 347	i:n	I
    //   3103: goto +623 -> 3726
    //   3106: aload 18
    //   3108: getfield 379	q:M	B
    //   3111: iconst_2
    //   3112: if_icmpne +614 -> 3726
    //   3115: aload 18
    //   3117: getfield 381	q:O	B
    //   3120: tableswitch	default:+606->3726, 1:+32->3152, 2:+171->3291, 3:+319->3439, 4:+467->3587
    //   3152: aload 18
    //   3154: getfield 389	q:h	S
    //   3157: bipush 10
    //   3159: isub
    //   3160: istore 28
    //   3162: aload 17
    //   3164: aload 18
    //   3166: getfield 402	q:w	I
    //   3169: getstatic 230	g:aS	[B
    //   3172: iload 28
    //   3174: iconst_1
    //   3175: ishl
    //   3176: baload
    //   3177: getstatic 332	h:d	[I
    //   3180: aload 18
    //   3182: getfield 371	q:D	S
    //   3185: iaload
    //   3186: ineg
    //   3187: imul
    //   3188: iadd
    //   3189: getstatic 230	g:aS	[B
    //   3192: iload 28
    //   3194: iconst_1
    //   3195: ishl
    //   3196: iconst_1
    //   3197: iadd
    //   3198: baload
    //   3199: getstatic 330	h:a	[I
    //   3202: aload 18
    //   3204: getfield 371	q:D	S
    //   3207: iaload
    //   3208: imul
    //   3209: iadd
    //   3210: putfield 345	i:l	I
    //   3213: aload 17
    //   3215: aload 18
    //   3217: getfield 403	q:x	I
    //   3220: getstatic 230	g:aS	[B
    //   3223: iload 28
    //   3225: iconst_1
    //   3226: ishl
    //   3227: baload
    //   3228: getstatic 330	h:a	[I
    //   3231: aload 18
    //   3233: getfield 371	q:D	S
    //   3236: iaload
    //   3237: ineg
    //   3238: imul
    //   3239: iadd
    //   3240: getstatic 230	g:aS	[B
    //   3243: iload 28
    //   3245: iconst_1
    //   3246: ishl
    //   3247: iconst_1
    //   3248: iadd
    //   3249: baload
    //   3250: getstatic 332	h:d	[I
    //   3253: aload 18
    //   3255: getfield 371	q:D	S
    //   3258: iaload
    //   3259: ineg
    //   3260: imul
    //   3261: iadd
    //   3262: putfield 346	i:m	I
    //   3265: aload 17
    //   3267: aload 18
    //   3269: getfield 404	q:y	I
    //   3272: ldc 40
    //   3274: iadd
    //   3275: getstatic 333	h:e	[I
    //   3278: aload 18
    //   3280: getfield 379	q:M	B
    //   3283: iaload
    //   3284: isub
    //   3285: putfield 347	i:n	I
    //   3288: goto +438 -> 3726
    //   3291: aload 18
    //   3293: getfield 389	q:h	S
    //   3296: bipush 20
    //   3298: isub
    //   3299: dup
    //   3300: istore 30
    //   3302: iflt +424 -> 3726
    //   3305: iload 30
    //   3307: bipush 20
    //   3309: if_icmpgt +417 -> 3726
    //   3312: iload 30
    //   3314: iconst_1
    //   3315: ishl
    //   3316: istore 30
    //   3318: aload 17
    //   3320: aload 18
    //   3322: getfield 402	q:w	I
    //   3325: getstatic 232	g:aU	[B
    //   3328: iload 30
    //   3330: baload
    //   3331: getstatic 332	h:d	[I
    //   3334: aload 18
    //   3336: getfield 371	q:D	S
    //   3339: iaload
    //   3340: ineg
    //   3341: imul
    //   3342: iadd
    //   3343: getstatic 232	g:aU	[B
    //   3346: iload 30
    //   3348: iconst_1
    //   3349: iadd
    //   3350: baload
    //   3351: getstatic 330	h:a	[I
    //   3354: aload 18
    //   3356: getfield 371	q:D	S
    //   3359: iaload
    //   3360: imul
    //   3361: iadd
    //   3362: putfield 345	i:l	I
    //   3365: aload 17
    //   3367: aload 18
    //   3369: getfield 403	q:x	I
    //   3372: getstatic 232	g:aU	[B
    //   3375: iload 30
    //   3377: baload
    //   3378: getstatic 330	h:a	[I
    //   3381: aload 18
    //   3383: getfield 371	q:D	S
    //   3386: iaload
    //   3387: ineg
    //   3388: imul
    //   3389: iadd
    //   3390: getstatic 232	g:aU	[B
    //   3393: iload 30
    //   3395: iconst_1
    //   3396: iadd
    //   3397: baload
    //   3398: getstatic 332	h:d	[I
    //   3401: aload 18
    //   3403: getfield 371	q:D	S
    //   3406: iaload
    //   3407: ineg
    //   3408: imul
    //   3409: iadd
    //   3410: putfield 346	i:m	I
    //   3413: aload 17
    //   3415: aload 18
    //   3417: getfield 404	q:y	I
    //   3420: ldc 41
    //   3422: iadd
    //   3423: getstatic 333	h:e	[I
    //   3426: aload 18
    //   3428: getfield 379	q:M	B
    //   3431: iaload
    //   3432: isub
    //   3433: putfield 347	i:n	I
    //   3436: goto +290 -> 3726
    //   3439: aload 18
    //   3441: getfield 389	q:h	S
    //   3444: bipush 20
    //   3446: isub
    //   3447: dup
    //   3448: istore 31
    //   3450: iflt +276 -> 3726
    //   3453: iload 31
    //   3455: bipush 20
    //   3457: if_icmpgt +269 -> 3726
    //   3460: iload 31
    //   3462: iconst_1
    //   3463: ishl
    //   3464: istore 31
    //   3466: aload 17
    //   3468: aload 18
    //   3470: getfield 402	q:w	I
    //   3473: getstatic 229	g:aR	[B
    //   3476: iload 31
    //   3478: baload
    //   3479: getstatic 332	h:d	[I
    //   3482: aload 18
    //   3484: getfield 371	q:D	S
    //   3487: iaload
    //   3488: ineg
    //   3489: imul
    //   3490: iadd
    //   3491: getstatic 229	g:aR	[B
    //   3494: iload 31
    //   3496: iconst_1
    //   3497: iadd
    //   3498: baload
    //   3499: getstatic 330	h:a	[I
    //   3502: aload 18
    //   3504: getfield 371	q:D	S
    //   3507: iaload
    //   3508: imul
    //   3509: iadd
    //   3510: putfield 345	i:l	I
    //   3513: aload 17
    //   3515: aload 18
    //   3517: getfield 403	q:x	I
    //   3520: getstatic 229	g:aR	[B
    //   3523: iload 31
    //   3525: baload
    //   3526: getstatic 330	h:a	[I
    //   3529: aload 18
    //   3531: getfield 371	q:D	S
    //   3534: iaload
    //   3535: ineg
    //   3536: imul
    //   3537: iadd
    //   3538: getstatic 229	g:aR	[B
    //   3541: iload 31
    //   3543: iconst_1
    //   3544: iadd
    //   3545: baload
    //   3546: getstatic 332	h:d	[I
    //   3549: aload 18
    //   3551: getfield 371	q:D	S
    //   3554: iaload
    //   3555: ineg
    //   3556: imul
    //   3557: iadd
    //   3558: putfield 346	i:m	I
    //   3561: aload 17
    //   3563: aload 18
    //   3565: getfield 404	q:y	I
    //   3568: ldc 39
    //   3570: iadd
    //   3571: getstatic 333	h:e	[I
    //   3574: aload 18
    //   3576: getfield 379	q:M	B
    //   3579: iaload
    //   3580: isub
    //   3581: putfield 347	i:n	I
    //   3584: goto +142 -> 3726
    //   3587: aload 18
    //   3589: getfield 389	q:h	S
    //   3592: bipush 20
    //   3594: isub
    //   3595: dup
    //   3596: istore 32
    //   3598: iflt +128 -> 3726
    //   3601: iload 32
    //   3603: bipush 20
    //   3605: if_icmpgt +121 -> 3726
    //   3608: iload 32
    //   3610: iconst_1
    //   3611: ishl
    //   3612: dup
    //   3613: istore 32
    //   3615: bipush 10
    //   3617: if_icmpge +109 -> 3726
    //   3620: aload 17
    //   3622: aload 18
    //   3624: getfield 402	q:w	I
    //   3627: getstatic 231	g:aT	[B
    //   3630: iload 32
    //   3632: baload
    //   3633: getstatic 332	h:d	[I
    //   3636: aload 18
    //   3638: getfield 371	q:D	S
    //   3641: iaload
    //   3642: ineg
    //   3643: imul
    //   3644: iadd
    //   3645: bipush -26
    //   3647: getstatic 330	h:a	[I
    //   3650: aload 18
    //   3652: getfield 371	q:D	S
    //   3655: iaload
    //   3656: imul
    //   3657: iadd
    //   3658: putfield 345	i:l	I
    //   3661: aload 17
    //   3663: aload 18
    //   3665: getfield 403	q:x	I
    //   3668: getstatic 231	g:aT	[B
    //   3671: iload 32
    //   3673: baload
    //   3674: getstatic 330	h:a	[I
    //   3677: aload 18
    //   3679: getfield 371	q:D	S
    //   3682: iaload
    //   3683: ineg
    //   3684: imul
    //   3685: iadd
    //   3686: bipush -26
    //   3688: getstatic 332	h:d	[I
    //   3691: aload 18
    //   3693: getfield 371	q:D	S
    //   3696: iaload
    //   3697: ineg
    //   3698: imul
    //   3699: iadd
    //   3700: putfield 346	i:m	I
    //   3703: aload 17
    //   3705: aload 18
    //   3707: getfield 404	q:y	I
    //   3710: ldc 42
    //   3712: iadd
    //   3713: getstatic 333	h:e	[I
    //   3716: aload 18
    //   3718: getfield 379	q:M	B
    //   3721: iaload
    //   3722: isub
    //   3723: putfield 347	i:n	I
    //   3726: aload 8
    //   3728: iconst_0
    //   3729: putfield 348	i:o	I
    //   3732: aload 8
    //   3734: sipush 359
    //   3737: getstatic 313	g:i	[Lq;
    //   3740: iload 19
    //   3742: aaload
    //   3743: getfield 371	q:D	S
    //   3746: isub
    //   3747: putfield 349	i:p	I
    //   3750: aload 8
    //   3752: getstatic 313	g:i	[Lq;
    //   3755: iload 19
    //   3757: aaload
    //   3758: getfield 381	q:O	B
    //   3761: bipush 51
    //   3763: iadd
    //   3764: i2b
    //   3765: putfield 352	i:s	B
    //   3768: getstatic 313	g:i	[Lq;
    //   3771: iload 19
    //   3773: aaload
    //   3774: getfield 379	q:M	B
    //   3777: dup
    //   3778: istore 30
    //   3780: ifne +6 -> 3786
    //   3783: iconst_1
    //   3784: istore 30
    //   3786: aload 8
    //   3788: getstatic 308	g:d	[Lx;
    //   3791: aload 8
    //   3793: getfield 352	i:s	B
    //   3796: aaload
    //   3797: getfield 451	x:b	[S
    //   3800: putfield 335	i:b	[S
    //   3803: aload 8
    //   3805: getstatic 308	g:d	[Lx;
    //   3808: aload 8
    //   3810: getfield 352	i:s	B
    //   3813: aaload
    //   3814: getfield 450	x:a	[S
    //   3817: putfield 334	i:a	[S
    //   3820: aload 8
    //   3822: getstatic 312	g:h	[Lt;
    //   3825: iload 30
    //   3827: aaload
    //   3828: getfield 433	t:d	I
    //   3831: invokestatic 512	h:a	(Li;I)V
    //   3834: aload 8
    //   3836: getfield 335	i:b	[S
    //   3839: arraylength
    //   3840: iconst_4
    //   3841: ishr
    //   3842: istore 31
    //   3844: iload_0
    //   3845: iconst_4
    //   3846: ishl
    //   3847: istore_3
    //   3848: iconst_0
    //   3849: istore 17
    //   3851: getstatic 312	g:h	[Lt;
    //   3854: iload 30
    //   3856: aaload
    //   3857: getfield 433	t:d	I
    //   3860: iconst_3
    //   3861: imul
    //   3862: i2s
    //   3863: istore 18
    //   3865: iconst_0
    //   3866: istore 28
    //   3868: goto +66 -> 3934
    //   3871: aload 8
    //   3873: getfield 335	i:b	[S
    //   3876: iload 17
    //   3878: aload 10
    //   3880: iload_3
    //   3881: bipush 16
    //   3883: invokestatic 538	java/lang/System:arraycopy	(Ljava/lang/Object;ILjava/lang/Object;II)V
    //   3886: aload 10
    //   3888: iload_3
    //   3889: dup2
    //   3890: saload
    //   3891: iload 18
    //   3893: iadd
    //   3894: i2s
    //   3895: sastore
    //   3896: aload 10
    //   3898: iload_3
    //   3899: iconst_1
    //   3900: iadd
    //   3901: dup2
    //   3902: saload
    //   3903: iload 18
    //   3905: iadd
    //   3906: i2s
    //   3907: sastore
    //   3908: aload 10
    //   3910: iload_3
    //   3911: iconst_2
    //   3912: iadd
    //   3913: dup2
    //   3914: saload
    //   3915: iload 18
    //   3917: iadd
    //   3918: i2s
    //   3919: sastore
    //   3920: iinc 3 16
    //   3923: iload 17
    //   3925: bipush 16
    //   3927: iadd
    //   3928: i2s
    //   3929: istore 17
    //   3931: iinc 28 1
    //   3934: iload 28
    //   3936: iload 31
    //   3938: if_icmplt -67 -> 3871
    //   3941: iload_0
    //   3942: iload 31
    //   3944: iadd
    //   3945: istore_0
    //   3946: iconst_0
    //   3947: istore_3
    //   3948: iconst_1
    //   3949: istore 28
    //   3951: iconst_1
    //   3952: istore 8
    //   3954: iload 28
    //   3956: ifeq +14 -> 3970
    //   3959: aload 10
    //   3961: aload 9
    //   3963: iload_0
    //   3964: invokestatic 521	h:a	([S[II)V
    //   3967: goto +41 -> 4008
    //   3970: aload 10
    //   3972: bipush 9
    //   3974: saload
    //   3975: dup
    //   3976: putstatic 185	g:A	I
    //   3979: bipush 6
    //   3981: if_icmpge +20 -> 4001
    //   3984: getstatic 185	g:A	I
    //   3987: aload 5
    //   3989: iload 19
    //   3991: aaload
    //   3992: bipush 12
    //   3994: iaload
    //   3995: iconst_1
    //   3996: isub
    //   3997: iadd
    //   3998: putstatic 185	g:A	I
    //   4001: aload 10
    //   4003: aload 9
    //   4005: invokestatic 520	h:a	([S[I)V
    //   4008: iload_0
    //   4009: iconst_1
    //   4010: isub
    //   4011: istore 31
    //   4013: goto +636 -> 4649
    //   4016: aload 21
    //   4018: iload 31
    //   4020: iaload
    //   4021: iconst_4
    //   4022: ishl
    //   4023: istore 30
    //   4025: iload 8
    //   4027: ifeq +195 -> 4222
    //   4030: aload 10
    //   4032: iload 30
    //   4034: bipush 13
    //   4036: iadd
    //   4037: saload
    //   4038: istore_0
    //   4039: aload 10
    //   4041: iload 30
    //   4043: bipush 14
    //   4045: iadd
    //   4046: saload
    //   4047: istore 17
    //   4049: aload 10
    //   4051: iload 30
    //   4053: bipush 15
    //   4055: iadd
    //   4056: saload
    //   4057: istore 18
    //   4059: aload 10
    //   4061: iload 30
    //   4063: bipush 13
    //   4065: iadd
    //   4066: iload_0
    //   4067: iload 24
    //   4069: imul
    //   4070: iload 17
    //   4072: iload 25
    //   4074: imul
    //   4075: isub
    //   4076: bipush 16
    //   4078: ishr
    //   4079: sastore
    //   4080: aload 10
    //   4082: iload 30
    //   4084: bipush 14
    //   4086: iadd
    //   4087: iload_0
    //   4088: iload 25
    //   4090: imul
    //   4091: iload 17
    //   4093: iload 24
    //   4095: imul
    //   4096: iadd
    //   4097: bipush 16
    //   4099: ishr
    //   4100: sastore
    //   4101: aload 10
    //   4103: iload 30
    //   4105: bipush 15
    //   4107: iadd
    //   4108: iload 18
    //   4110: iload 26
    //   4112: imul
    //   4113: aload 10
    //   4115: iload 30
    //   4117: bipush 14
    //   4119: iadd
    //   4120: saload
    //   4121: iload 27
    //   4123: imul
    //   4124: isub
    //   4125: bipush 16
    //   4127: ishr
    //   4128: sastore
    //   4129: aload 10
    //   4131: iload 30
    //   4133: bipush 14
    //   4135: iadd
    //   4136: iload 18
    //   4138: iload 27
    //   4140: imul
    //   4141: aload 10
    //   4143: iload 30
    //   4145: bipush 14
    //   4147: iadd
    //   4148: saload
    //   4149: iload 26
    //   4151: imul
    //   4152: iadd
    //   4153: bipush 16
    //   4155: ishr
    //   4156: sastore
    //   4157: aload 10
    //   4159: iload 30
    //   4161: saload
    //   4162: istore_0
    //   4163: aload 10
    //   4165: iload 30
    //   4167: bipush 13
    //   4169: iadd
    //   4170: saload
    //   4171: i2l
    //   4172: aload 9
    //   4174: iload_0
    //   4175: iaload
    //   4176: i2l
    //   4177: lmul
    //   4178: aload 10
    //   4180: iload 30
    //   4182: bipush 14
    //   4184: iadd
    //   4185: saload
    //   4186: i2l
    //   4187: aload 9
    //   4189: iload_0
    //   4190: iconst_1
    //   4191: iadd
    //   4192: iaload
    //   4193: i2l
    //   4194: lmul
    //   4195: ladd
    //   4196: aload 10
    //   4198: iload 30
    //   4200: bipush 15
    //   4202: iadd
    //   4203: saload
    //   4204: i2l
    //   4205: aload 9
    //   4207: iload_0
    //   4208: iconst_2
    //   4209: iadd
    //   4210: iaload
    //   4211: i2l
    //   4212: lmul
    //   4213: ladd
    //   4214: lconst_0
    //   4215: lcmp
    //   4216: ifle +430 -> 4646
    //   4219: goto +9 -> 4228
    //   4222: aload 10
    //   4224: iload 30
    //   4226: saload
    //   4227: istore_0
    //   4228: aload 13
    //   4230: aload 9
    //   4232: iload_0
    //   4233: iaload
    //   4234: putfield 174	e:a	I
    //   4237: aload 13
    //   4239: aload 9
    //   4241: iinc 0 1
    //   4244: iload_0
    //   4245: iaload
    //   4246: putfield 175	e:b	I
    //   4249: aload 13
    //   4251: aload 9
    //   4253: iinc 0 1
    //   4256: iload_0
    //   4257: iaload
    //   4258: putfield 176	e:c	I
    //   4261: aload 10
    //   4263: iload 30
    //   4265: iconst_1
    //   4266: iadd
    //   4267: saload
    //   4268: istore_0
    //   4269: aload 14
    //   4271: aload 9
    //   4273: iload_0
    //   4274: iaload
    //   4275: putfield 174	e:a	I
    //   4278: aload 14
    //   4280: aload 9
    //   4282: iinc 0 1
    //   4285: iload_0
    //   4286: iaload
    //   4287: putfield 175	e:b	I
    //   4290: aload 14
    //   4292: aload 9
    //   4294: iinc 0 1
    //   4297: iload_0
    //   4298: iaload
    //   4299: putfield 176	e:c	I
    //   4302: aload 10
    //   4304: iload 30
    //   4306: iconst_2
    //   4307: iadd
    //   4308: saload
    //   4309: istore_0
    //   4310: aload 15
    //   4312: aload 9
    //   4314: iload_0
    //   4315: iaload
    //   4316: putfield 174	e:a	I
    //   4319: aload 15
    //   4321: aload 9
    //   4323: iinc 0 1
    //   4326: iload_0
    //   4327: iaload
    //   4328: putfield 175	e:b	I
    //   4331: aload 15
    //   4333: aload 9
    //   4335: iinc 0 1
    //   4338: iload_0
    //   4339: iaload
    //   4340: putfield 176	e:c	I
    //   4343: iinc 30 3
    //   4346: aload 13
    //   4348: aload 10
    //   4350: iload 30
    //   4352: saload
    //   4353: putfield 179	e:f	S
    //   4356: aload 13
    //   4358: aload 10
    //   4360: iinc 30 1
    //   4363: iload 30
    //   4365: saload
    //   4366: putfield 180	e:h	S
    //   4369: aload 14
    //   4371: aload 10
    //   4373: iinc 30 1
    //   4376: iload 30
    //   4378: saload
    //   4379: putfield 179	e:f	S
    //   4382: aload 14
    //   4384: aload 10
    //   4386: iinc 30 1
    //   4389: iload 30
    //   4391: saload
    //   4392: putfield 180	e:h	S
    //   4395: aload 15
    //   4397: aload 10
    //   4399: iinc 30 1
    //   4402: iload 30
    //   4404: saload
    //   4405: putfield 179	e:f	S
    //   4408: aload 15
    //   4410: aload 10
    //   4412: iinc 30 1
    //   4415: iload 30
    //   4417: saload
    //   4418: putfield 180	e:h	S
    //   4421: iinc 30 1
    //   4424: aload 12
    //   4426: aload 11
    //   4428: aload_2
    //   4429: invokestatic 543	k:a	([Le;[Le;[[I)I
    //   4432: dup
    //   4433: istore_0
    //   4434: dup
    //   4435: iconst_1
    //   4436: isub
    //   4437: istore_0
    //   4438: ifeq +208 -> 4646
    //   4441: iload 28
    //   4443: ifeq +95 -> 4538
    //   4446: aload 10
    //   4448: iload 30
    //   4450: saload
    //   4451: dup
    //   4452: putstatic 185	g:A	I
    //   4455: bipush 6
    //   4457: if_icmple +36 -> 4493
    //   4460: iinc 0 -1
    //   4463: goto +20 -> 4483
    //   4466: aload 16
    //   4468: aload 12
    //   4470: iload_0
    //   4471: iconst_1
    //   4472: iadd
    //   4473: aaload
    //   4474: aload 12
    //   4476: iload_0
    //   4477: iconst_2
    //   4478: iadd
    //   4479: aaload
    //   4480: invokestatic 545	m:a	(Le;Le;Le;)V
    //   4483: iinc 0 -1
    //   4486: iload_0
    //   4487: ifge -21 -> 4466
    //   4490: goto +156 -> 4646
    //   4493: getstatic 313	g:i	[Lq;
    //   4496: iload 19
    //   4498: aaload
    //   4499: getfield 377	q:K	B
    //   4502: putstatic 185	g:A	I
    //   4505: iinc 0 -1
    //   4508: goto +20 -> 4528
    //   4511: aload 16
    //   4513: aload 12
    //   4515: iload_0
    //   4516: iconst_1
    //   4517: iadd
    //   4518: aaload
    //   4519: aload 12
    //   4521: iload_0
    //   4522: iconst_2
    //   4523: iadd
    //   4524: aaload
    //   4525: invokestatic 548	m:c	(Le;Le;Le;)V
    //   4528: iinc 0 -1
    //   4531: iload_0
    //   4532: ifge -21 -> 4511
    //   4535: goto +111 -> 4646
    //   4538: getstatic 185	g:A	I
    //   4541: bipush 6
    //   4543: if_icmple +73 -> 4616
    //   4546: iload_3
    //   4547: ifne +36 -> 4583
    //   4550: iinc 0 -1
    //   4553: goto +20 -> 4573
    //   4556: aload 16
    //   4558: aload 12
    //   4560: iload_0
    //   4561: iconst_1
    //   4562: iadd
    //   4563: aaload
    //   4564: aload 12
    //   4566: iload_0
    //   4567: iconst_2
    //   4568: iadd
    //   4569: aaload
    //   4570: invokestatic 547	m:b	(Le;Le;Le;)V
    //   4573: iinc 0 -1
    //   4576: iload_0
    //   4577: ifge -21 -> 4556
    //   4580: goto +66 -> 4646
    //   4583: iinc 0 -1
    //   4586: goto +20 -> 4606
    //   4589: aload 16
    //   4591: aload 12
    //   4593: iload_0
    //   4594: iconst_1
    //   4595: iadd
    //   4596: aaload
    //   4597: aload 12
    //   4599: iload_0
    //   4600: iconst_2
    //   4601: iadd
    //   4602: aaload
    //   4603: invokestatic 545	m:a	(Le;Le;Le;)V
    //   4606: iinc 0 -1
    //   4609: iload_0
    //   4610: ifge -21 -> 4589
    //   4613: goto +33 -> 4646
    //   4616: iinc 0 -1
    //   4619: goto +20 -> 4639
    //   4622: aload 16
    //   4624: aload 12
    //   4626: iload_0
    //   4627: iconst_1
    //   4628: iadd
    //   4629: aaload
    //   4630: aload 12
    //   4632: iload_0
    //   4633: iconst_2
    //   4634: iadd
    //   4635: aaload
    //   4636: invokestatic 548	m:c	(Le;Le;Le;)V
    //   4639: iinc 0 -1
    //   4642: iload_0
    //   4643: ifge -21 -> 4622
    //   4646: iinc 31 -1
    //   4649: iload 31
    //   4651: ifge -635 -> 4016
    //   4654: iload 28
    //   4656: ifeq +196 -> 4852
    //   4659: iload 19
    //   4661: istore 17
    //   4663: getstatic 363	m:a	I
    //   4666: ifeq +186 -> 4852
    //   4669: getstatic 313	g:i	[Lq;
    //   4672: iload 17
    //   4674: aaload
    //   4675: dup
    //   4676: astore 18
    //   4678: getfield 379	q:M	B
    //   4681: iconst_4
    //   4682: if_icmpeq +170 -> 4852
    //   4685: new 122	e
    //   4688: dup
    //   4689: invokespecial 463	e:<init>	()V
    //   4692: dup
    //   4693: astore 28
    //   4695: aload 18
    //   4697: getfield 402	q:w	I
    //   4700: putfield 181	e:j	I
    //   4703: aload 28
    //   4705: aload 18
    //   4707: getfield 403	q:x	I
    //   4710: putfield 182	e:k	I
    //   4713: aload 28
    //   4715: aload 18
    //   4717: getfield 404	q:y	I
    //   4720: getstatic 263	g:az	[B
    //   4723: aload 18
    //   4725: getfield 379	q:M	B
    //   4728: baload
    //   4729: bipush 16
    //   4731: ishl
    //   4732: iadd
    //   4733: putfield 183	e:l	I
    //   4736: aload 28
    //   4738: invokestatic 524	h:b	(Le;)V
    //   4741: aload 28
    //   4743: getfield 176	e:c	I
    //   4746: ifle +106 -> 4852
    //   4749: aload 28
    //   4751: ldc2_w 147
    //   4754: aload 28
    //   4756: getfield 174	e:a	I
    //   4759: i2l
    //   4760: getstatic 199	g:O	I
    //   4763: i2l
    //   4764: lmul
    //   4765: aload 28
    //   4767: getfield 176	e:c	I
    //   4770: i2l
    //   4771: ldiv
    //   4772: ladd
    //   4773: l2i
    //   4774: i2s
    //   4775: putfield 177	e:d	S
    //   4778: aload 28
    //   4780: ldc2_w 149
    //   4783: aload 28
    //   4785: getfield 175	e:b	I
    //   4788: i2l
    //   4789: getstatic 199	g:O	I
    //   4792: i2l
    //   4793: lmul
    //   4794: aload 28
    //   4796: getfield 176	e:c	I
    //   4799: i2l
    //   4800: ldiv
    //   4801: lsub
    //   4802: l2i
    //   4803: i2s
    //   4804: putfield 178	e:e	S
    //   4807: getstatic 212	g:aA	[B
    //   4810: iload 17
    //   4812: iconst_3
    //   4813: bastore
    //   4814: aload 28
    //   4816: getfield 178	e:e	S
    //   4819: iconst_5
    //   4820: isub
    //   4821: bipush 126
    //   4823: if_icmplt +10 -> 4833
    //   4826: getstatic 212	g:aA	[B
    //   4829: iload 17
    //   4831: iconst_1
    //   4832: bastore
    //   4833: aload 28
    //   4835: getfield 178	e:e	S
    //   4838: iconst_5
    //   4839: iadd
    //   4840: bipush 126
    //   4842: if_icmpgt +10 -> 4852
    //   4845: getstatic 212	g:aA	[B
    //   4848: iload 17
    //   4850: iconst_2
    //   4851: bastore
    //   4852: iconst_0
    //   4853: putstatic 363	m:a	I
    //   4856: iinc 29 -1
    //   4859: iload 29
    //   4861: ifge -3599 -> 1262
    //   4864: return
  }
  
  static void a(q paramq)
  {
    i[] arrayOfi = e;
    for (int i1 = 0; i1 < N; i1++)
    {
      i locali;
      if ((!(locali = arrayOfi[i1]).t) && (locali.s - 51 == paramq.O))
      {
        locali.t = true;
        locali.l = paramq.w;
        locali.m = paramq.x;
        locali.n = (paramq.y - 6553600);
        locali.q = paramq.B;
        return;
      }
    }
  }
  
  static final void i()
  {
    w.l = true;
    w.t = 0;
    g();
    w.n = 15;
    w.l = false;
    s.g();
    s.f();
  }
  
  static final void a(int paramInt)
  {
    if ((paramInt = i[0]).m >= 0)
    {
      i[paramInt.m].m = -1;
      i[paramInt.m].N = true;
      paramInt.m = -1;
      paramInt.N = true;
      aY = 0;
    }
  }
  
  private static boolean a(c paramc)
  {
    if (v.a) {
      return false;
    }
    q[] arrayOfq = i;
    int i2 = paramc.g + paramc.d >> 1;
    int i3 = paramc.h + paramc.e >> 1;
    for (int i4 = 0; i4 < arrayOfq.length; i4++) {
      if (!arrayOfq[i4].k)
      {
        paramc = i2 - arrayOfq[i4].w >> 16;
        int i1 = i3 - arrayOfq[i4].x >> 16;
        if ((paramc = paramc * paramc + i1 * i1) < 202500) {
          return true;
        }
      }
    }
    return false;
  }
  
  static final void j()
  {
    if ((p) && (!l.a)) {
      return;
    }
    i[] arrayOfi = e;
    for (int i1 = 0; i1 < N; i1++)
    {
      i locali;
      if ((arrayOfi[i1].s == 12) && (Math.abs((locali = arrayOfi[i1]).l - i[0].w >> 16) + Math.abs(locali.m - i[0].x >> 16) + Math.abs(locali.n - i[0].y >> 16) < 400))
      {
        ae = (byte)i1;
        w.n = 25;
        w.h = true;
        s.d = true;
        return;
      }
    }
  }
  
  static final void b(q paramq)
  {
    if (paramq.M < 2)
    {
      switch (paramq.O)
      {
      case 1: 
        a(paramq.w + 146 * -h.d[paramq.D] + -1 * h.a[paramq.D], paramq.x + 146 * -h.a[paramq.D] + -1 * -h.d[paramq.D], paramq.y + 12713984 - h.e[paramq.M], (byte)3, paramq.B);
        break;
      case 2: 
        a(paramq.w + 131 * -h.d[paramq.D] + -26 * h.a[paramq.D], paramq.x + 131 * -h.a[paramq.D] + -26 * -h.d[paramq.D], paramq.y + 12648448 - h.e[paramq.M], (byte)3, paramq.B);
        break;
      case 3: 
        a(paramq.w + 120 * -h.d[paramq.D] + -26 * h.a[paramq.D], paramq.x + 120 * -h.a[paramq.D] + -26 * -h.d[paramq.D], paramq.y + 12779520 - h.e[paramq.M], (byte)3, paramq.B);
        break;
      case 4: 
        a(paramq.w + 135 * -h.d[paramq.D] + -37 * h.a[paramq.D], paramq.x + 135 * -h.a[paramq.D] + -37 * -h.d[paramq.D], paramq.y + 13107200 - h.e[paramq.M], (byte)9, paramq.B);
      default: 
        return;
      }
    }
    else if (paramq.M == 2)
    {
      switch (paramq.O)
      {
      case 1: 
        a(paramq.w + 135 * -h.d[paramq.D] + -5 * h.a[paramq.D], paramq.x + 135 * -h.a[paramq.D] + -5 * -h.d[paramq.D], paramq.y + 12779520 - h.e[paramq.M], (byte)3, paramq.B);
        break;
      case 2: 
        a(paramq.w + 147 * -h.d[paramq.D] + -13 * h.a[paramq.D], paramq.x + 147 * -h.a[paramq.D] + -13 * -h.d[paramq.D], paramq.y + 12582912 - h.e[paramq.M], (byte)3, paramq.B);
        break;
      case 3: 
        a(paramq.w + 122 * -h.d[paramq.D] + -12 * h.a[paramq.D], paramq.x + 122 * -h.a[paramq.D] + -12 * -h.d[paramq.D], paramq.y + 12517376 - h.e[paramq.M], (byte)3, paramq.B);
        break;
      case 4: 
        a(paramq.w + 133 * -h.d[paramq.D] + -26 * h.a[paramq.D], paramq.x + 133 * -h.a[paramq.D] + -26 * -h.d[paramq.D], paramq.y + 13107200 - h.e[paramq.M], (byte)9, paramq.B);
      default: 
        return;
      }
    }
    else
    {
      if (paramq.L == 3) {
        a(paramq.w + 100 * -h.d[paramq.D] + 130 * h.a[paramq.D], paramq.x + 100 * -h.a[paramq.D] + 130 * -h.d[paramq.D], paramq.y + 19595264 - h.e[paramq.M], (byte)9, paramq.B);
      }
      if (paramq.L == 2) {
        a(paramq.w + 100 * -h.d[paramq.D] - 130 * h.a[paramq.D], paramq.x + 100 * -h.a[paramq.D] - 130 * -h.d[paramq.D], paramq.y + 19595264 - h.e[paramq.M], (byte)9, paramq.B);
      }
    }
  }
  
  static boolean k()
  {
    if (v.a) {
      return false;
    }
    q[] arrayOfq = i;
    q localq1 = i[(ah - 1)];
    int i3 = ah;
    if (p) {
      i3 = ah - 1;
    }
    for (int i4 = 1; i4 < i3; i4++)
    {
      q localq2;
      if (((localq2 = arrayOfq[i4]).M < 3) && (localq2.k) && (localq2.s < localq1.s)) {
        localq1 = arrayOfq[i4];
      }
    }
    if ((localq1.k) && (localq1.s < -100))
    {
      int i1 = a;
      if (localq1.K < 3) {
        i1 = an;
      }
      c localc = g[m[i1]];
      int i2 = localq1.B;
      i3 = localq1.w;
      i4 = localq1.x;
      int i5 = localq1.y;
      localq1.B = ((short)m[i1]);
      localq1.w = (localc.g + h.a(localc.d - localc.g));
      localq1.x = (localc.h + h.a(localc.e - localc.h));
      localq1.y = (localc.i + h.a(localc.f - localc.i));
      h.b(localq1);
      if ((Math.abs(localq1.w - i[0].w >> 16) + Math.abs(localq1.x - i[0].x >> 16) < 700) || ((r.a(localq1, i[0])) && (!r.b(i[0], localq1))))
      {
        localq1.B = ((byte)i2);
        localq1.w = i3;
        localq1.x = i4;
        localq1.y = i5;
        return false;
      }
      f(localq1);
      F = localq1.n;
      if (localq1.K < 3)
      {
        i1 = w.b;
        w.b = 1;
        f();
        w.b = (short)i1;
      }
      return true;
    }
    return false;
  }
  
  private static int a(byte[] paramArrayOfByte, byte paramByte)
  {
    int i2 = 0;
    if (paramArrayOfByte[3] == 1) {
      i2 = 1;
    }
    if (paramByte == 2) {
      return paramArrayOfByte[4];
    }
    int i1;
    if ((i1 = paramArrayOfByte[5]) < 0) {
      i1 += 256;
    }
    if (i2 != 0) {
      i2 = 5 + (i1 << 2);
    } else {
      i2 = 5 + i1 * 3;
    }
    int i3;
    if (paramByte == 0)
    {
      if ((i1 = (short)paramArrayOfByte[(++i2)]) < 0) {
        i1 = (short)(i1 + 256);
      }
      if ((i3 = (short)paramArrayOfByte[(++i2)]) < 0) {
        i3 = (short)(i3 + 256);
      }
      i1 = i1 << 8 | i3;
    }
    if (paramByte == 1)
    {
      i2 += 2;
      if ((i1 = (short)paramArrayOfByte[(++i2)]) < 0) {
        i1 = (short)(i1 + 256);
      }
      if ((i3 = (short)paramArrayOfByte[(++i2)]) < 0) {
        i3 = (short)(i3 + 256);
      }
      i1 = i1 << 8 | i3;
    }
    return i1;
  }
  
  public static final void l()
  {
    q localq;
    int i2 = (localq = i[0]).w;
    int i3 = localq.x;
    int i1 = localq.y;
    i[] arrayOfi = e;
    for (int i5 = 0; i5 < N; i5++)
    {
      i locali;
      if (((locali = arrayOfi[i5]).t) && (locali.s > 51) && (locali.s < 56) && (Math.abs(locali.l - i2) + Math.abs(locali.m - i3) + Math.abs(locali.n - i1) < 19005440))
      {
        (locali = locali).t = false;
        int i4 = locali.s - 51;
        if (by[i4] == 0)
        {
          by[i4] = 1;
          l[i4] = aQ[i4];
          k[i4] = aQ[i4];
          d();
        }
        else
        {
          int i6;
          if ((i6 = k[i4] + (aQ[i4] << 1)) > aP[i4]) {
            i6 = aP[i4];
          }
          k[i4] = ((byte)i6);
        }
      }
    }
  }
  
  static void c(q paramq)
  {
    if ((paramq.k) && (paramq.s > 64936))
    {
      paramq.s = ((short)(paramq.s - 1));
      if (paramq.s <= 64936) {
        paramq.N = false;
      }
    }
  }
  
  static void a(q paramq, byte paramByte1, byte paramByte2)
  {
    if (!paramq.k)
    {
      a(paramq.w, paramq.x, paramq.y, paramq.B, (byte)0);
      paramq.k = true;
      paramq.L = ((byte)(7 + (paramByte1 & 0x1)));
      if (paramq.M == 2) {
        paramq.L = 7;
      }
      paramq.j = 0;
      if ((paramByte2 & 0x1) == 1)
      {
        paramq.s = -120;
        a(paramq, true);
        return;
      }
      for (paramByte1 = 0; paramByte1 < 4; paramByte1++) {
        a(paramq.w, paramq.x, paramq.y, paramq.B);
      }
    }
  }
  
  static void a(q paramq, boolean paramBoolean)
  {
    switch (paramq.M)
    {
    case 0: 
    case 1: 
    case 2: 
      if (paramq.s < -30)
      {
        paramq.N = false;
        for (paramBoolean = false; paramBoolean < true; paramBoolean++) {
          a(paramq.w, paramq.x, paramq.y, paramq.B, (byte)(10 + paramq.K));
        }
        for (paramBoolean = false; paramBoolean < true; paramBoolean++) {
          a(paramq.w, paramq.x, paramq.y, paramq.B, (byte)0);
        }
        a(paramq.w, paramq.x, paramq.y - 4194304, (byte)10, paramq.B);
        a(paramq.w, paramq.x, paramq.y, (byte)10, paramq.B);
        a(paramq.w, paramq.x, paramq.y - 8388608, paramq.B, (byte)2);
      }
      break;
    }
  }
  
  static final void m()
  {
    if (I != null)
    {
      q localq = i[0];
      for (int i2 = 0; i2 < I.length; i2 += 3) {
        if (I[(i2 + 2)] != 0)
        {
          i locali = e[I[i2]];
          if (p) {
            localq = i[(ah - 1)];
          }
          if ((locali.l - locali.e < localq.w) && (locali.l + locali.e > localq.w) && (locali.m - locali.e < localq.x) && (locali.m + locali.e > localq.x) && (Math.abs(localq.y - locali.n) <= 26214400)) {
            if (I[(i2 + 2)] < 0)
            {
              locali.n -= 655360;
              int i1;
              if ((i1 = h.a(locali)) == 2)
              {
                locali.n = g[locali.q].i;
                I[(i2 + 2)] = 0;
                I[(i2 + 1)] = 0;
              }
            }
            else if (I[(i2 + 1)] < 2)
            {
              locali.n += 655360;
              if (h.a(locali) == 1)
              {
                int tmp235_234 = (i2 + 1);
                short[] tmp235_229 = I;
                tmp235_229[tmp235_234] = ((short)(tmp235_229[tmp235_234] + 1));
                if (I[(i2 + 1)] >= 2)
                {
                  I[(i2 + 1)] = 2;
                  locali.n = g[locali.q].i;
                }
              }
            }
          }
        }
      }
    }
  }
  
  public static final void n()
  {
    int i1 = aJ * 3;
    q localq = i[0];
    short[] arrayOfShort = aK;
    int i2 = i[0].w >> 16;
    int i3 = i[0].x >> 16;
    int i4 = i[0].y >> 16;
    if (v)
    {
      localq.t = 255;
      return;
    }
    localq.t = 0;
    int i5;
    int i6;
    for (int i8 = 0; i8 < i1; i8 += 3)
    {
      i5 = i2 - arrayOfShort[i8];
      i6 = i3 - arrayOfShort[(i8 + 1)];
      int i7 = i4 - arrayOfShort[(i8 + 2)];
      if ((i5 = (int)(65536L * (i5 * i5 + i6 * i6 + i7 * i7) >> 30)) > 255) {
        i5 = 255;
      }
      q tmp150_149 = localq;
      tmp150_149.t = ((short)(tmp150_149.t + (255 - i5)));
      if (localq.t > 255)
      {
        localq.t = 255;
        break;
      }
      if (localq.t < 20) {
        localq.t = 30;
      }
    }
    if (localq.t < 0) {
      localq.t = 0;
    }
    if (s.y == 4)
    {
      i5 = i2 - (e[0].l >> 16);
      i6 = i3 - (e[0].m >> 16);
      if ((i5 = (int)(65536L * (i5 * i5 + i6 * i6) >> 28)) > 255) {
        i5 = 255;
      }
      q tmp294_293 = localq;
      tmp294_293.t = ((short)(tmp294_293.t + (255 - i5)));
      if (localq.t > 255) {
        localq.t = 255;
      }
      if (localq.t < 20) {
        localq.t = 20;
      }
      i5 = i2 - (e[13].l >> 16);
      i6 = i3 - (e[13].m >> 16);
      if ((i5 = (int)(65536L * (i5 * i5 + i6 * i6) >> 28)) > 255) {
        i5 = 255;
      }
      q tmp409_408 = localq;
      tmp409_408.t = ((short)(tmp409_408.t + (255 - i5)));
      if (localq.t > 255) {
        localq.t = 255;
      }
      if (localq.t < 20) {
        localq.t = 30;
      }
    }
  }
  
  private static void L()
  {
    ap = new byte[12][];
    ao = new int[12][];
    bM = new short[36][3];
    for (int i1 = 1; i1 < 12; i1++)
    {
      byte[] arrayOfByte;
      if ((arrayOfByte = p.d.b(p.a(au) + i1, -1)) != null)
      {
        ao[i1] = b(arrayOfByte);
        ap[i1] = a(arrayOfByte, false, 0, 0, 0, 0);
        bM[i1][0] = ((short)a(arrayOfByte, 0));
        bM[i1][1] = ((short)a(arrayOfByte, 1));
        bM[i1][2] = ((short)a(arrayOfByte, 2));
      }
    }
  }
  
  private static int[] b(byte[] paramArrayOfByte)
  {
    int i2 = 3;
    int i3 = 0;
    if (paramArrayOfByte[3] == 1) {
      i3 = 1;
    }
    i2++;
    int i1;
    if ((i1 = (i2++)[5]) < 0) {
      i1 += 256;
    }
    int[] arrayOfInt = new int[i1];
    if (i3 == 0)
    {
      i3 = 0;
      tmpTernaryOp = paramArrayOfByte;
      while (i3 < i1)
      {
        arrayOfInt[i3] = ((paramArrayOfByte[(++i2)] & 0xFF) << 16 | (paramArrayOfByte[(++i2)] & 0xFF) << 8 | paramArrayOfByte[(++i2)] & 0xFF);
        i3++;
      }
    }
    else
    {
      for (i3 = 0; i3 < i1; i3++) {
        if (paramArrayOfByte[(++i2)] != 0)
        {
          arrayOfInt[i3] = (0xFF000000 | (paramArrayOfByte[(++i2)] & 0xFF) << 16 | (paramArrayOfByte[(++i2)] & 0xFF) << 8 | paramArrayOfByte[(++i2)] & 0xFF);
        }
        else
        {
          i2 += 3;
          arrayOfInt[i3] = 0;
        }
      }
    }
    return arrayOfInt;
  }
  
  private static byte[] a(byte[] paramArrayOfByte, boolean paramBoolean, int paramInt1, int paramInt2, int paramInt3, int paramInt4)
  {
    int i1 = 0;
    if (paramArrayOfByte[3] == 1) {
      i1 = 1;
    }
    int i2 = 0;
    if (paramArrayOfByte[4] == 1) {
      i2 = 1;
    }
    boolean bool;
    if ((bool = paramArrayOfByte[5]) < 0) {
      bool += 256;
    }
    if (i1 != 0) {
      i1 = 5 + (bool << true);
    } else {
      i1 = 5 + bool * true;
    }
    byte[] arrayOfByte;
    if (!paramBoolean)
    {
      paramBoolean = paramArrayOfByte[(++i1)] << 8 | paramArrayOfByte[(++i1)];
      paramInt1 = paramArrayOfByte[(++i1)] << 8 | paramArrayOfByte[(++i1)];
      if (paramBoolean) {
        paramBoolean += 256;
      }
      if (paramInt1 < 0) {
        paramInt1 += 256;
      }
      i1++;
      if (i2 == 0)
      {
        arrayOfByte = new byte[paramBoolean *= paramInt1];
        for (bool = false; bool < paramBoolean; bool++) {
          arrayOfByte[bool] = paramArrayOfByte[(++i1)];
        }
      }
      else
      {
        i1++;
        arrayOfByte = new byte[paramBoolean = paramArrayOfByte.length - i1];
        for (bool = false; bool < paramBoolean; bool++) {
          arrayOfByte[bool] = paramArrayOfByte[(i1++)];
        }
      }
    }
    else
    {
      paramBoolean = false;
      int i3 = paramArrayOfByte[(++i1)] << 8 | paramArrayOfByte[(++i1)];
      i1++;
      i1++;
      if (i3 < 0) {
        i3 += 256;
      }
      arrayOfByte = new byte[paramInt3 * paramInt4];
      i1 += paramInt2 * i3 + paramInt1;
      i1++;
      i1++;
      for (paramInt2 = 0; paramInt2 < paramInt4; paramInt2++)
      {
        paramInt1 = paramInt2 * i3 + i1;
        for (int i4 = 0; i4 < paramInt3; i4++)
        {
          arrayOfByte[paramBoolean] = paramArrayOfByte[(paramInt1 + i4)];
          paramBoolean++;
        }
      }
    }
    return arrayOfByte;
  }
  
  private static final int M()
  {
    byte[] arrayOfByte;
    int i1;
    int i5 = (short)(i1 = (arrayOfByte = p.d.b("cu", -1)).length / 6);
    q = new short[i1][6];
    for (int i2 = 0; i2 < i1; i2++)
    {
      int i4 = i2 * 6;
      for (int i3 = 0; i3 < 6; i3++)
      {
        q[i2][i3] = ((short)arrayOfByte[(i4 + i3)]);
        if (q[i2][i3] < 0)
        {
          int tmp76_75 = i3;
          short[] tmp76_74 = q[i2];
          tmp76_74[tmp76_75] = ((short)(tmp76_74[tmp76_75] + 256));
        }
      }
    }
    return i5;
  }
  
  private static void i(int paramInt)
  {
    b = 0;
    if (paramInt == 9) {
      b = 61;
    }
    int i1 = -2;
    paramInt = p.d.b("lvl" + paramInt, -1);
    i1 += 2;
    if ((i4 = h.b(paramInt[0], paramInt[1])) != 0) {
      bg = new byte[i4];
    }
    for (int i2 = 0; i2 < i4; i2++)
    {
      i1 += 2;
      bg[i2] = ((byte)h.b(paramInt[i1], paramInt[(i1 + 1)]));
    }
    i1 += 2;
    ab[0] = (h.b(paramInt[i1], paramInt[(i1 + 1)]) << 16);
    i1 += 2;
    ab[1] = (h.b(paramInt[i1], paramInt[(i1 + 1)]) << 16);
    i1 += 2;
    ab[2] = (h.b(paramInt[i1], paramInt[(i1 + 1)]) << 16);
    i1 += 2;
    Z = h.b(paramInt[i1], paramInt[(i1 + 1)]);
    i1 += 2;
    if ((aa = h.b(paramInt[i1], paramInt[(i1 + 1)])) > 361) {
      aa -= 65536;
    }
    if (Z > 361) {
      Z -= 65536;
    }
    if (aa < 0) {
      aa = -aa;
    } else {
      aa = 360 - aa;
    }
    if (aa == 360) {
      aa = 0;
    }
    if (Z < 0) {
      Z = 270 + Z;
    } else {
      Z = 270 - Z;
    }
    if (Z == 360) {
      Z = 0;
    }
    bn = 270;
    i1 += 2;
    Y = (short)h.b(paramInt[i1], paramInt[(i1 + 1)]);
    i1 += 2;
    c = new int[i2 = h.b(paramInt[i1], paramInt[(i1 + 1)])];
    for (int i4 = 0; i4 < i2; i4 += 3)
    {
      i1 += 2;
      c[i4] = ((int)(65536 * h.b(paramInt[i1], paramInt[(i1 + 1)]) / 10000L));
      i1 += 2;
      c[(i4 + 1)] = ((int)(65536 * h.b(paramInt[i1], paramInt[(i1 + 1)]) / 10000L));
      i1 += 2;
      c[(i4 + 2)] = ((int)(65536 * h.b(paramInt[i1], paramInt[(i1 + 1)]) / 10000L));
    }
    i1 += 2;
    bG = new short[i2 = h.b(paramInt[i1], paramInt[(i1 + 1)])];
    for (i4 = 0; i4 < i2; i4 += 2)
    {
      i1 += 2;
      bG[i4] = ((short)(int)(128 * h.b(paramInt[i1], paramInt[(i1 + 1)]) / 100L));
      i1 += 2;
      bG[(i4 + 1)] = ((short)(int)(128 * h.b(paramInt[i1], paramInt[(i1 + 1)]) / 100L));
    }
    g = new c[Y];
    Q = new byte[Y];
    for (i2 = 0; i2 < Y; i2++) {
      g[i2] = new c();
    }
    for (int i5 = 0; i5 < Y; i5++)
    {
      i1 += 2;
      g[i5].d = (h.b(paramInt[i1], paramInt[(i1 + 1)]) << 16);
      i1 += 2;
      g[i5].e = (h.b(paramInt[i1], paramInt[(i1 + 1)]) << 16);
      i1 += 2;
      g[i5].f = (h.b(paramInt[i1], paramInt[(i1 + 1)]) << 16);
      i1 += 2;
      g[i5].g = (h.b(paramInt[i1], paramInt[(i1 + 1)]) << 16);
      i1 += 2;
      g[i5].h = (h.b(paramInt[i1], paramInt[(i1 + 1)]) << 16);
      i1 += 2;
      g[i5].i = (h.b(paramInt[i1], paramInt[(i1 + 1)]) << 16);
      i1 += 2;
      i4 = h.b(paramInt[i1], paramInt[(i1 + 1)]);
      i1 += 2;
      i2 = h.b(paramInt[i1], paramInt[(i1 + 1)]);
      g[i5].a = new short[i4 * 3];
      g[i5].k = i4;
      g[i5].b = new short[i2 * 7];
      g[i5].l = i2;
      for (i6 = 0; i6 < i4; i6++)
      {
        i1 += 2;
        g[i5].a[(i6 * 3)] = ((short)h.b(paramInt[i1], paramInt[(i1 + 1)]));
        i1 += 2;
        g[i5].a[(i6 * 3 + 1)] = ((short)h.b(paramInt[i1], paramInt[(i1 + 1)]));
        i1 += 2;
        g[i5].a[(i6 * 3 + 2)] = ((short)h.b(paramInt[i1], paramInt[(i1 + 1)]));
      }
      short[] arrayOfShort = g[i5].b;
      for (i6 = 0; i6 < i2; i6++)
      {
        i4 = i6 * 7;
        i1 += 2;
        g[i5].b[i4] = ((short)(h.b(paramInt[i1], paramInt[(i1 + 1)]) * 3));
        i1 += 2;
        g[i5].b[(i4 + 1)] = ((short)(h.b(paramInt[i1], paramInt[(i1 + 1)]) * 3));
        i1 += 2;
        g[i5].b[(i4 + 2)] = ((short)(h.b(paramInt[i1], paramInt[(i1 + 1)]) * 3));
      }
      i1 += 2;
      i4 = h.b(paramInt[i1], paramInt[(i1 + 1)]);
      g[i5].j = new int[i4 << 1];
      for (i6 = 0; i6 < i4; i6++)
      {
        i1 += 2;
        g[i5].j[(i6 << 1)] = (h.b(paramInt[i1], paramInt[(i1 + 1)]) * 3);
        i1 += 2;
        g[i5].j[((i6 << 1) + 1)] = arrayOfShort[(h.b(paramInt[i1], paramInt[(i1 + 1)]) * 7)];
      }
      for (i7 = 0; i7 < i2; i7++)
      {
        i4 = i7 * 7;
        i1 += 2;
        g[i5].b[(i4 + 3)] = ((short)(h.b(paramInt[i1], paramInt[(i1 + 1)]) << 1));
        i1 += 2;
        g[i5].b[(i4 + 4)] = ((short)(h.b(paramInt[i1], paramInt[(i1 + 1)]) << 1));
        i1 += 2;
        g[i5].b[(i4 + 5)] = ((short)(h.b(paramInt[i1], paramInt[(i1 + 1)]) << 1));
      }
      i1++;
      for (i4 = 0; i4 < i2; i4++)
      {
        i1++;
        if ((i8 = paramInt[i1]) < 0) {
          i8 += 256;
        }
        g[i5].b[(i4 * 7 + 6)] = ((short)i8);
        if (g[i5].b[(i4 * 7 + 6)] < 50) {
          aN[g[i5].b[(i4 * 7 + 6)]] = true;
        }
      }
      for (i7 = 0; i7 < i2; i7++)
      {
        i1++;
        if ((i4 = (i4 = h.b(paramInt[i1], paramInt[(i1 + 1)])) & 0xFF) < 70) {
          i4 = 70;
        }
        i8 = g[i5].b[(i7 * 7 + 6)] & 0xFF;
        g[i5].b[(i7 * 7 + 6)] = ((short)(i4 << 8 | i8));
      }
      i1--;
    }
    i1 += 2;
    f = new k[i2 = h.b(paramInt[i1], paramInt[(i1 + 1)])];
    for (int i6 = 0; i6 < i2; i6++)
    {
      f[i6] = new k();
      f[i6].b[0] = new e();
      f[i6].b[1] = new e();
      f[i6].b[2] = new e();
      f[i6].b[3] = new e();
    }
    for (int i7 = 0; i7 < i2; i7++)
    {
      for (i4 = 0; i4 < 4; i4++)
      {
        i1 += 2;
        f[i7].b[i4].j = (h.b(paramInt[i1], paramInt[(i1 + 1)]) << 16);
        i1 += 2;
        f[i7].b[i4].k = (h.b(paramInt[i1], paramInt[(i1 + 1)]) << 16);
        i1 += 2;
        f[i7].b[i4].l = (h.b(paramInt[i1], paramInt[(i1 + 1)]) << 16);
      }
      i1 += 2;
      i4 = (int)(65536 * h.b(paramInt[i1], paramInt[(i1 + 1)]) / 10000L);
      i1 += 2;
      i5 = (int)(65536 * h.b(paramInt[i1], paramInt[(i1 + 1)]) / 10000L);
      i1 += 2;
      i6 = (int)(65536 * h.b(paramInt[i1], paramInt[(i1 + 1)]) / 10000L);
      i1 += 2;
      f[i7].c = ((short)(h.b(paramInt[i1], paramInt[(i1 + 1)]) - 1));
      i1 += 2;
      f[i7].d = ((short)(h.b(paramInt[i1], paramInt[(i1 + 1)]) - 1));
      if (i4 != 0) {
        f[i7].a = 1;
      } else if (i5 != 0) {
        f[i7].a = 2;
      } else if (i6 != 0) {
        f[i7].a = 3;
      }
    }
    for (i4 = 0; i4 < i2; i4++)
    {
      if (f[i4].c < 999)
      {
        g[f[i4].c].m[g[f[i4].c].n] = ((byte)i4);
        g[f[i4].c].n += 1;
      }
      if (f[i4].d < 999)
      {
        g[f[i4].d].m[g[f[i4].d].n] = ((byte)i4);
        g[f[i4].d].n += 1;
      }
    }
    i1 += 2;
    e = new i[N = (short)h.b(paramInt[i1], paramInt[(i1 + 1)])];
    bb = new short[Y];
    for (i6 = 0; i6 < N; i6++) {
      e[i6] = new i();
    }
    i6 = 0;
    for (i7 = 0; i7 < Y; i7++)
    {
      i1 += 2;
      i4 = h.b(paramInt[i1], paramInt[(i1 + 1)]);
      g[i7].o = ((short)i6);
      g[i7].c = ((short)(i6 + i4));
      for (i8 = 0; i8 < i4; i8++)
      {
        e[i6].q = ((short)i7);
        i1 += 2;
        e[i6].l = (h.b(paramInt[i1], paramInt[(i1 + 1)]) << 16);
        i1 += 2;
        e[i6].m = (h.b(paramInt[i1], paramInt[(i1 + 1)]) << 16);
        i1 += 2;
        e[i6].n = (h.b(paramInt[i1], paramInt[(i1 + 1)]) << 16);
        i1 += 2;
        e[i6].o = h.b(paramInt[i1], paramInt[(i1 + 1)]);
        i1 += 2;
        e[i6].p = ((short)h.b(paramInt[i1], paramInt[(i1 + 1)]));
        if (e[i6].p > 360) {
          e[i6].p = (65536 - e[i6].p);
        }
        if (e[i6].o > 360) {
          e[i6].o = (65536 - e[i6].o);
        }
        if (e[i6].p < 0) {
          e[i6].p = (360 + e[i6].p);
        }
        if (e[i6].o < 0) {
          e[i6].o = (360 + e[i6].o);
        } else {
          e[i6].o = (360 - e[i6].o);
        }
        if (e[i6].o == 360) {
          e[i6].o = 0;
        }
        i1 += 2;
        e[i6].s = ((byte)h.b(paramInt[i1], paramInt[(i1 + 1)]));
        if (((e[i6].s > 2) && (e[i6].s < 7)) || ((e[i6].s > 33) && (e[i6].s < 38)))
        {
          Q[i7] = 1;
          if (e[i6].s < 10) {
            bb[i7] = ((short)((e[i6].n >> 16) + 150));
          } else if (e[i6].s < 36) {
            bb[i7] = ((short)((e[i6].m >> 16) + 300));
          } else {
            bb[i7] = ((short)((e[i6].l >> 16) + 300));
          }
        }
        aL[e[i6].s] = true;
        i1 += 2;
        e[i6].d = ((short)h.b(paramInt[i1], paramInt[(i1 + 1)]));
        if (e[i6].d < 0)
        {
          i tmp2756_2755 = e[i6];
          tmp2756_2755.d = ((short)(tmp2756_2755.d + 256));
        }
        i tmp2774_2773 = e[i6];
        tmp2774_2773.d = ((short)(tmp2774_2773.d & 0xFF));
        if (e[i6].d < 70) {
          e[i6].d = 70;
        }
        i1 += 2;
        i6++;
      }
    }
    V = null;
    W = null;
    int i8 = 0;
    for (i4 = 0; i4 < e.length; i4++) {
      if (e[i4].s == 31) {
        i8++;
      }
    }
    V = new byte[i8 * 5];
    W = new short[i8];
    i8 = 0;
    for (i4 = 0; i4 < e.length; i4++) {
      if (e[i4].s == 31)
      {
        V[(i8 * 5)] = ((byte)i4);
        V[(i8 * 5 + 1)] = ((byte)e[i4].q);
        V[(i8 * 5 + 3)] = 0;
        V[(i8 * 5 + 4)] = 1;
        i8++;
      }
    }
    Object localObject;
    for (i7 = 0; i7 < g.length; i7++)
    {
      localObject = g[i7].m;
      g[i7].m = null;
      i2 = g[i7].n;
      g[i7].m = new byte[i2];
      for (i5 = 0; i5 < i2; i5++) {
        g[i7].m[i5] = localObject[i5];
      }
    }
    i1 += 2;
    ah = (short)(h.b(paramInt[i1], paramInt[(i1 + 1)]) + 1);
    if (p) {
      ah = (short)(ah + 1);
    }
    aA = new byte[ah];
    i = new q[ah];
    for (i2 = 0; i2 < ah; i2++)
    {
      i[i2] = new q();
      i[i2].n = ((byte)i2);
    }
    i6 = 1;
    i[0].w = ab[0];
    i[0].x = ab[1];
    i[0].y = ab[2];
    for (int i9 = 0; i9 < Y; i9++)
    {
      i1 += 2;
      i5 = h.b(paramInt[i1], paramInt[(i1 + 1)]);
      for (i10 = 0; i10 < i5; i10++)
      {
        localObject = i[i6];
        i1 += 2;
        ((q)localObject).w = (h.b(paramInt[i1], paramInt[(i1 + 1)]) << 16);
        i1 += 2;
        ((q)localObject).x = (h.b(paramInt[i1], paramInt[(i1 + 1)]) << 16);
        i1 += 2;
        ((q)localObject).y = (h.b(paramInt[i1], paramInt[(i1 + 1)]) << 16);
        i1 += 2;
        ((q)localObject).M = ((byte)h.b(paramInt[i1], paramInt[(i1 + 1)]));
        i8 = ((q)localObject).M;
        for (i7 = 0; i7 < N; i7++)
        {
          i locali;
          if (((locali = e[i7]).s > 51) && (locali.s < 56) && (locali.l == ((q)localObject).w) && (locali.m == ((q)localObject).x) && (Math.abs(locali.n - ((q)localObject).y >> 16) <= 30))
          {
            ((q)localObject).O = ((byte)(locali.s - 51));
            locali.t = false;
          }
        }
        if (i8 > 30)
        {
          i8 -= 30;
          if (i8 == 1)
          {
            ((q)localObject).K = 4;
            aN[4] = true;
          }
        }
        else if (i8 > 20)
        {
          i8 -= 20;
          if (i8 == 1)
          {
            ((q)localObject).K = 3;
            aN[3] = true;
          }
        }
        else if (i8 > 10)
        {
          i8 -= 10;
          if (i8 == 1)
          {
            ((q)localObject).K = 2;
            aN[2] = true;
          }
        }
        if (i8 == 2) {
          ((q)localObject).K = 5;
        }
        if ((i8 == 3) || (i8 == 4)) {
          ((q)localObject).K = 6;
        }
        ((q)localObject).M = ((byte)i8);
        aO[i8] = true;
        i1 += 2;
        if ((i3 = h.b(paramInt[i1], paramInt[(i1 + 1)])) > 360) {
          i3 -= 65536;
        }
        if (i3 < 0) {
          i3 = -i3;
        } else {
          i3 = 360 - i3;
        }
        if (i3 == 360) {
          i3 = 0;
        }
        ((q)localObject).E[0] = (-h.d[i3]);
        ((q)localObject).E[1] = (-h.a[i3]);
        ((q)localObject).D = ((short)i3);
        ((q)localObject).B = ((short)i9);
        i6++;
      }
    }
    for (int i10 = 0; i10 < i.length; i10++) {
      i[i10].s = H[i[i10].M];
    }
    i1 += 2;
    aJ = i8 = (byte)h.b(paramInt[i1], paramInt[(i1 + 1)]);
    aK = new short[i8 * 3];
    for (int i3 = 0; i3 < i8; i3++)
    {
      i1 += 2;
      aK[(i3 * 3)] = ((short)h.b(paramInt[i1], paramInt[(i1 + 1)]));
      i1 += 2;
      aK[(i3 * 3 + 1)] = ((short)h.b(paramInt[i1], paramInt[(i1 + 1)]));
      i1 += 2;
      aK[(i3 * 3 + 2)] = ((short)h.b(paramInt[i1], paramInt[(i1 + 1)]));
    }
    i1 += 2;
    i1 += 2;
    m = new byte[i8 = h.b(paramInt[i1], paramInt[(i1 + 1)])];
    for (i3 = 0; i3 < i8; i3++)
    {
      i1 += 2;
      m[i3] = ((byte)h.b(paramInt[i1], paramInt[(i1 + 1)]));
    }
    X = 0;
    for (paramInt = ah - 1; paramInt >= 0; paramInt--)
    {
      h.a(i[paramInt]);
      h.b(i[paramInt]);
      if (paramInt == 0)
      {
        X = i[paramInt].B;
        ab[0] = i[0].w;
        ab[1] = i[0].x;
        ab[2] = (i[0].y + 4587520);
        i[0].D = ((short)aa);
      }
      else
      {
        i[paramInt].A = ((byte)h.a(10));
      }
    }
    i[0].B = ((short)X);
  }
  
  public static final void b(int paramInt)
  {
    s.M = 0;
    s.J = false;
    s.I = 5;
    s.e = false;
    s.y = (byte)paramInt;
    C = new byte[4];
    for (int i1 = 0; i1 < 4; i1++) {
      C[i1] = -1;
    }
    D = new byte[4];
    for (i1 = 0; i1 < 4; i1++) {
      D[i1] = -1;
    }
    s = new int[60960];
    w.i.c(10);
    O();
    w.i.c(15);
    B = new int['Î'];
    y = new int['Î'];
    u = new int['È'];
    aH = new e[10];
    x = new e[10];
    for (i1 = 0; i1 < 10; i1++)
    {
      aH[i1] = new e();
      x[i1] = new e();
    }
    o = new int['ʁ'];
    for (int i2 = 1; i2 < 641; i2++) {
      o[i2] = (65536 / i2);
    }
    t = new int[33600];
    for (int i3 = 1; i3 < 33600; i3++) {
      t[i3] = (262144 / i3);
    }
    K = new int['ɪ'];
    ab = new int[3];
    ai = new int[3];
    ac = new int[50][13];
    bE = new int[15][6];
    bc = new int[''];
    w.i.c(25);
    i(paramInt);
    w.i.c(40);
    s.e(paramInt);
    aI = new int[65 + ah + N];
    aG = new int[65 + ah + N];
    Q();
    P();
    w.i.c(45);
    i[0].F = 1;
    h = new t[5];
    for (int i8 = 0; i8 < 5; i8++) {
      if (aO[i8] != 0)
      {
        i1 = -2;
        byte[] arrayOfByte = p.d.b("un" + i8, -1);
        h[i8] = new t();
        t localt = h[i8];
        i1 += 2;
        i1 += 2;
        i1 += 2;
        i1 += 2;
        i1 += 2;
        i1 += 2;
        i1 += 2;
        int i4 = h.b(arrayOfByte[12], arrayOfByte[13]);
        i1 += 2;
        i3 = h.b(arrayOfByte[14], arrayOfByte[15]);
        i1 += 2;
        int i5 = h.b(arrayOfByte[16], arrayOfByte[17]);
        i1 += 2;
        int i6 = h.b(arrayOfByte[18], arrayOfByte[19]);
        localt.a = new short[i6][];
        localt.c = new byte[i6][];
        localt.d = i4;
        localt.e = i3;
        for (int i7 = 0; i7 < i6; i7++)
        {
          localt.c[i7] = new byte[i3 * 3];
          localt.a[i7] = new short[(i4 + 13) * 3];
        }
        localt.b = new short[i3 + 22 << 4];
        short[] arrayOfShort = new short[i5 <<= 1];
        int i9 = 1;
        int i10 = 1;
        if (i8 < 3) {
          i9 = -1;
        }
        if (i8 < 3) {
          i10 = -1;
        }
        int i12;
        for (int i11 = 0; i11 < i6; i11++) {
          for (i12 = 0; i12 < i4; i12++)
          {
            i1 += 2;
            localt.a[i11][(i12 * 3)] = ((short)(h.b(arrayOfByte[i1], arrayOfByte[(i1 + 1)]) * i9));
            i1 += 2;
            localt.a[i11][(i12 * 3 + 1)] = ((short)(h.b(arrayOfByte[i1], arrayOfByte[(i1 + 1)]) * i10));
            i1 += 2;
            localt.a[i11][(i12 * 3 + 2)] = ((short)h.b(arrayOfByte[i1], arrayOfByte[(i1 + 1)]));
          }
        }
        i4 = i3 << 4;
        for (i11 = 0; i11 < i4; i11 += 16)
        {
          i1 += 2;
          localt.b[i11] = ((short)(h.b(arrayOfByte[i1], arrayOfByte[(i1 + 1)]) * 3));
          i1 += 2;
          localt.b[(i11 + 1)] = ((short)(h.b(arrayOfByte[i1], arrayOfByte[(i1 + 1)]) * 3));
          i1 += 2;
          localt.b[(i11 + 2)] = ((short)(h.b(arrayOfByte[i1], arrayOfByte[(i1 + 1)]) * 3));
        }
        i4 = i3 * 3;
        i1++;
        for (i11 = 0; i11 < i6; i11++) {
          for (i12 = 0; i12 < i4; i12 += 3)
          {
            i1++;
            localt.c[i11][i12] = ((byte)(arrayOfByte[i1] * i9));
            i1++;
            localt.c[i11][(i12 + 1)] = ((byte)(arrayOfByte[i1] * i10));
            i1++;
            localt.c[i11][(i12 + 2)] = arrayOfByte[i1];
          }
        }
        i1--;
        for (i4 = 0; i4 < i5; i4 += 2)
        {
          i1 += 2;
          arrayOfShort[i4] = ((short)(int)(256L * h.b(arrayOfByte[i1], arrayOfByte[(i1 + 1)]) / 1000L));
          i1 += 2;
          arrayOfShort[(i4 + 1)] = ((short)(int)(256L * h.b(arrayOfByte[i1], arrayOfByte[(i1 + 1)]) / 1000L));
        }
        i3 <<= 4;
        for (i4 = 0; i4 < i3; i4 += 16)
        {
          i1 += 2;
          localt.b[(i4 + 3)] = arrayOfShort[(h.b(arrayOfByte[i1], arrayOfByte[(i1 + 1)]) << 1)];
          localt.b[(i4 + 4)] = arrayOfShort[((h.b(arrayOfByte[i1], arrayOfByte[(i1 + 1)]) << 1) + 1)];
          i1 += 2;
          localt.b[(i4 + 5)] = arrayOfShort[(h.b(arrayOfByte[i1], arrayOfByte[(i1 + 1)]) << 1)];
          localt.b[(i4 + 6)] = arrayOfShort[((h.b(arrayOfByte[i1], arrayOfByte[(i1 + 1)]) << 1) + 1)];
          i1 += 2;
          localt.b[(i4 + 7)] = arrayOfShort[(h.b(arrayOfByte[i1], arrayOfByte[(i1 + 1)]) << 1)];
          localt.b[(i4 + 8)] = arrayOfShort[((h.b(arrayOfByte[i1], arrayOfByte[(i1 + 1)]) << 1) + 1)];
        }
        for (i4 = 0; i4 < i3; i4 += 16)
        {
          i1 += 2;
          localt.b[(i4 + 9)] = ((byte)h.b(arrayOfByte[i1], arrayOfByte[(i1 + 1)]));
          aN[localt.b[(i4 + 9)]] = true;
        }
      }
    }
    N();
    w.i.c(50);
    J();
    w.i.c(55);
    if (paramInt != 0) {
      v.a(paramInt);
    }
    k(paramInt);
    if (paramInt != 0) {
      L();
    }
    w.i.c(60);
    R();
    w.i.c(90);
    i[0].B = i[0].B;
    K();
    if (paramInt != 0) {
      j(paramInt);
    }
    w.i.c(100);
    if (w.g) {
      for (paramInt = 1; paramInt < 7; paramInt++)
      {
        l[paramInt] = aQ[paramInt];
        k[paramInt] = aP[paramInt];
        by[paramInt] = 1;
      }
    }
    if (p)
    {
      v.e();
      if (!l.a)
      {
        s.b.e[1] = 1;
        l.h = false;
        s.J = true;
      }
    }
  }
  
  private static void N()
  {
    for (int i2 = 0; i2 < i.length; i2++)
    {
      int i1;
      if ((i1 = i[i2].M) == 0) {
        i1 = 1;
      }
      if (h[i1] != null)
      {
        i[i2].v = h[i1].c;
        i[i2].e = h[i1].a;
        i[i2].f = h[i1].b;
      }
    }
  }
  
  private static void O()
  {
    aN = new boolean[57];
    aL = new boolean[59];
    aO = new boolean[5];
  }
  
  private static void j(int paramInt)
  {
    
    String[][] arrayOfString;
    String[] arrayOfString1 = new String[(arrayOfString = p.d.a("tg", 61))[paramInt].length];
    for (int i2 = 0; i2 < arrayOfString[paramInt].length; i2++) {
      arrayOfString1[i2] = new String(arrayOfString[paramInt][i2]);
    }
    L = new String[arrayOfString1.length][];
    for (int i1 = 0; i1 < arrayOfString1.length; i1++)
    {
      paramInt = arrayOfString1[i1];
      L[i1] = p.d.a(paramInt, s.o, 240, true);
    }
  }
  
  private static final void P()
  {
    d = new x[59];
    x localx;
    int i9;
    for (int i7 = 0; i7 < 59; i7++) {
      if (aL[i7] != 0)
      {
        int i1 = -2;
        byte[] arrayOfByte1 = p.d.b("o/o" + i7, -1);
        d[i7] = new x();
        localx = d[i7];
        i1 += 2;
        localx.e = (h.b(arrayOfByte1[0], arrayOfByte1[1]) << 16);
        i1 += 2;
        localx.f = (h.b(arrayOfByte1[2], arrayOfByte1[3]) << 16);
        i1 += 2;
        localx.g = (h.b(arrayOfByte1[4], arrayOfByte1[5]) << 16);
        i1 += 2;
        localx.h = (h.b(arrayOfByte1[6], arrayOfByte1[7]) << 16);
        i1 += 2;
        localx.i = (h.b(arrayOfByte1[8], arrayOfByte1[9]) << 16);
        i1 += 2;
        localx.j = (h.b(arrayOfByte1[10], arrayOfByte1[11]) << 16);
        int i2 = localx.e >> 16;
        int i3 = localx.f >> 16;
        i5 = localx.g >> 16;
        i2 = i2 * i2 + i3 * i3 + i5 * i5;
        i3 = 65536;
        i5 = 0;
        while (i3 >>= 1 > 0) {
          if ((i5 + i3) * (i5 + i3) <= i2) {
            i5 += i3;
          }
        }
        localx.d = ((i5 << 3) * 240 << 1);
        localx.c = ((i5 << 1) * 252);
        i1 += 2;
        i1 += 2;
        i1 += 2;
        i1 += 2;
        i1 += 2;
        i3 = h.b(arrayOfByte1[20], arrayOfByte1[21]);
        i1 += 2;
        i2 = h.b(arrayOfByte1[22], arrayOfByte1[23]);
        i1 += 2;
        i5 = h.b(arrayOfByte1[24], arrayOfByte1[25]);
        localx.k = i3;
        localx.a = new short[i3 * 3];
        localx.b = new short[i2 << 4];
        int[] arrayOfInt = new int[i5 <<= 1];
        i6 = 0;
        for (int i8 = 0; i8 < i3; i8++)
        {
          i1 += 2;
          localx.a[i6] = ((short)h.b(arrayOfByte1[i1], arrayOfByte1[(i1 + 1)]));
          i1 += 2;
          localx.a[(i6 + 1)] = ((short)h.b(arrayOfByte1[i1], arrayOfByte1[(i1 + 1)]));
          i1 += 2;
          localx.a[(i6 + 2)] = ((short)h.b(arrayOfByte1[i1], arrayOfByte1[(i1 + 1)]));
          i6 += 3;
        }
        i6 = 0;
        for (i3 = 0; i3 < i2; i3++)
        {
          i1 += 2;
          localx.b[i6] = ((short)(h.b(arrayOfByte1[i1], arrayOfByte1[(i1 + 1)]) * 3));
          i1 += 2;
          localx.b[(i6 + 1)] = ((short)(h.b(arrayOfByte1[i1], arrayOfByte1[(i1 + 1)]) * 3));
          i1 += 2;
          localx.b[(i6 + 2)] = ((short)(h.b(arrayOfByte1[i1], arrayOfByte1[(i1 + 1)]) * 3));
          i6 += 16;
        }
        i6 = 0;
        i1++;
        for (i9 = 0; i9 < i2; i9++)
        {
          i1++;
          localx.b[(i6 + 10)] = ((short)arrayOfByte1[i1]);
          i1++;
          localx.b[(i6 + 11)] = ((short)arrayOfByte1[i1]);
          i1++;
          localx.b[(i6 + 12)] = ((short)arrayOfByte1[i1]);
          i6 += 16;
        }
        i1--;
        i6 = 128;
        if ((i7 >= 44) && (i7 <= 51)) {
          i6 = 256;
        }
        for (i3 = 0; i3 < i5; i3 += 2)
        {
          i1 += 2;
          arrayOfInt[i3] = ((int)(i6 * h.b(arrayOfByte1[i1], arrayOfByte1[(i1 + 1)]) / 100L));
          i1 += 2;
          arrayOfInt[(i3 + 1)] = ((int)(i6 * h.b(arrayOfByte1[i1], arrayOfByte1[(i1 + 1)]) / 100L));
        }
        i6 = 0;
        for (i5 = 0; i5 < i2; i5++)
        {
          i1 += 2;
          localx.b[(i6 + 3)] = ((short)arrayOfInt[(h.b(arrayOfByte1[i1], arrayOfByte1[(i1 + 1)]) << 1)]);
          localx.b[(i6 + 4)] = ((short)arrayOfInt[((h.b(arrayOfByte1[i1], arrayOfByte1[(i1 + 1)]) << 1) + 1)]);
          i1 += 2;
          localx.b[(i6 + 5)] = ((short)arrayOfInt[(h.b(arrayOfByte1[i1], arrayOfByte1[(i1 + 1)]) << 1)]);
          localx.b[(i6 + 6)] = ((short)arrayOfInt[((h.b(arrayOfByte1[i1], arrayOfByte1[(i1 + 1)]) << 1) + 1)]);
          i1 += 2;
          localx.b[(i6 + 7)] = ((short)arrayOfInt[(h.b(arrayOfByte1[i1], arrayOfByte1[(i1 + 1)]) << 1)]);
          localx.b[(i6 + 8)] = ((short)arrayOfInt[((h.b(arrayOfByte1[i1], arrayOfByte1[(i1 + 1)]) << 1) + 1)]);
          i6 += 16;
        }
        i6 = 0;
        i1 += 2;
        for (i5 = 0; i5 < i2; i5++)
        {
          localx.b[(i6 + 9)] = ((short)arrayOfByte1[i1]);
          aN[localx.b[(i6 + 9)]] = true;
          i1++;
          i6 += 16;
        }
      }
    }
    byte[] arrayOfByte2 = p.d.b("oi", -1);
    for (int i6 = 0; i6 < e.length; i6++)
    {
      i locali;
      if ((locali = e[i6]).s < 120)
      {
        i9 = locali.s << 2;
        if (arrayOfByte2[i9] == 1) {
          locali.c = true;
        }
        if (arrayOfByte2[(i9 + 1)] == 1) {
          locali.r = true;
        }
        if (arrayOfByte2[(i9 + 3)] == 1) {
          locali.k = true;
        }
        localx = d[locali.s];
        locali.a = localx.a;
        locali.b = localx.b;
        locali.e = localx.e;
        locali.h = localx.h;
        locali.f = localx.f;
        locali.i = localx.i;
        locali.g = localx.g;
        locali.j = localx.j;
      }
    }
    int i4 = 0;
    for (int i5 = 0; i5 < e.length; i5++) {
      if ((e[i5].s > 39) && (e[i5].s < 44)) {
        i4++;
      }
    }
    I = new short[i4 * 3];
    i4 = 0;
    for (i5 = 0; i5 < e.length; i5++) {
      if ((e[i5].s > 39) && (e[i5].s < 44))
      {
        I[(i4 * 3)] = ((short)i5);
        I[(i4 * 3 + 1)] = 0;
        I[(i4 * 3 + 2)] = 0;
        i4++;
      }
    }
  }
  
  static final void a(boolean paramBoolean1, boolean paramBoolean2)
  {
    p.b = true;
    p.a();
    if (s.m)
    {
      s.L = true;
      s.A = 0;
      s.m = false;
      s.h = true;
      y.c = 60;
      s.y = 1;
      s.E = 0;
      s.j = 0;
      for (paramBoolean1 = false; paramBoolean1 < s.D.length; paramBoolean1++) {
        s.D[paramBoolean1] = 0;
      }
      s.g = true;
      b(false, true);
      return;
    }
    if (paramBoolean2)
    {
      y.c = p.a[0];
      if (p.a[1] == 1) {
        s.g = true;
      } else {
        s.g = false;
      }
      if (p.a[2] == 1) {
        s.r = false;
      } else {
        s.r = true;
      }
      if (p.a[3] == 1) {
        s.h = true;
      } else {
        s.h = false;
      }
      s.E = p.a[11];
      if (p.a[13] == 0) {
        s.n = true;
      } else {
        s.n = false;
      }
      if (p.a[16] == 1) {
        s.L = true;
      } else {
        s.L = false;
      }
      s.j = p.a[20];
      if (p.a[21] == 1) {
        s.h = true;
      } else {
        s.h = false;
      }
    }
    if (!paramBoolean1) {
      s.y = p.a[17];
    }
    if (s.y == 0) {
      s.y = 1;
    }
    r.a = p.a[18];
    s.A = p.a[19];
    paramBoolean1 = 22 + 18 * (s.y - 1);
    paramBoolean2 = true;
    r.a = p.a[paramBoolean1];
    paramBoolean1++;
    for (int i1 = 0; i1 < 7; i1++)
    {
      if ((p.a[paramBoolean1] & paramBoolean2) != 0) {
        by[i1] = 1;
      } else {
        by[i1] = 0;
      }
      paramBoolean2 <<= true;
    }
    paramBoolean1++;
    for (i1 = 0; i1 < 7; i1++)
    {
      l[i1] = p.a[paramBoolean1];
      paramBoolean1++;
    }
    for (i1 = 0; i1 < 7; i1++)
    {
      k[i1] = p.a[paramBoolean1];
      paramBoolean1++;
    }
    by[0] = 1;
    bz = p.a[paramBoolean1];
    paramBoolean1++;
    aj = p.a[paramBoolean1];
    paramBoolean1++;
    for (i1 = 0; i1 < s.D.length; i1++)
    {
      s.D[i1] = ((short)(p.a[paramBoolean1] << 8 | p.a[(paramBoolean1 + true)]));
      paramBoolean1 += 2;
    }
  }
  
  private static void Q()
  {
    ba = new i();
  }
  
  private static void R()
  {
    av = 0;
    af = new byte[57][];
    R = new int[57][];
    int i1 = 0;
    for (int i2 = 0; i2 < 57; i2++) {
      if (aN[i2] != 0)
      {
        av = (byte)(av + 1);
        try
        {
          arrayOfByte = p.d.b(p.a(as) + i2, -1);
          R[i2] = b(arrayOfByte);
          af[i2] = a(arrayOfByte, false, 0, 0, 0, 0);
          if (i2 * 30 / 57 > i1)
          {
            i1 = i2 * 30 / 57;
            w.i.c(i1 + 60);
          }
        }
        catch (Exception localException) {}
      }
    }
    ag = new byte[91][];
    byte[] arrayOfByte = p.d.b(p.a(at), -1);
    i1 = M();
    S = b(arrayOfByte);
    for (i2 = 0; i2 < i1; i2++) {
      ag[i2] = a(arrayOfByte, true, q[i2][0], q[i2][1], q[i2][2], q[i2][3]);
    }
    w.e();
  }
  
  static final void o()
  {
    if (i[0].m == -1)
    {
      i[0].b[0] = h.d[aa];
      i[0].b[1] = h.a[aa];
    }
    else
    {
      i[i[0].m].b[0] = h.d[aa];
      i[i[0].m].b[1] = h.a[aa];
    }
    bJ = true;
  }
  
  static final void p()
  {
    if (i[0].m == -1)
    {
      i[0].b[0] = h.a[aa];
      i[0].b[1] = (-h.d[aa]);
    }
    else
    {
      i[i[0].m].b[0] = h.a[aa];
      i[i[0].m].b[1] = (-h.d[aa]);
    }
    bJ = true;
  }
  
  static final void q()
  {
    if (i[0].m == -1)
    {
      i[0].b[0] = (-h.a[aa]);
      i[0].b[1] = h.d[aa];
    }
    else
    {
      i[i[0].m].b[0] = (-h.a[aa]);
      i[i[0].m].b[1] = h.d[aa];
    }
    bJ = true;
  }
  
  static final void r()
  {
    if (i[0].m == -1)
    {
      i[0].b[0] = (-h.d[aa]);
      i[0].b[1] = (-h.a[aa]);
    }
    else
    {
      i[i[0].m].b[0] = (-h.d[aa]);
      i[i[0].m].b[1] = (-h.a[aa]);
    }
    bJ = true;
  }
  
  static final void s()
  {
    if ((p) && (!l.a)) {
      return;
    }
    q localq = i[0];
    n = 0;
    switch (s.y)
    {
    case 2: 
      if (Q[9] == 10)
      {
        if ((localq.B == 8) && (localq.w < 304742400)) {
          localq.w = 304742400;
        }
        if (Math.abs(localq.w - 284819456) + Math.abs(localq.x - 110755840) < 19660800) {
          n = 9;
        }
      }
      if (Q[32] == 10)
      {
        if ((localq.B == 31) && (localq.w < -285081600)) {
          localq.w = -285081600;
        }
        if (Math.abs(localq.w + 281280512) + Math.abs(localq.x - 235274240) < 19660800) {
          n = 32;
        }
        return;
      }
      break;
    case 3: 
      if (I[2] == 0)
      {
        if (Math.abs(localq.w + 274595840) + Math.abs(localq.x - 117964800) < 19660800) {
          n = 1;
        }
        return;
      }
      if (Q[39] == 10)
      {
        if (localq.w > 6553600) {
          localq.w = 6553600;
        }
        if (Math.abs(localq.w + 274595840) + Math.abs(localq.x + 9961472) < 19660800) {
          n = 39;
        }
      }
      return;
    case 4: 
      if (Q[15] == 10)
      {
        if ((localq.B == 13) && (localq.x > -134348800)) {
          localq.x = -134348800;
        }
        if (Math.abs(localq.w - 88473600) + Math.abs(localq.x - 38666240) < 19660800) {
          n = 15;
        }
      }
      if (Q[30] == 10)
      {
        if ((localq.B == 29) && (localq.x < 108134400)) {
          localq.x = 108134400;
        }
        if (Math.abs(localq.w) + Math.abs(localq.x - 108134400) < 19660800) {
          n = 30;
        }
        return;
      }
      if ((I[2] == 0) && (Math.abs(localq.w - 4390912) + Math.abs(localq.x - 655360) < 19660800)) {
        n = -1;
      }
      return;
    case 5: 
      if (Q[18] == 10)
      {
        if (((localq.B == 13) || (localq.B == 23)) && (localq.w > 68812800)) {
          localq.w = 68812800;
        }
        if (Math.abs(localq.w + 16384000) + Math.abs(localq.x - 59441152) + Math.abs(localq.y - 46923776) < 19660800) {
          n = 18;
        }
        return;
      }
      break;
    case 6: 
      if (I[2] == 0)
      {
        if (Math.abs(localq.w - 78643200) + Math.abs(localq.x - 274595840) + Math.abs(localq.y - 65536000) < 19660800) {
          n = -1;
        }
        return;
      }
      break;
    case 8: 
      if (I[2] == 0)
      {
        if (Math.abs(localq.w - 39321600) + Math.abs(localq.x + 472514560) < 19660800) {
          n = -1;
        }
        return;
      }
      break;
    case 9: 
      if ((I[2] == 0) && (Math.abs(localq.w - 77987840) + Math.abs(localq.x + 373555200) < 19660800)) {
        n = -1;
      }
      if (Q[44] == 10)
      {
        if ((localq.B == 45) && (localq.x < -522649600)) {
          localq.x = -522649600;
        }
        if (Math.abs(localq.w + 9240576) + Math.abs(localq.x + 530186240) < 19660800) {
          n = 44;
        }
      }
      if (b != 0)
      {
        if (Math.abs(localq.w + 29818880) + Math.abs(localq.x + 294256640) < 19660800) {
          n = 100;
        }
        return;
      }
      break;
    case 10: 
      if ((I[2] == 0) && (Math.abs(localq.w) + Math.abs(localq.x - 77660160) < 19660800)) {
        n = -1;
      }
      if ((I[5] == 0) && (Math.abs(localq.w - 176291840) + Math.abs(localq.x + 265420800) < 19660800)) {
        n = -2;
      }
      if ((I[8] == 0) && (Math.abs(localq.w + 176291840) + Math.abs(localq.x + 265420800) < 19660800)) {
        n = -3;
      }
      if (Q[42] == 10)
      {
        if ((localq.B == 41) && (localq.w < -104857600)) {
          localq.w = -104857600;
        }
        if (Math.abs(localq.w + 28835840) + Math.abs(localq.x - 933888000) < 19660800) {
          n = 42;
        }
      }
      if (Q[45] == 10)
      {
        if ((localq.B == 41) && (localq.x > 792985600)) {
          localq.x = 792985600;
        }
        if (Math.abs(localq.w - 206438400) + Math.abs(localq.x - 737280000) < 19660800) {
          n = 45;
        }
        return;
      }
      break;
    case 11: 
      for (int i1 = 0; i1 < 11; i1++) {
        if (((I[(2 + i1 * 3)] == 0) || (I[(2 + i1 * 3)] == -1)) && (Math.abs(localq.w - (aM[(i1 * 3)] << 16)) + Math.abs(localq.x - (aM[(i1 * 3 + 1)] << 16)) + Math.abs(localq.y - (aM[(i1 * 3 + 2)] << 16)) < 19660800)) {
          n = (byte)-(i1 + 1);
        }
      }
      if (n == 0) {
        for (i1 = 5; i1 < 10; i1++) {
          if (((I[(2 + i1 * 3)] == 0) || (I[(2 + i1 * 3)] == 1)) && (Math.abs(localq.w - (aM[(i1 * 3 + 15)] << 16)) + Math.abs(localq.x - (aM[(i1 * 3 + 1 + 15)] << 16)) + Math.abs(localq.y - (aM[(i1 * 3 + 2 + 15)] << 16)) < 19660800)) {
            n = (byte)i1;
          }
        }
      }
      if ((Q[65] == 10) && (localq.B == 39) && (localq.w > 128450560)) {
        localq.w = 128450560;
      }
      if (((b & 0x1) == 0) && (Math.abs(localq.w - 30277632) + Math.abs(localq.x + 18612224) + Math.abs(localq.y - 660471808) < 19660800)) {
        n = 64;
      }
      if (((b & 0x2) == 0) && (Math.abs(localq.w + 29294592) + Math.abs(localq.x + 39714816) + Math.abs(localq.y - 660471808) < 19660800)) {
        n = 65;
      }
      break;
    }
  }
  
  private static int a(short[] paramArrayOfShort1, short[] paramArrayOfShort2, int paramInt1, int paramInt2, i parami)
  {
    int i1 = (parami.l >> 16) - (paramArrayOfShort1[paramArrayOfShort2[paramInt1]] + paramArrayOfShort1[paramArrayOfShort2[(paramInt1 + 1)]] + paramArrayOfShort1[paramArrayOfShort2[(paramInt1 + 2)]]) / 3;
    paramArrayOfShort1 = (parami.m >> 16) - (paramArrayOfShort1[(paramArrayOfShort2[paramInt1] + 1)] + paramArrayOfShort1[(paramArrayOfShort2[(paramInt1 + 1)] + 1)] + paramArrayOfShort1[(paramArrayOfShort2[(paramInt1 + 2)] + 1)]) / 3;
    if ((paramArrayOfShort1 = (int)(65536L * (i1 * i1 + paramArrayOfShort1 * paramArrayOfShort1) >> 28)) > 255) {
      paramArrayOfShort1 = 255;
    }
    if (paramInt2 += 255 - paramArrayOfShort1 > 255) {
      paramInt2 = 255;
    }
    return paramInt2;
  }
  
  static final boolean t()
  {
    if (s.y >= 12)
    {
      w.n = 29;
      w.h = true;
      s.d = true;
      return true;
    }
    s.D[(s.y - 1)] = s.C;
    s.y = (byte)(s.y + 1);
    if ((p) && ((s.y == 6) || (s.y == 7))) {
      s.y = 8;
    }
    if (s.A < s.y) {
      s.A = s.y;
    }
    b(true, false);
    w.h = true;
    s.d = true;
    w.l = true;
    w.t = 0;
    g();
    w.t = 0;
    b(s.y);
    w.b();
    w.n = 2;
    w.l = false;
    w.h = false;
    s.d = false;
    return false;
  }
  
  static final boolean u()
  {
    boolean bool = false;
    if (X == bg[0])
    {
      if (s.y == 6)
      {
        if (Math.abs(-345178112 - ab[0]) + Math.abs(-1060110336 - ab[1]) < 32768000) {
          t();
        }
        return false;
      }
      if (s.y == 7)
      {
        if (Math.abs(-967966720 - ab[0]) + Math.abs(-452198400 - ab[1]) < 32768000) {
          t();
        }
        return false;
      }
      if (!p) {
        bool = t();
      } else {
        s.M = 2;
      }
    }
    return bool;
  }
  
  static void v()
  {
    if ((a < m.length) && (i[0].B == m[a]))
    {
      an = (byte)(an + 1);
      a = (byte)(a + 1);
    }
  }
  
  public static final void w()
  {
    c[] arrayOfc = g;
    Object localObject = null;
    i[] arrayOfi = e;
    for (int i1 = 0; i1 < Y; i1++)
    {
      c localc;
      if (((localc = arrayOfc[i1]).c - localc.o == 2) && (Q[i1] != 10))
      {
        i locali;
        if (((locali = arrayOfi[localc.o]).s <= 2) || (locali.s >= 7))
        {
          if ((locali.s <= 33) || (locali.s >= 38)) {
            continue;
          }
          if (locali.s == 34)
          {
            locali = arrayOfi[localc.o];
            localObject = arrayOfi[(localc.o + 1)];
          }
          if (locali.s == 35)
          {
            localObject = arrayOfi[localc.o];
            locali = arrayOfi[(localc.o + 1)];
          }
          if (locali.s == 36)
          {
            localObject = arrayOfi[localc.o];
            locali = arrayOfi[(localc.o + 1)];
          }
          if (locali.s == 37)
          {
            locali = arrayOfi[localc.o];
            localObject = arrayOfi[(localc.o + 1)];
          }
        }
        else if ((arrayOfi[localc.o].s == 3) || (arrayOfi[localc.o].s == 5))
        {
          localObject = arrayOfi[(localc.o + 1)];
          locali = arrayOfi[localc.o];
        }
        else
        {
          locali = arrayOfi[(localc.o + 1)];
          localObject = arrayOfi[localc.o];
        }
        int i4;
        int i3;
        if ((((i)localObject).s == 34) || (((i)localObject).s == 35))
        {
          i4 = ((i)localObject).m;
          i3 = 2;
        }
        else if (((i)localObject).s > 10)
        {
          i4 = ((i)localObject).l;
          i3 = 2;
        }
        else
        {
          i4 = ((i)localObject).n;
          i3 = 1;
        }
        int i2;
        if (a(localc))
        {
          if (i4 -= 1310720 >> 16 < bb[i1] - i3 * 300)
          {
            i2 = i4 = (bb[i1] << 16) - i3 * 19660800;
            i3 = i4 + i3 * 9830400;
          }
          else
          {
            i3 = (i2 = i4) + i3 * 9830400;
          }
        }
        else if (i4 += 1310720 >> 16 > bb[i1] - i3 * 150)
        {
          i2 = i4 = (bb[i1] << 16) - i3 * 9830400;
          i3 = i4 + i3 * 9830400;
        }
        else
        {
          i3 = (i2 = i4) + i3 * 9830400;
        }
        if ((((i)localObject).s == 34) || (((i)localObject).s == 35))
        {
          ((i)localObject).i = i2;
          ((i)localObject).f = i3;
          ((i)localObject).m = i4;
          i4 = locali.m;
          i3 = 2;
        }
        else if (((i)localObject).s > 10)
        {
          ((i)localObject).h = i2;
          ((i)localObject).e = i3;
          ((i)localObject).l = i4;
          i4 = locali.l;
          i3 = 2;
        }
        else
        {
          ((i)localObject).j = i2;
          ((i)localObject).g = i3;
          ((i)localObject).n = i4;
          i4 = locali.n;
          i3 = 1;
        }
        if (Q[i1] >= 0) {
          Q[i1] = 0;
        }
        if (a(localc))
        {
          if (i4 += 1310720 >> 16 > bb[i1])
          {
            i2 = i4 = bb[i1] << 16;
            i3 = i4 + i3 * 9830400;
          }
          else
          {
            i3 = (i2 = i4) + i3 * 9830400;
          }
        }
        else if (i4 -= 1310720 >> 16 < bb[i1] - i3 * 150)
        {
          i2 = i4 = (bb[i1] << 16) - i3 * 9830400;
          i3 = i4 + i3 * 9830400;
          if (Q[i1] >= 0) {
            Q[i1] = 1;
          }
        }
        else
        {
          i3 = (i2 = i4) + i3 * 9830400;
        }
        if ((((i)localObject).s == 34) || (((i)localObject).s == 35))
        {
          locali.i = i2;
          locali.f = i3;
          locali.m = i4;
        }
        else if (((i)localObject).s > 10)
        {
          locali.h = i2;
          locali.e = i3;
          locali.l = i4;
        }
        else
        {
          locali.j = i2;
          locali.g = i3;
          locali.n = i4;
        }
      }
    }
  }
  
  static final void x()
  {
    if ((!i[0].k) && ((aq = (short)(aq + 2)) >= 17))
    {
      aq = 0;
      q tmp35_34 = i[0];
      tmp35_34.s = ((short)(tmp35_34.s + 1));
      if (i[0].s > 100) {
        i[0].s = 100;
      }
    }
  }
  
  private static void g(q paramq)
  {
    if (paramq.m == -1) {
      paramq.z = ((byte)(paramq.z + bh[paramq.O]));
    } else {
      paramq.z = ((byte)(paramq.z + bh[3]));
    }
    if (paramq.z > 15) {
      paramq.z = 15;
    }
  }
  
  static final void y()
  {
    if (bi > 0)
    {
      bi = (byte)(bi - 1);
      if ((aC = (byte)(aC + 1)) >= 4) {
        aC = 4;
      }
      if ((aj == 1) && (ap[5] != null)) {
        aC = 0;
      }
      if ((aj == 3) && (ap[7] != null)) {
        aC = 0;
      }
    }
  }
  
  private static void k(int paramInt)
  {
    s.C = 0;
    G = 0;
    w.k = 0;
    w.d = 0;
    w.v = 5;
    w.r = 0;
    w.j = 0;
    w.p = false;
    bz = 0;
    s.I = 5;
    if (s.b != null)
    {
      int i1 = s.b.e.length;
      for (int i2 = 0; i2 < i1; i2++)
      {
        s.b.e[i2] = 0;
        s.b.d[i2] = 0;
      }
    }
    F = -1;
    z = -1;
    n = 0;
    an = 0;
    a = 1;
    s.k = 0;
    aY = 0;
    s.F = 0;
    s.K = 0;
    M = 0;
    bs = (short)((bD = (short)((aZ = (short)i.length) + N)) + 15);
    if (paramInt != 0) {
      v.c();
    }
    J = false;
    bF = 0;
    ad = 0;
    ai = new int[3];
    bi = 0;
    ak = 255;
    E = 0;
    aq = 0;
  }
  
  public static final void c(int paramInt)
  {
    s.M = 0;
    s.J = false;
    s.I = 5;
    s.e = false;
    w.l = true;
    w.t = 0;
    g = null;
    w.i.c(10);
    f = null;
    w.i.c(20);
    i = null;
    w.i.c(40);
    d = null;
    w.i.c(50);
    e = null;
    w.i.c(60);
    ai = null;
    bE = null;
    ai = new int[3];
    ac = new int[50][13];
    bE = new int[15][6];
    O();
    w.i.c(65);
    i(paramInt);
    w.i.c(70);
    i[0].F = 1;
    Q();
    P();
    w.i.c(80);
    N();
    w.i.c(90);
    J();
    k(paramInt);
    w.i.c(100);
    a(true, false);
    w.i.c(101);
    s.y = (byte)paramInt;
    if (w.g) {
      for (paramInt = 1; paramInt < 7; paramInt++)
      {
        l[paramInt] = aQ[paramInt];
        k[paramInt] = aP[paramInt];
        by[paramInt] = 1;
      }
    }
    if (p)
    {
      v.e();
      if (!l.a)
      {
        s.b.e[1] = 1;
        l.h = false;
        s.J = true;
      }
    }
    w.l = false;
    s.d = false;
    w.h = false;
  }
  
  static final void z()
  {
    if ((bk = (short)(bk + 6)) >= 360) {
      bk = (short)(bk - 360);
    }
  }
  
  static final void b(boolean paramBoolean1, boolean paramBoolean2)
  {
    if (paramBoolean2)
    {
      p.a[0] = ((byte)y.c);
      p.a[1] = (s.g ? 1 : 0);
      p.a[2] = (s.r ? 0 : 1);
      p.a[3] = (s.h ? 1 : 0);
      p.a[11] = s.E;
      p.a[12] = (s.n ? 0 : 1);
      p.a[13] = (s.m ? 0 : 1);
      if (s.H) {
        p.a[15] = 1;
      } else {
        p.a[15] = 0;
      }
      if (s.L) {
        p.a[16] = 1;
      } else {
        p.a[16] = 0;
      }
    }
    p.a[19] = ((byte)s.A);
    if (p.a[19] > 15) {
      p.a[19] = 15;
    }
    if (paramBoolean1)
    {
      p.a[17] = s.y;
      p.a[18] = r.a;
      p.a[20] = s.j;
      if (s.h) {
        p.a[21] = 1;
      } else {
        p.a[21] = 0;
      }
      int i1 = 1;
      paramBoolean1 = 22 + 18 * (s.y - 1);
      p.a[paramBoolean1] = r.a;
      paramBoolean1++;
      p.a[paramBoolean1] = 0;
      for (paramBoolean2 = false; paramBoolean2 < true; paramBoolean2++)
      {
        boolean tmp273_272 = paramBoolean1;
        byte[] tmp273_269 = p.a;
        tmp273_269[tmp273_272] = ((byte)(tmp273_269[tmp273_272] | (by[paramBoolean2] == 0 ? 0 : i1)));
        i1 <<= 1;
      }
      paramBoolean1++;
      for (paramBoolean2 = false; paramBoolean2 < true; paramBoolean2++)
      {
        p.a[paramBoolean1] = l[paramBoolean2];
        paramBoolean1++;
      }
      for (paramBoolean2 = false; paramBoolean2 < true; paramBoolean2++)
      {
        p.a[paramBoolean1] = k[paramBoolean2];
        paramBoolean1++;
      }
      p.a[paramBoolean1] = bz;
      paramBoolean1++;
      p.a[paramBoolean1] = ((byte)aj);
      paramBoolean1++;
      for (paramBoolean2 = false; paramBoolean2 < s.D.length; paramBoolean2++)
      {
        p.a[paramBoolean1] = ((byte)(s.D[paramBoolean2] >> 8 & 0xFF));
        p.a[(paramBoolean1 + true)] = ((byte)s.D[paramBoolean2]);
        paramBoolean1 += 2;
      }
    }
    p.c = true;
    p.b();
  }
  
  public static final void A()
  {
    a(e[z], Z, aa, X);
  }
  
  public static final void B()
  {
    if (bt > 0) {
      bt = (byte)(bt - 1);
    }
  }
  
  static final void a(i parami, int paramInt1, int paramInt2, int paramInt3)
  {
    int[] arrayOfInt1 = aG;
    int[] arrayOfInt2 = aI;
    h.a(ai, h.a(paramInt1, 10), h.a(paramInt2, 10));
    arrayOfInt2[0] = (parami.l + ai[0]);
    arrayOfInt2[1] = (parami.m + ai[1]);
    arrayOfInt2[2] = (parami.n + ai[2]);
    arrayOfInt1[0] = 0;
    arrayOfInt1[1] = paramInt3;
    arrayOfInt1[2] = (0x7F00 | bw[1]);
    arrayOfInt1[3] = bx[1];
    parami = bu[1] << 8 | 0x3;
    if (aj == 5) {
      parami = bu[1] << 8 | 0x4;
    }
    arrayOfInt1[4] = parami;
    arrayOfInt1[5] = (paramInt1 << 16 | paramInt2);
    h.a(arrayOfInt2, ai, arrayOfInt1);
  }
  
  static final void d(q paramq)
  {
    int[] arrayOfInt1 = aG;
    int[] arrayOfInt2 = aI;
    h.a(ai, h.a(paramq.C, paramq.z), h.a(paramq.D, paramq.z));
    g(paramq);
    if (paramq.M == 3)
    {
      paramq.j = -1;
      paramq.L = ((byte)(2 + (paramq.u & 0x1)));
    }
    arrayOfInt2[0] = (paramq.w + ai[0]);
    arrayOfInt2[1] = (paramq.x + ai[1]);
    arrayOfInt2[2] = (paramq.y + 2293760 + ai[2]);
    b(paramq);
    arrayOfInt1[0] = (paramq.O == 4 ? 1 : 0);
    arrayOfInt1[1] = paramq.B;
    arrayOfInt1[2] = (paramq.n << 8 | bw[paramq.O]);
    arrayOfInt1[3] = bx[paramq.O];
    int i1 = bu[paramq.O] << 8 | 0x3;
    if (aj == 5) {
      i1 = bu[paramq.O] << 8 | 0x4;
    }
    arrayOfInt1[4] = i1;
    arrayOfInt1[5] = (paramq.C << 16 | paramq.D);
    h.a(arrayOfInt2, ai, arrayOfInt1);
    if (paramq.O == 2)
    {
      h.a(ai, h.a(paramq.C, paramq.z + 3), h.a(paramq.D, paramq.z + 3));
      h.a(arrayOfInt2, ai, arrayOfInt1);
      h.a(ai, h.a(paramq.C, paramq.z + 3), h.a(paramq.D, paramq.z + 3));
      h.a(arrayOfInt2, ai, arrayOfInt1);
    }
  }
  
  public static final void C()
  {
    if ((aj == 0) && (i[0].m == -1)) {
      return;
    }
    if ((bt == 0) && (aC == 0) && (bi == 0))
    {
      q localq;
      if ((localq = i[0]).m == -1)
      {
        if (aj != 0)
        {
          i2 = aj;
          if (aQ[i2] > k[i2])
          {
            l[i2] = k[i2];
            k[i2] = 0;
          }
          else
          {
            int tmp117_116 = i2;
            byte[] tmp117_113 = k;
            tmp117_113[tmp117_116] = ((byte)(tmp117_113[tmp117_116] - aQ[i2]));
            l[i2] = aQ[i2];
          }
          bi = 20;
          int tmp150_149 = i2;
          byte[] tmp150_146 = l;
          tmp150_146[tmp150_149] = ((byte)(tmp150_146[tmp150_149] - 1));
          if ((l[i2] == 0 ? 0 : k[i2] == 0 ? 0 : 1) == 0) {
            return;
          }
        }
      }
      else {
        localq = i[i[0].m];
      }
      int i1 = aj;
      if (localq.m != -1) {
        i1 = 3;
      }
      s.g(i1);
      bt = r[i1];
      h.a(ai, h.a(Z, i[0].z), h.a(aa, i[0].z));
      g(i[0]);
      if ((bC = (byte)(bC + (-Math.abs(aV.nextInt() & 0xF) - 16))) < -40) {
        bC = -40;
      }
      if (bC > 40) {
        bC = 40;
      }
      int i2 = 1;
      if ((aj != 4) && ((aV.nextInt() & 0x1) == 0)) {
        i2 = -1;
      }
      if ((bB = (byte)(bB + i2 * ((aV.nextInt() & 0xF) + 16))) < -70) {
        bB = -70;
      }
      if (bB > 70) {
        bB = 70;
      }
      int[] arrayOfInt;
      (arrayOfInt = aG)[0] = (i1 == 4 ? 1 : 0);
      arrayOfInt[1] = i[0].B;
      arrayOfInt[2] = (localq.n << 8 | bw[i1]);
      arrayOfInt[3] = bx[i1];
      int i3 = bu[i1] << 8 | 0x3;
      if (i1 == 5) {
        i3 = bu[i1] << 8 | 0x4;
      }
      arrayOfInt[4] = i3;
      arrayOfInt[5] = (Z << 16 | aa);
      h.a(ab, ai, arrayOfInt);
      if (i1 == 2)
      {
        h.a(ai, h.a(Z, i[0].z + 3), h.a(aa, i[0].z + 3));
        h.a(ab, ai, arrayOfInt);
        h.a(ai, h.a(Z, i[0].z + 3), h.a(aa, i[0].z + 3));
        h.a(ab, ai, arrayOfInt);
      }
      bN = localq.w;
      bO = localq.x;
      bP = localq.y;
      v = true;
    }
  }
  
  public static final void D()
  {
    if ((bB > 0) && ((bB = (byte)(bB - 5)) < 0)) {
      bB = 0;
    }
    if ((bB < 0) && ((bB = (byte)(bB + 5)) > 0)) {
      bB = 0;
    }
    if ((bC > 0) && ((bC = (byte)(bC - 5)) < 0)) {
      bC = 0;
    }
    if ((bC < 0) && ((bC = (byte)(bC + 5)) > 0)) {
      bC = 0;
    }
  }
  
  public static final void e(q paramq)
  {
    if (paramq.z > 0) {
      paramq.z = ((byte)(paramq.z - 1));
    }
  }
  
  static final void E()
  {
    if ((aC > 0) && (bi == 0) && ((aC = (byte)(aC - 1)) == 4)) {
      aj = aD;
    }
  }
  
  public static final void F()
  {
    i[] arrayOfi = e;
    q[] arrayOfq = i;
    Object localObject;
    for (int i2 = 0; i2 < N; i2++) {
      if ((localObject = arrayOfi[i2]).s == 29)
      {
        localObject.o += b;
        if (((i)localObject).o > 359) {
          localObject.o -= 360;
        }
      }
    }
    for (i2 = 0; i2 < ah; i2++) {
      if ((!(localObject = arrayOfq[i2]).k) && (((q)localObject).y > 111411200) && (((q)localObject).y < 131072000) && (((q)localObject).w > -137625600) && (((q)localObject).w < 275251200))
      {
        int i4 = (((q)localObject).w >> 16) - 1800;
        int i5 = (((q)localObject).x >> 16) + 3300;
        int i3;
        if ((i3 = i4 * i4 + i5 * i5) < 15210000)
        {
          int i6 = 1073741824;
          int i1 = 0;
          while (i6 != 0)
          {
            int i7 = i1 | i6;
            i1 >>= 1;
            if (i3 >= i7)
            {
              i3 -= i7;
              i1 |= i6;
            }
            i6 >>= 2;
          }
          if ((i1 < 30) || (((q)localObject).w > 117964800))
          {
            ((q)localObject).k = true;
            ((q)localObject).L = 7;
            ((q)localObject).j = 0;
            ((q)localObject).s = -100;
            a((q)localObject, true);
          }
          else
          {
            ((q)localObject).g[0] -= (i4 << 16) / i1 * (3900 - i1 >> 7);
            ((q)localObject).g[1] -= (i5 << 16) / i1 * (3900 - i1 >> 7);
          }
        }
      }
    }
  }
  
  static final void d(int paramInt)
  {
    paramInt = i[0];
    q[] arrayOfq = i;
    if ((s.y == 7) || (s.y == 6)) {
      for (int i1 = 0; i1 < ah; i1++)
      {
        q localq;
        if ((arrayOfq[i1].M == 3) && ((localq = arrayOfq[i1]).m == -1) && (Math.abs(localq.w - paramInt.w >> 16) + Math.abs(localq.x - paramInt.x >> 16) + Math.abs(localq.y - paramInt.y >> 16) < 400))
        {
          paramInt.m = ((byte)i1);
          localq.m = 0;
          localq.N = false;
          paramInt.N = false;
          aY = 15;
          return;
        }
      }
    }
  }
  
  static final void G()
  {
    if ((bn = bn - 2) < 180) {
      bn = 180;
    }
  }
  
  static final void H()
  {
    if ((bn = bn + 2) > 359) {
      bn = 359;
    }
  }
  
  static final void e(int paramInt)
  {
    bI = true;
    if ((bl = bl + (paramInt + 2)) > 5 << paramInt) {
      bl = 5 << paramInt;
    }
  }
  
  static final void f(int paramInt)
  {
    bH = true;
    if (s.r) {
      bm -= paramInt + 1;
    }
    if (bm < -5 << paramInt)
    {
      bm = -5 << paramInt;
      return;
    }
    if ((aa = aa - paramInt) < 0) {
      aa += 360;
    }
  }
  
  static final void g(int paramInt)
  {
    bH = true;
    if (s.r) {
      bm += paramInt + 1;
    }
    if (bm > 5 << paramInt)
    {
      bm = 5 << paramInt;
      return;
    }
    if ((aa = aa + paramInt) > 359) {
      aa -= 360;
    }
  }
  
  static final void h(int paramInt)
  {
    bI = true;
    if ((bl = bl - (paramInt + 2)) < -5 << paramInt) {
      bl = -5 << paramInt;
    }
  }
  
  static void f(q paramq)
  {
    paramq.p = 0;
    paramq.q = 0;
    paramq.k = false;
    paramq.N = true;
    paramq.i = true;
    paramq.P = false;
    paramq.s = H[paramq.M];
    paramq.a = 0;
    paramq.L = 0;
    paramq.j = 0;
    paramq.h = 0;
    paramq.l = -1;
  }
  
  static void I()
  {
    for (int i1 = 1; i1 < 7; i1++)
    {
      by[i1] = 0;
      l[i1] = 0;
      k[i1] = 0;
    }
    aj = 0;
  }
}


/* Location:              E:\NET Lizard\3D射击\clone_3d_nokia_s40_3_240x320修正更新.jar!\g.class
 * Java compiler version: 4 (48.0)
 * JD-Core Version:       0.7.1
 */